{
  "type": "Feature",
  "properties": {
    "addr:full":"450 Holly Springs Rd Timberlake NC 27540",
    "addr:housenumber":"450",
    "addr:postcode":"27540",
    "addr:street":"Holly Springs Rd",
    "iso:country":"US",
    "sg:address":"450 Holly Springs Rd",
    "sg:city":"Timberlake",
    "sg:classifiers":[
        {
            "category":"Professional",
            "subcategory":"Business Services",
            "type":"Services"
        },
        {
            "category":"Building & Trades",
            "subcategory":"Construction",
            "type":"Services"
        }
    ],
    "sg:phone":"+1 336 364 1781",
    "sg:postcode":"27540",
    "sg:province":"NC",
    "sg:tags":[
        "restoration",
        "cleaning",
        "patio",
        "deck"
    ],
    "wof:name":"Barnette's Pro Wash",
    "wof:placetype":"venue"
},
  "geometry": {"coordinates":[-78.82935500000001,35.654726],"type":"Point"}
}