{
  "type": "Feature",
  "properties": {
    "iso:country":"US",
    "sg:address":"420 Idlebrook Dr",
    "sg:city":"Kernersville",
    "sg:classifiers":[
        {
            "category":"Shopping",
            "subcategory":"Hobbies, Toys, & Games",
            "type":"Retail Goods"
        }
    ],
    "sg:phone":"+1 336 993 5120",
    "sg:postcode":"27284",
    "sg:province":"NC",
    "sg:tags":[
        "model",
        "supply"
    ],
    "wof:name":"Hot Shots",
    "wof:placetype":"venue"
},
  "geometry": {"coordinates":[-80.042755,36.099375],"type":"Point"}
}