{
  "type": "Feature",
  "properties": {
    "iso:country":"US",
    "sg:address":"803 Wismar Ct",
    "sg:city":"Charlotte",
    "sg:classifiers":[
        {
            "category":"Professional",
            "subcategory":"Business Services",
            "type":"Services"
        }
    ],
    "sg:phone":"+1 704 517 7350",
    "sg:postcode":"28270",
    "sg:province":"NC",
    "sg:tags":[
        "organizing"
    ],
    "wof:name":"Organizing Pro",
    "wof:placetype":"venue"
},
  "geometry": {"coordinates":[-80.768621,35.106189],"type":"Point"}
}