{
  "type": "Feature",
  "properties": {
    "iso:country":"US",
    "sg:address":"1536 Haywood Rd",
    "sg:city":"Hendersonville",
    "sg:classifiers":[
        {
            "category":"Home & Garden",
            "subcategory":"Home Furnishings",
            "type":"Retail Goods"
        }
    ],
    "sg:phone":"+1 828 696 2208",
    "sg:postcode":"28791",
    "sg:province":"NC",
    "sg:tags":[
        "curtain",
        "made",
        "drapery"
    ],
    "wof:name":"Acorn Creek Interiors-Furnish",
    "wof:placetype":"venue"
},
  "geometry": {"coordinates":[-82.471284,35.328546],"type":"Point"}
}