{
  "type": "Feature",
  "properties": {
    "addr:full":"3827 Landsford Rd Marshville NC 28103",
    "addr:housenumber":"3827",
    "addr:postcode":"28103",
    "addr:street":"Landsford Rd",
    "iso:country":"US",
    "sg:address":"3827 Landsford Rd",
    "sg:city":"Marshville",
    "sg:classifiers":[
        {
            "category":"Professional",
            "subcategory":"Management & Consulting",
            "type":"Services"
        }
    ],
    "sg:phone":"+1   ",
    "sg:postcode":"28103",
    "sg:province":"NC",
    "sg:tags":[
        "business"
    ],
    "wof:name":"Spring Hollow Farm",
    "wof:placetype":"venue"
},
  "geometry": {"coordinates":[-80.332899,34.89122],"type":"Point"}
}