{
  "type": "Feature",
  "properties": {
    "addr:full":"205 Anderson St Elm City NC 27822",
    "addr:housenumber":"205",
    "addr:postcode":"27822",
    "addr:street":"Anderson St",
    "iso:country":"US",
    "sg:address":"205 Anderson St",
    "sg:city":"Elm City",
    "sg:classifiers":[
        {
            "category":"Insurance",
            "subcategory":"Insurance Agent",
            "type":"Services"
        }
    ],
    "sg:phone":"+1 252 236 4447",
    "sg:postcode":"27822",
    "sg:province":"NC",
    "wof:name":"AFLAC",
    "wof:placetype":"venue"
},
  "geometry": {"coordinates":[-77.865216,35.805321],"type":"Point"}
}