{
  "type": "Feature",
  "properties": {
    "addr:full":"511 Nelson St Kernersville NC 27284",
    "addr:housenumber":"511",
    "addr:postcode":"27284",
    "addr:street":"Nelson St",
    "iso:country":"US",
    "sg:address":"511 Nelson St",
    "sg:city":"Kernersville",
    "sg:classifiers":[
        {
            "category":"Professional",
            "subcategory":"Accounting & Tax Preparation",
            "type":"Services"
        }
    ],
    "sg:phone":"+1 336 993 9636",
    "sg:postcode":"27284",
    "sg:province":"NC",
    "sg:tags":[
        "return",
        "filing"
    ],
    "wof:name":"Jackson Hewitt Tax Svc",
    "wof:placetype":"venue"
},
  "geometry": {"coordinates":[-80.06891400000001,36.127331],"type":"Point"}
}