{
  "type": "Feature",
  "properties": {
    "iso:country":"US",
    "sg:address":"4510 Weybridge Ln",
    "sg:city":"Greensboro",
    "sg:classifiers":[
        {
            "category":"Utilities",
            "subcategory":"Cable",
            "type":"Services"
        }
    ],
    "sg:phone":"+1 336 665 0160",
    "sg:postcode":"27407",
    "sg:province":"NC",
    "sg:tags":[
        "administrative"
    ],
    "wof:name":"Time Warner",
    "wof:placetype":"venue"
},
  "geometry": {"coordinates":[-79.871527,35.995612],"type":"Point"}
}