{
  "type": "Feature",
  "properties": {
    "addr:full":"9493 Rocky River Rd Harrisburg NC 28075",
    "addr:housenumber":"9493",
    "addr:postcode":"28075",
    "addr:street":"Rocky River Rd",
    "iso:country":"US",
    "sg:address":"9493 Rocky River Rd",
    "sg:city":"Harrisburg",
    "sg:classifiers":[
        {
            "category":"Insurance",
            "subcategory":"Insurance Agent",
            "type":"Services"
        }
    ],
    "sg:phone":"+1 704 454 5098",
    "sg:postcode":"28075",
    "sg:province":"NC",
    "wof:name":"Travelers Insurance",
    "wof:placetype":"venue"
},
  "geometry": {"coordinates":[-80.659614,35.284143],"type":"Point"}
}