{
  "type": "Feature",
  "properties": {
    "iso:country":"US",
    "sg:address":"105 Ritter Dr",
    "sg:city":"Castle Hayne",
    "sg:classifiers":[
        {
            "category":"Professional",
            "type":"Services"
        }
    ],
    "sg:phone":"+1   ",
    "sg:postcode":"28429",
    "sg:province":"NC",
    "wof:name":"By Molly Creative Designs",
    "wof:placetype":"venue"
},
  "geometry": {"coordinates":[-77.925864,34.297953],"type":"Point"}
}