{
  "type": "Feature",
  "properties": {
    "addr:full":"1120 Thorpe Rd Rocky Mount NC 27804",
    "addr:housenumber":"1120",
    "addr:postcode":"27804",
    "addr:street":"Thorpe Rd",
    "iso:country":"US",
    "sg:address":"1120 Thorpe Rd",
    "sg:city":"Rocky Mount",
    "sg:classifiers":[
        {
            "category":"Retail",
            "subcategory":"Auto Repair",
            "type":"Services"
        }
    ],
    "sg:phone":"+1 252 442 0808",
    "sg:postcode":"27804",
    "sg:province":"NC",
    "sg:tags":[
        "repairing",
        "automobile",
        "radiator"
    ],
    "wof:name":"Eagle Radiator & Auto Repair",
    "wof:placetype":"venue"
},
  "geometry": {"coordinates":[-77.79550500000001,35.973159],"type":"Point"}
}