{
  "type": "Feature",
  "properties": {
    "iso:country":"US",
    "sg:address":"409 N 7th St",
    "sg:city":"Sanford",
    "sg:classifiers":[
        {
            "category":"Wholesale",
            "subcategory":"Durable Goods & Equipment",
            "type":"Manufacturing & Wholesale Goods"
        },
        {
            "category":"Professional",
            "subcategory":"Advertising",
            "type":"Services"
        }
    ],
    "sg:phone":"+1 919 774 1635",
    "sg:postcode":"27330",
    "sg:province":"NC",
    "sg:tags":[
        "distribution"
    ],
    "wof:name":"P M Distributors",
    "wof:placetype":"venue"
},
  "geometry": {"coordinates":[-79.16754400000001,35.487373],"type":"Point"}
}