{
  "type": "Feature",
  "properties": {
    "addr:full":"29 Page Ave Asheville NC 28801",
    "addr:housenumber":"29",
    "addr:postcode":"28801",
    "addr:street":"Page Ave",
    "iso:country":"US",
    "sg:address":"29 Page Ave",
    "sg:city":"Asheville",
    "sg:classifiers":[
        {
            "category":"Banks & Credit Unions",
            "subcategory":"Bank",
            "type":"Services"
        }
    ],
    "sg:phone":"+1 828 253 2834",
    "sg:postcode":"28801",
    "sg:province":"NC",
    "sg:tags":[
        "personal",
        "institution"
    ],
    "wof:name":"Mountain Microenterprise Fund",
    "wof:placetype":"venue"
},
  "geometry": {"coordinates":[-82.555987,35.59519],"type":"Point"}
}