{
  "type": "Feature",
  "properties": {
    "addr:full":"1129 Weaver Dairy Rd Chapel Hill NC 27514",
    "addr:housenumber":"1129",
    "addr:postcode":"27514",
    "addr:street":"Weaver Dairy Rd",
    "iso:country":"US",
    "sg:address":"1129 Weaver Dairy Rd",
    "sg:city":"Chapel Hill",
    "sg:classifiers":[
        {
            "category":"Retail",
            "subcategory":"Repair Shop",
            "type":"Services"
        },
        {
            "category":"Shopping",
            "subcategory":"Jewelry",
            "type":"Retail Goods"
        }
    ],
    "sg:phone":"+1 919 932 5083",
    "sg:postcode":"27514",
    "sg:province":"NC",
    "sg:tags":[
        "bu"
    ],
    "wof:name":"Wentworth & Sloan Jewelers Inc",
    "wof:placetype":"venue"
},
  "geometry": {"coordinates":[-79.055736,35.963934],"type":"Point"}
}