{
  "type": "Feature",
  "properties": {
    "addr:full":"3328 16th St NE Hickory NC 28601",
    "addr:housenumber":"3328",
    "addr:postcode":"28601",
    "addr:street":"16Th St Ne",
    "iso:country":"US",
    "sg:address":"3328 16th St NE",
    "sg:city":"Hickory",
    "sg:classifiers":[
        {
            "category":"Home & Garden",
            "subcategory":"Hardware",
            "type":"Retail Goods"
        }
    ],
    "sg:phone":"+1 828 256 5654",
    "sg:postcode":"28601",
    "sg:province":"NC",
    "wof:name":"JM Propst Inc",
    "wof:placetype":"venue"
},
  "geometry": {"coordinates":[-81.29579699999999,35.776208],"type":"Point"}
}