{
  "type": "Feature",
  "properties": {
    "addr:full":"225 N Salem St Apex NC 27502",
    "addr:housenumber":"225",
    "addr:postcode":"27502",
    "addr:street":"N Salem St",
    "iso:country":"US",
    "sg:address":"225 N Salem St",
    "sg:city":"Apex",
    "sg:classifiers":[
        {
            "category":"Manufacturing",
            "subcategory":"Printing",
            "type":"Manufacturing & Wholesale Goods"
        }
    ],
    "sg:phone":"+1 919 367 0273",
    "sg:postcode":"27502",
    "sg:province":"NC",
    "sg:tags":[
        "commercial",
        "design"
    ],
    "wof:name":"Earley & Assoc Comm Design",
    "wof:placetype":"venue"
},
  "geometry": {"coordinates":[-78.850792,35.731969],"type":"Point"}
}