{
  "type": "Feature",
  "properties": {
    "iso:country":"US",
    "sg:address":"1202 New Bethel Rd",
    "sg:city":"Garner",
    "sg:classifiers":[
        {
            "category":"Social Services",
            "subcategory":"Child Care",
            "type":"Services"
        }
    ],
    "sg:phone":"+1 919 772 8704",
    "sg:postcode":"27529",
    "sg:province":"NC",
    "sg:tags":[
        "day"
    ],
    "wof:name":"Thompson Preschool & Day Care",
    "wof:placetype":"venue"
},
  "geometry": {"coordinates":[-78.55834900000001,35.631305],"type":"Point"}
}