{
  "type": "Feature",
  "properties": {
    "addr:full":"314 S Jefferson Ave West Jefferson NC 28694",
    "addr:housenumber":"314",
    "addr:postcode":"28694",
    "addr:street":"S Jefferson Ave",
    "iso:country":"US",
    "sg:address":"314 S Jefferson Ave",
    "sg:city":"West Jefferson",
    "sg:classifiers":[
        {
            "category":"Building & Trades",
            "subcategory":"Construction",
            "type":"Services"
        }
    ],
    "sg:phone":"+1 336 246 4206",
    "sg:postcode":"28694",
    "sg:province":"NC",
    "sg:tags":[
        "general",
        "contractor"
    ],
    "wof:name":"River Rock Co",
    "wof:placetype":"venue"
},
  "geometry": {"coordinates":[-81.49133999999999,36.399468],"type":"Point"}
}