{
  "type": "Feature",
  "properties": {
    "addr:full":"952 High House Rd Cary NC 27513",
    "addr:housenumber":"952",
    "addr:postcode":"27513",
    "addr:street":"High House Rd",
    "iso:country":"US",
    "sg:address":"952 High House Rd",
    "sg:city":"Cary",
    "sg:classifiers":[
        {
            "category":"Shopping",
            "type":"Retail Goods"
        }
    ],
    "sg:phone":"+1 919 319 1776",
    "sg:postcode":"27513",
    "sg:province":"NC",
    "sg:tags":[
        "art",
        "gallery"
    ],
    "sg:website":"www.fastframe.com/Storelocations...",
    "wof:name":"Fastframe",
    "wof:placetype":"venue"
},
  "geometry": {"coordinates":[-78.827003,35.787399],"type":"Point"}
}