{
  "type": "Feature",
  "properties": {
    "iso:country":"US",
    "sg:address":"14021 Clarendon Pointe Ct",
    "sg:city":"Huntersville",
    "sg:classifiers":[
        {
            "category":"Professional",
            "subcategory":"Business Services",
            "type":"Services"
        }
    ],
    "sg:phone":"+1   ",
    "sg:postcode":"28078",
    "sg:province":"NC",
    "wof:name":"Huddleston Group Inc",
    "wof:placetype":"venue"
},
  "geometry": {"coordinates":[-80.934589,35.431641],"type":"Point"}
}