{
  "type": "Feature",
  "properties": {
    "addr:full":"4017 Hartley St Charlotte NC 28206",
    "addr:housenumber":"4017",
    "addr:postcode":"28206",
    "addr:street":"Hartley St",
    "iso:country":"US",
    "sg:address":"4017 Hartley St",
    "sg:city":"Charlotte",
    "sg:classifiers":[
        {
            "category":"Manufacturing",
            "subcategory":"Metals",
            "type":"Manufacturing & Wholesale Goods"
        }
    ],
    "sg:phone":"+1 704 596 3646",
    "sg:postcode":"28206",
    "sg:province":"NC",
    "sg:tags":[
        "steel",
        "fabricates",
        "iron"
    ],
    "wof:name":"Colonial Iron Works Inc",
    "wof:placetype":"venue"
},
  "geometry": {"coordinates":[-80.82002900000001,35.272457],"type":"Point"}
}