{
  "type": "Feature",
  "properties": {
    "addr:full":"510 Applecross Dr Cary NC 27511",
    "addr:housenumber":"510",
    "addr:postcode":"27511",
    "addr:street":"Applecross Dr",
    "iso:country":"US",
    "sg:address":"510 Applecross Dr",
    "sg:city":"Cary",
    "sg:classifiers":[
        {
            "category":"Arts & Performance",
            "subcategory":"Theater",
            "type":"Entertainment"
        }
    ],
    "sg:phone":"+1   ",
    "sg:postcode":"27511",
    "sg:province":"NC",
    "sg:tags":[
        "group"
    ],
    "wof:name":"First Class Djs",
    "wof:placetype":"venue"
},
  "geometry": {"coordinates":[-78.81532,35.757159],"type":"Point"}
}