{
  "type": "Feature",
  "properties": {
    "iso:country":"US",
    "sg:address":"204 S Walker St",
    "sg:city":"Burgaw",
    "sg:classifiers":[
        {
            "category":"Health Services",
            "subcategory":"Clinic",
            "type":"Services"
        }
    ],
    "sg:phone":"+1 910 259 1150",
    "sg:postcode":"28425",
    "sg:province":"NC",
    "sg:tags":[
        "home"
    ],
    "wof:name":"Liberty Home Care",
    "wof:placetype":"venue"
},
  "geometry": {"coordinates":[-77.924706,34.550166],"type":"Point"}
}