{
  "type": "Feature",
  "properties": {
    "addr:full":"2143 Statesville Blvd Salisbury NC 28147",
    "addr:housenumber":"2143",
    "addr:postcode":"28147",
    "addr:street":"Statesville Blvd",
    "iso:country":"US",
    "sg:address":"2143 Statesville Blvd",
    "sg:city":"Salisbury",
    "sg:classifiers":[
        {
            "category":"Manufacturing",
            "subcategory":"Furniture",
            "type":"Manufacturing & Wholesale Goods"
        }
    ],
    "sg:phone":"+1 704 281 3767",
    "sg:postcode":"28147",
    "sg:province":"NC",
    "sg:tags":[
        "mfg",
        "wood",
        "contractor",
        "carpentry"
    ],
    "wof:name":"Monongahela Fixture Co Inc",
    "wof:placetype":"venue"
},
  "geometry": {"coordinates":[-80.515542,35.694204],"type":"Point"}
}