{
  "type": "Feature",
  "properties": {
    "addr:full":"116 Bear St Moyock NC 27958",
    "addr:housenumber":"116",
    "addr:postcode":"27958",
    "addr:street":"Bear St",
    "iso:country":"US",
    "sg:address":"116 Bear St",
    "sg:city":"Moyock",
    "sg:classifiers":[
        {
            "category":"Professional",
            "subcategory":"Business Services",
            "type":"Services"
        }
    ],
    "sg:phone":"+1   ",
    "sg:postcode":"27958",
    "sg:province":"NC",
    "wof:name":"Stikes Products Svcs",
    "wof:placetype":"venue"
},
  "geometry": {"coordinates":[-76.253677,36.533732],"type":"Point"}
}