{
  "type": "Feature",
  "properties": {
    "iso:country":"US",
    "sg:address":"150 Forest Hill Rd",
    "sg:city":"Lexington",
    "sg:classifiers":[
        {
            "category":"Restaurant",
            "type":"Food & Drink"
        }
    ],
    "sg:menulink":"http://www.allmenus.com/nc/lexington/85419-dominos-pizza/menu/",
    "sg:phone":"+1 336 238 7272",
    "sg:postcode":"27295",
    "sg:province":"NC",
    "sg:tags":[
        "american",
        "wing",
        "pizza"
    ],
    "wof:name":"Domino's Pizza",
    "wof:placetype":"venue"
},
  "geometry": {"coordinates":[-80.27725,35.836551],"type":"Point"}
}