{
  "type": "Feature",
  "properties": {
    "addr:full":"510 W Center St Mebane NC 27302",
    "addr:housenumber":"510",
    "addr:postcode":"27302",
    "addr:street":"W Center St",
    "iso:country":"US",
    "sg:address":"510 W Center St",
    "sg:city":"Mebane",
    "sg:classifiers":[
        {
            "category":"Autos & Motor Vehicles",
            "subcategory":"Automobile Sales",
            "type":"Retail Goods"
        }
    ],
    "sg:phone":"+1 919 563 4116",
    "sg:postcode":"27302",
    "sg:province":"NC",
    "sg:tags":[
        "car",
        "dealer"
    ],
    "wof:name":"Weaver's Auto Sales",
    "wof:placetype":"venue"
},
  "geometry": {"coordinates":[-79.276008,36.097993],"type":"Point"}
}