{
  "type": "Feature",
  "properties": {
    "addr:full":"423 Pitts School Rd NW Concord NC 28027",
    "addr:housenumber":"423",
    "addr:postcode":"28027",
    "addr:street":"Pitts School Rd Nw",
    "iso:country":"US",
    "sg:address":"423 Pitts School Rd NW",
    "sg:city":"Concord",
    "sg:classifiers":[
        {
            "category":"Freight",
            "type":"Transportation"
        }
    ],
    "sg:phone":"+1 704 785 9171",
    "sg:postcode":"28027",
    "sg:province":"NC",
    "sg:tags":[
        "trucking"
    ],
    "sg:website":"www.jevic.com",
    "wof:name":"Jevic Transportation Inc",
    "wof:placetype":"venue"
},
  "geometry": {"coordinates":[-80.686661,35.383453],"type":"Point"}
}