{
  "type": "Feature",
  "properties": {
    "addr:full":"412 W State St Black Mountain NC 28711",
    "addr:housenumber":"412",
    "addr:postcode":"28711",
    "addr:street":"W State St",
    "iso:country":"US",
    "sg:address":"412 W State St",
    "sg:city":"Black Mountain",
    "sg:classifiers":[
        {
            "category":"Shopping",
            "subcategory":"Pharmacy",
            "type":"Retail Goods"
        }
    ],
    "sg:phone":"+1 828 669 2992",
    "sg:postcode":"28711",
    "sg:province":"NC",
    "wof:name":"CVS Pharmacy",
    "wof:placetype":"venue"
},
  "geometry": {"coordinates":[-82.325541,35.614321],"type":"Point"}
}