{
  "type": "Feature",
  "properties": {
    "iso:country":"US",
    "sg:address":"512 N Main St",
    "sg:city":"Roxboro",
    "sg:classifiers":[
        {
            "category":"Food & Beverages",
            "subcategory":"Fruits & Vegetables",
            "type":"Retail Goods"
        }
    ],
    "sg:phone":"+1 336 597 2992",
    "sg:postcode":"27573",
    "sg:province":"NC",
    "sg:tags":[
        "produce"
    ],
    "wof:name":"Riley's Produce",
    "wof:placetype":"venue"
},
  "geometry": {"coordinates":[-78.979659,36.40039],"type":"Point"}
}