{
  "type": "Feature",
  "properties": {
    "iso:country":"US",
    "sg:address":"382 Montford Ave",
    "sg:city":"Asheville",
    "sg:classifiers":[
        {
            "category":"Education",
            "subcategory":"College",
            "type":"Public Place"
        }
    ],
    "sg:phone":"+1 828 225 3993",
    "sg:postcode":"28801",
    "sg:province":"NC",
    "sg:tags":[
        "academic",
        "school"
    ],
    "sg:website":"www.daoisttraditions.com",
    "wof:name":"Daoist Traditions",
    "wof:placetype":"venue"
},
  "geometry": {"coordinates":[-82.57067600000001,35.607869],"type":"Point"}
}