{
  "type": "Feature",
  "properties": {
    "iso:country":"US",
    "sg:address":"2723 Olde Whitehall Rd",
    "sg:city":"Charlotte",
    "sg:classifiers":[
        {
            "category":"Shopping",
            "subcategory":"Crafts & Fabrics",
            "type":"Retail Goods"
        },
        {
            "category":"Manufacturing",
            "subcategory":"Glass & Minerals",
            "type":"Manufacturing & Wholesale Goods"
        }
    ],
    "sg:phone":"+1 704 525 8128",
    "sg:postcode":"28273",
    "sg:province":"NC",
    "sg:tags":[
        "glass-stained",
        "stained",
        "art",
        "supply",
        "leaded-commercial",
        "leaded"
    ],
    "wof:name":"Glass House Studio",
    "wof:placetype":"venue"
},
  "geometry": {"coordinates":[-80.928708,35.156191],"type":"Point"}
}