{
  "type": "Feature",
  "properties": {
    "addr:full":"7816 Wallace Ln Charlotte NC 28212",
    "addr:housenumber":"7816",
    "addr:postcode":"28212",
    "addr:street":"Wallace Ln",
    "iso:country":"US",
    "sg:address":"7816 Wallace Ln",
    "sg:city":"Charlotte",
    "sg:classifiers":[
        {
            "category":"Professional",
            "subcategory":"Management & Consulting",
            "type":"Services"
        }
    ],
    "sg:phone":"+1   ",
    "sg:postcode":"28212",
    "sg:province":"NC",
    "sg:tags":[
        "educational",
        "consultation",
        "representative"
    ],
    "wof:name":"Chongqing Fgn Trade Rprsnttive",
    "wof:placetype":"venue"
},
  "geometry": {"coordinates":[-80.740148,35.172185],"type":"Point"}
}