{
  "type": "Feature",
  "properties": {
    "addr:full":"1141 W Broad St St Pauls NC 28384",
    "addr:housenumber":"1141",
    "addr:postcode":"28384",
    "addr:street":"W Broad St",
    "iso:country":"US",
    "sg:address":"1141 W Broad St",
    "sg:city":"St Pauls",
    "sg:classifiers":[
        {
            "category":"Organizations",
            "subcategory":"Religious Organization",
            "type":"Services"
        }
    ],
    "sg:phone":"+1 910 865 2680",
    "sg:postcode":"28384",
    "sg:province":"NC",
    "sg:tags":[
        "church"
    ],
    "wof:name":"Calvary Holiness Church",
    "wof:placetype":"venue"
},
  "geometry": {"coordinates":[-78.991518,34.814634],"type":"Point"}
}