{
  "type": "Feature",
  "properties": {
    "iso:country":"US",
    "sg:address":"444 N Daughtry St",
    "sg:city":"Rocky Mount",
    "sg:classifiers":[
        {
            "category":"Insurance",
            "subcategory":"Hazard Insurance",
            "type":"Services"
        },
        {
            "category":"Professional",
            "subcategory":"Business Services",
            "type":"Services"
        }
    ],
    "sg:phone":"+1 252 977 7007",
    "sg:postcode":"27801",
    "sg:province":"NC",
    "sg:tags":[
        "bonding",
        "bail",
        "bond"
    ],
    "wof:name":"Holloways Bail Bonding Svcs",
    "wof:placetype":"venue"
},
  "geometry": {"coordinates":[-77.784498,35.941381],"type":"Point"}
}