{
  "type": "Feature",
  "properties": {
    "addr:full":"81 Elmwood Way Waynesville NC 28786",
    "addr:housenumber":"81",
    "addr:postcode":"28786",
    "addr:street":"Elmwood Way",
    "iso:country":"US",
    "sg:address":"81 Elmwood Way",
    "sg:city":"Waynesville",
    "sg:classifiers":[
        {
            "category":"Social Services",
            "type":"Services"
        }
    ],
    "sg:phone":"+1   ",
    "sg:postcode":"28786",
    "sg:province":"NC",
    "wof:name":"Friends Program The",
    "wof:placetype":"venue"
},
  "geometry": {"coordinates":[-82.987836,35.517895],"type":"Point"}
}