{
  "type": "Feature",
  "properties": {
    "addr:full":"1650 Owen Dr Fayetteville NC 28304",
    "addr:housenumber":"1650",
    "addr:postcode":"28304",
    "addr:street":"Owen Dr",
    "iso:country":"US",
    "sg:address":"1650 Owen Dr",
    "sg:city":"Fayetteville",
    "sg:classifiers":[
        {
            "category":"Home & Garden",
            "subcategory":"Building Materials",
            "type":"Retail Goods"
        }
    ],
    "sg:phone":"+1 910 424 7630",
    "sg:postcode":"28304",
    "sg:province":"NC",
    "wof:name":"Countertop Shop",
    "wof:placetype":"venue"
},
  "geometry": {"coordinates":[-78.931122,35.032419],"type":"Point"}
}