{
  "type": "Feature",
  "properties": {
    "iso:country":"US",
    "sg:address":"100 Albemarle Rd",
    "sg:city":"Wilmington",
    "sg:classifiers":[
        {
            "category":"Building & Trades",
            "subcategory":"Construction",
            "type":"Services"
        }
    ],
    "sg:phone":"+1 910 392 9493",
    "sg:postcode":"28405",
    "sg:province":"NC",
    "sg:tags":[
        "on",
        "welding",
        "contractor"
    ],
    "wof:name":"G & T Fabricators Inc",
    "wof:placetype":"venue"
},
  "geometry": {"coordinates":[-77.851697,34.257356],"type":"Point"}
}