{
  "type": "Feature",
  "properties": {
    "iso:country":"US",
    "sg:address":"1 W Chapel Cir",
    "sg:city":"Asheville",
    "sg:classifiers":[
        {
            "category":"Retail",
            "subcategory":"Car Wash",
            "type":"Services"
        }
    ],
    "sg:phone":"+1   ",
    "sg:postcode":"28803",
    "sg:province":"NC",
    "sg:tags":[
        "carwash"
    ],
    "wof:name":"Queens Mobile Car Detailing",
    "wof:placetype":"venue"
},
  "geometry": {"coordinates":[-82.527254,35.551995],"type":"Point"}
}