{
  "type": "Feature",
  "properties": {
    "addr:full":"2295 Cloverdale Ave Winston Salem NC 27103",
    "addr:housenumber":"2295",
    "addr:postcode":"27103",
    "addr:street":"Cloverdale Ave",
    "iso:country":"US",
    "sg:address":"2295 Cloverdale Ave",
    "sg:city":"Winston Salem",
    "sg:classifiers":[
        {
            "category":"Personal",
            "subcategory":"Beauty Salon",
            "type":"Services"
        }
    ],
    "sg:phone":"+1 336 727 9990",
    "sg:postcode":"27103",
    "sg:province":"NC",
    "sg:website":"www.greatclips.com",
    "wof:name":"Great Clips",
    "wof:placetype":"venue"
},
  "geometry": {"coordinates":[-80.276607,36.090062],"type":"Point"}
}