{
  "type": "Feature",
  "properties": {
    "addr:full":"415 Moore Rd Reidsville NC 27320",
    "addr:housenumber":"415",
    "addr:postcode":"27320",
    "addr:street":"Moore Rd",
    "iso:country":"US",
    "sg:address":"415 Moore Rd",
    "sg:city":"Reidsville",
    "sg:classifiers":[
        {
            "category":"Shopping",
            "subcategory":"Musical Instruments",
            "type":"Retail Goods"
        }
    ],
    "sg:phone":"+1 336 349 3000",
    "sg:postcode":"27320",
    "sg:province":"NC",
    "wof:name":"Scales Street Music",
    "wof:placetype":"venue"
},
  "geometry": {"coordinates":[-79.86971699999999,36.323355],"type":"Point"}
}