{
  "type": "Feature",
  "properties": {
    "iso:country":"US",
    "sg:address":"1222 Oaklawn Ave",
    "sg:city":"Charlotte",
    "sg:classifiers":[
        {
            "category":"Organizations",
            "subcategory":"Religious Organization",
            "type":"Services"
        }
    ],
    "sg:phone":"+1 704 333 4280",
    "sg:postcode":"28206",
    "sg:province":"NC",
    "sg:tags":[
        "church"
    ],
    "wof:name":"Community Outreach Christian",
    "wof:placetype":"venue"
},
  "geometry": {"coordinates":[-80.84250299999999,35.247422],"type":"Point"}
}