{
  "type": "Feature",
  "properties": {
    "iso:country":"US",
    "sg:address":"32 New Clyde Hwy",
    "sg:city":"Canton",
    "sg:classifiers":[
        {
            "category":"Shopping",
            "subcategory":"Bicycles & Sporting Goods",
            "type":"Retail Goods"
        }
    ],
    "sg:phone":"+1 828 648 5544",
    "sg:postcode":"28716",
    "sg:province":"NC",
    "sg:tags":[
        "equipment",
        "golf",
        "supply"
    ],
    "wof:name":"T & R Golf Carts",
    "wof:placetype":"venue"
},
  "geometry": {"coordinates":[-82.86120099999999,35.532303],"type":"Point"}
}