{
  "type": "Feature",
  "properties": {
    "addr:full":"11504 Bainbridge Ter Raleigh NC 27614",
    "addr:housenumber":"11504",
    "addr:postcode":"27614",
    "addr:street":"Bainbridge Ter",
    "iso:country":"US",
    "sg:address":"11504 Bainbridge Ter",
    "sg:city":"Raleigh",
    "sg:classifiers":[
        {
            "category":"Professional",
            "subcategory":"Engineering",
            "type":"Services"
        }
    ],
    "sg:phone":"+1   ",
    "sg:postcode":"27614",
    "sg:province":"NC",
    "wof:name":"QED",
    "wof:placetype":"venue"
},
  "geometry": {"coordinates":[-78.6341,35.941161],"type":"Point"}
}