{
  "type": "Feature",
  "properties": {
    "iso:country":"US",
    "sg:address":"254 David St",
    "sg:city":"Elizabethtown",
    "sg:classifiers":[
        {
            "category":"Building & Trades",
            "subcategory":"Construction",
            "type":"Services"
        }
    ],
    "sg:phone":"+1 252 583 1900",
    "sg:postcode":"28337",
    "sg:province":"NC",
    "sg:tags":[
        "mobile",
        "home"
    ],
    "wof:name":"W W Mobile Home Svc",
    "wof:placetype":"venue"
},
  "geometry": {"coordinates":[-78.59720799999999,34.62393],"type":"Point"}
}