{
  "type": "Feature",
  "properties": {
    "iso:country":"US",
    "sg:address":"212 Green Mountain Dr",
    "sg:city":"Burnsville",
    "sg:classifiers":[
        {
            "category":"Bus Station",
            "type":"Transportation"
        }
    ],
    "sg:phone":"+1 828 682 2167",
    "sg:postcode":"28714",
    "sg:province":"NC",
    "sg:tags":[
        "facility"
    ],
    "wof:name":"Scholl Bus Garage",
    "wof:placetype":"venue"
},
  "geometry": {"coordinates":[-82.29527899999999,35.921682],"type":"Point"}
}