{
  "type": "Feature",
  "properties": {
    "addr:full":"20124 W Catawba Ave Cornelius NC 28031",
    "addr:housenumber":"20124",
    "addr:postcode":"28031",
    "addr:street":"W Catawba Ave",
    "iso:country":"US",
    "sg:address":"20124 W Catawba Ave",
    "sg:city":"Cornelius",
    "sg:classifiers":[
        {
            "category":"Restaurant",
            "type":"Food & Drink"
        }
    ],
    "sg:menulink":"http://www.allmenus.com/nc/lemley/85348-dominos-pizza/menu/",
    "sg:phone":"+1 704 896 8007",
    "sg:postcode":"28031",
    "sg:province":"NC",
    "sg:tags":[
        "american",
        "wing",
        "pizza"
    ],
    "wof:name":"Domino's Pizza",
    "wof:placetype":"venue"
},
  "geometry": {"coordinates":[-80.880565,35.482223],"type":"Point"}
}