{
  "type": "Feature",
  "properties": {
    "iso:country":"US",
    "sg:address":"708 Tangle Dr",
    "sg:city":"Jamestown",
    "sg:classifiers":[
        {
            "category":"Building & Trades",
            "subcategory":"Construction",
            "type":"Services"
        }
    ],
    "sg:phone":"+1 336 454 5694",
    "sg:postcode":"27282",
    "sg:province":"NC",
    "sg:tags":[
        "contractor"
    ],
    "wof:name":"Burrow Construction Co",
    "wof:placetype":"venue"
},
  "geometry": {"coordinates":[-79.93323100000001,36.027119],"type":"Point"}
}