{
  "type": "Feature",
  "properties": {
    "addr:full":"2600 Carver St Durham NC 27705",
    "addr:housenumber":"2600",
    "addr:postcode":"27705",
    "addr:street":"Carver St",
    "iso:country":"US",
    "sg:address":"2600 Carver St",
    "sg:city":"Durham",
    "sg:classifiers":[
        {
            "category":"Banks & Credit Unions",
            "subcategory":"Investment Brokerage",
            "type":"Services"
        }
    ],
    "sg:phone":"+1 919 477 9299",
    "sg:postcode":"27705",
    "sg:province":"NC",
    "sg:tags":[
        "stock",
        "bond"
    ],
    "sg:website":"www.edwardjones.com",
    "wof:name":"Edward Jones",
    "wof:placetype":"venue"
},
  "geometry": {"coordinates":[-78.929519,36.037779],"type":"Point"}
}