{
  "type": "Feature",
  "properties": {
    "iso:country":"US",
    "sg:address":"388 Landis Ln",
    "sg:city":"Nebo",
    "sg:classifiers":[
        {
            "category":"Building & Trades",
            "subcategory":"Construction",
            "type":"Services"
        }
    ],
    "sg:phone":"+1 828 652 5952",
    "sg:postcode":"28761",
    "sg:province":"NC",
    "sg:tags":[
        "contractor"
    ],
    "wof:name":"Harvey & Associates Inc",
    "wof:placetype":"venue"
},
  "geometry": {"coordinates":[-81.86398699999999,35.593388],"type":"Point"}
}