{
  "type": "Feature",
  "properties": {
    "addr:full":"149 Station Rd Mayodan NC 27027",
    "addr:housenumber":"149",
    "addr:postcode":"27027",
    "addr:street":"Station Rd",
    "iso:country":"US",
    "sg:address":"149 Station Rd",
    "sg:city":"Mayodan",
    "sg:classifiers":[
        {
            "category":"Organizations",
            "subcategory":"Religious Organization",
            "type":"Services"
        }
    ],
    "sg:phone":"+1   ",
    "sg:postcode":"27027",
    "sg:province":"NC",
    "wof:name":"Clearview Baptist Parsonage",
    "wof:placetype":"venue"
},
  "geometry": {"coordinates":[-79.983023,36.42244],"type":"Point"}
}