{
  "type": "Feature",
  "properties": {
    "addr:full":"81 Vicksboro Rd Henderson NC 27536",
    "addr:housenumber":"81",
    "addr:postcode":"27536",
    "addr:street":"Vicksboro Rd",
    "iso:country":"US",
    "sg:address":"81 Vicksboro Rd",
    "sg:city":"Henderson",
    "sg:classifiers":[
        {
            "category":"Personal",
            "subcategory":"Barber",
            "type":"Services"
        }
    ],
    "sg:phone":"+1 252 431 0680",
    "sg:postcode":"27536",
    "sg:province":"NC",
    "wof:name":"Eastside Barber Shop",
    "wof:placetype":"venue"
},
  "geometry": {"coordinates":[-78.377878,36.316928],"type":"Point"}
}