{
  "type": "Feature",
  "properties": {
    "addr:full":"2205 N Church St Goldsboro NC 27530",
    "addr:housenumber":"2205",
    "addr:postcode":"27530",
    "addr:street":"N Church St",
    "iso:country":"US",
    "sg:address":"2205 N Church St",
    "sg:city":"Goldsboro",
    "sg:classifiers":[
        {
            "category":"Retail",
            "subcategory":"Car Wash",
            "type":"Services"
        }
    ],
    "sg:phone":"+1 919 222 8733",
    "sg:postcode":"27530",
    "sg:province":"NC",
    "sg:tags":[
        "automobile",
        "detail",
        "clean"
    ],
    "wof:name":"Tripp's Automotive Detailing",
    "wof:placetype":"venue"
},
  "geometry": {"coordinates":[-77.981634,35.408265],"type":"Point"}
}