{
  "type": "Feature",
  "properties": {
    "addr:full":"101 S Tryon St Charlotte NC 28280",
    "addr:housenumber":"101",
    "addr:postcode":"28280",
    "addr:street":"S Tryon St",
    "iso:country":"US",
    "sg:address":"101 S Tryon St",
    "sg:city":"Charlotte",
    "sg:classifiers":[
        {
            "category":"Coffee & Tea",
            "type":"Food & Drink"
        }
    ],
    "sg:menulink":"http://www.allmenus.com/nc/charlotte/124979-starbucks-coffee/menu/",
    "sg:phone":"+1 704 374 9519",
    "sg:postcode":"28280",
    "sg:province":"NC",
    "sg:tags":[
        "american"
    ],
    "wof:name":"Starbucks Coffee",
    "wof:placetype":"venue"
},
  "geometry": {"coordinates":[-80.842911,35.226366],"type":"Point"}
}