{
  "type": "Feature",
  "properties": {
    "iso:country":"US",
    "sg:address":"351 Butler Rd",
    "sg:city":"Forest City",
    "sg:classifiers":[
        {
            "category":"Banks & Credit Unions",
            "subcategory":"Bank",
            "type":"Services"
        }
    ],
    "sg:phone":"+1 828 245 1590",
    "sg:postcode":"28043",
    "sg:province":"NC",
    "wof:name":"First National Bank Of Shelby",
    "wof:placetype":"venue"
},
  "geometry": {"coordinates":[-81.886511,35.329053],"type":"Point"}
}