{
  "type": "Feature",
  "properties": {
    "iso:country":"US",
    "sg:address":"7101 Creedmoor Rd",
    "sg:city":"Raleigh",
    "sg:classifiers":[
        {
            "category":"Professional",
            "subcategory":"Lawyer & Legal Services",
            "type":"Services"
        }
    ],
    "sg:phone":"+1 919 845 6688",
    "sg:postcode":"27613",
    "sg:province":"NC",
    "sg:tags":[
        "attorney"
    ],
    "wof:name":"William Finn",
    "wof:placetype":"venue"
},
  "geometry": {"coordinates":[-78.679051,35.882956],"type":"Point"}
}