{
  "type": "Feature",
  "properties": {
    "addr:full":"1210 N Tryon St Charlotte NC 28206",
    "addr:housenumber":"1210",
    "addr:postcode":"28206",
    "addr:street":"N Tryon St",
    "iso:country":"US",
    "sg:address":"1210 N Tryon St",
    "sg:city":"Charlotte",
    "sg:classifiers":[
        {
            "category":"Health Services",
            "subcategory":"Clinic",
            "type":"Services"
        }
    ],
    "sg:phone":"+1 704 336 6615",
    "sg:postcode":"28206",
    "sg:province":"NC",
    "sg:tags":[
        "welfare"
    ],
    "wof:name":"Mecklenburg County Area Mental Health Authority",
    "wof:placetype":"venue"
},
  "geometry": {"coordinates":[-80.83058200000001,35.236427],"type":"Point"}
}