{
  "type": "Feature",
  "properties": {
    "addr:full":"257 Brandus Dr Hayesville NC 28904",
    "addr:housenumber":"257",
    "addr:postcode":"28904",
    "addr:street":"Brandus Dr",
    "iso:country":"US",
    "sg:address":"257 Brandus Dr",
    "sg:city":"Hayesville",
    "sg:classifiers":[
        {
            "category":"Health Services",
            "subcategory":"Medical Lab",
            "type":"Services"
        }
    ],
    "sg:phone":"+1 828 389 2505",
    "sg:postcode":"28904",
    "sg:province":"NC",
    "sg:tags":[
        "laboratory"
    ],
    "wof:name":"American Dental Lab",
    "wof:placetype":"venue"
},
  "geometry": {"coordinates":[-83.82810499999999,35.057451],"type":"Point"}
}