{
  "type": "Feature",
  "properties": {
    "addr:full":"115 E Eller Dr Winston Salem NC 27107",
    "addr:housenumber":"115",
    "addr:postcode":"27107",
    "addr:street":"E Eller Dr",
    "iso:country":"US",
    "sg:address":"115 E Eller Dr",
    "sg:city":"Winston Salem",
    "sg:classifiers":[
        {
            "category":"Building & Trades",
            "subcategory":"Construction",
            "type":"Services"
        }
    ],
    "sg:phone":"+1 336 775 2258",
    "sg:postcode":"27107",
    "sg:province":"NC",
    "sg:tags":[
        "contractor"
    ],
    "wof:name":"Cross Contracting",
    "wof:placetype":"venue"
},
  "geometry": {"coordinates":[-80.21723,35.957376],"type":"Point"}
}