{
  "type": "Feature",
  "properties": {
    "iso:country":"US",
    "sg:address":"185 Chapel View Dr",
    "sg:city":"Apex",
    "sg:classifiers":[
        {
            "category":"Retail",
            "subcategory":"Repair Shop",
            "type":"Services"
        }
    ],
    "sg:phone":"+1 919 303 2452",
    "sg:postcode":"27523",
    "sg:province":"NC",
    "sg:tags":[
        "equipment",
        "golf",
        "refinishing"
    ],
    "wof:name":"Nim Brann Custom Golf",
    "wof:placetype":"venue"
},
  "geometry": {"coordinates":[-78.966651,35.792933],"type":"Point"}
}