{
  "type": "Feature",
  "properties": {
    "iso:country":"US",
    "sg:address":"2494 US Hwy 70",
    "sg:city":"Beaufort",
    "sg:classifiers":[
        {
            "category":"Organizations",
            "subcategory":"Religious Organization",
            "type":"Services"
        }
    ],
    "sg:phone":"+1 252 504 2337",
    "sg:postcode":"28516",
    "sg:province":"NC",
    "sg:tags":[
        "church"
    ],
    "wof:name":"North River United Methodist",
    "wof:placetype":"venue"
},
  "geometry": {"coordinates":[-76.63057999999999,34.750075],"type":"Point"}
}