{
  "type": "Feature",
  "properties": {
    "iso:country":"US",
    "sg:address":"1032 Airport Rd",
    "sg:city":"Mebane",
    "sg:classifiers":[
        {
            "category":"Airport",
            "type":"Transportation"
        }
    ],
    "sg:phone":"+1 919 563 3490",
    "sg:postcode":"27360",
    "sg:province":"NC",
    "wof:name":"Hurdle Field Airport",
    "wof:placetype":"venue"
},
  "geometry": {"coordinates":[-80.06050500000001,35.79012],"type":"Point"}
}