{
  "type": "Feature",
  "properties": {
    "addr:full":"917 Pine Logging Rd Whiteville NC 28472",
    "addr:housenumber":"917",
    "addr:postcode":"28472",
    "addr:street":"Pine Logging Rd",
    "iso:country":"US",
    "sg:address":"917 Pine Logging Rd",
    "sg:city":"Whiteville",
    "sg:classifiers":[
        {
            "category":"Retail",
            "subcategory":"Funeral Services",
            "type":"Services"
        }
    ],
    "sg:phone":"+1 910 642 6000",
    "sg:postcode":"28472",
    "sg:province":"NC",
    "sg:tags":[
        "director"
    ],
    "wof:name":"Goodwill Funeral Home",
    "wof:placetype":"venue"
},
  "geometry": {"coordinates":[-78.723668,34.323778],"type":"Point"}
}