{
  "type": "Feature",
  "properties": {
    "addr:full":"1622 Harper Spring Dr Clemmons NC 27012",
    "addr:housenumber":"1622",
    "addr:postcode":"27012",
    "addr:street":"Harper Spring Dr",
    "iso:country":"US",
    "sg:address":"1622 Harper Spring Dr",
    "sg:city":"Clemmons",
    "sg:classifiers":[
        {
            "category":"Professional",
            "subcategory":"Computer Services",
            "type":"Services"
        }
    ],
    "sg:phone":"+1 336 403 1885",
    "sg:postcode":"27012",
    "sg:province":"NC",
    "sg:tags":[
        "website",
        "design"
    ],
    "wof:name":"Mindfre Moojjoo Web Design",
    "wof:placetype":"venue"
},
  "geometry": {"coordinates":[-80.37745099999999,36.066968],"type":"Point"}
}