{
  "type": "Feature",
  "properties": {
    "addr:full":"1533 Benvenue Rd Rocky Mount NC 27804",
    "addr:housenumber":"1533",
    "addr:postcode":"27804",
    "addr:street":"Benvenue Rd",
    "iso:country":"US",
    "sg:address":"1533 Benvenue Rd",
    "sg:city":"Rocky Mount",
    "sg:classifiers":[
        {
            "category":"Shopping",
            "subcategory":"Clothing, Apparel, & Fashions",
            "type":"Retail Goods"
        }
    ],
    "sg:phone":"+1 252 442 5555",
    "sg:postcode":"27804",
    "sg:province":"NC",
    "wof:name":"Catherines",
    "wof:placetype":"venue"
},
  "geometry": {"coordinates":[-77.808181,35.97984],"type":"Point"}
}