{
  "type": "Feature",
  "properties": {
    "addr:full":"500 Illahee Rd Brevard NC 28712",
    "addr:housenumber":"500",
    "addr:postcode":"28712",
    "addr:street":"Illahee Rd",
    "iso:country":"US",
    "sg:address":"500 Illahee Rd",
    "sg:city":"Brevard",
    "sg:classifiers":[
        {
            "category":"Travel",
            "subcategory":"Campground",
            "type":"Entertainment"
        }
    ],
    "sg:phone":"+1 828 883 2181",
    "sg:postcode":"28712",
    "sg:province":"NC",
    "sg:tags":[
        "summer",
        "girl",
        "camp",
        "private",
        "for"
    ],
    "wof:name":"Camp Illahee",
    "wof:placetype":"venue"
},
  "geometry": {"coordinates":[-82.753096,35.2125],"type":"Point"}
}