{
  "type": "Feature",
  "properties": {
    "iso:country":"US",
    "sg:address":"11846 US Hwy 601",
    "sg:city":"Midland",
    "sg:classifiers":[
        {
            "category":"Organizations",
            "subcategory":"Community Association",
            "type":"Services"
        }
    ],
    "sg:phone":"+1   ",
    "sg:postcode":"28107",
    "sg:province":"NC",
    "wof:name":"Grand Chpter of Nrth Crlina or",
    "wof:placetype":"venue"
},
  "geometry": {"coordinates":[-80.50031300000001,35.254225],"type":"Point"}
}