{
  "type": "Feature",
  "properties": {
    "addr:full":"901 N Charlotte Ave Monroe NC 28110",
    "addr:housenumber":"901",
    "addr:postcode":"28110",
    "addr:street":"N Charlotte Ave",
    "iso:country":"US",
    "sg:address":"901 N Charlotte Ave",
    "sg:city":"Monroe",
    "sg:classifiers":[
        {
            "category":"Shopping",
            "subcategory":"Used Merchandise",
            "type":"Retail Goods"
        }
    ],
    "sg:phone":"+1 704 291 7296",
    "sg:postcode":"28110",
    "sg:province":"NC",
    "sg:tags":[
        "pawnbroker"
    ],
    "wof:name":"Gold-N-Pawn",
    "wof:placetype":"venue"
},
  "geometry": {"coordinates":[-80.554267,34.989498],"type":"Point"}
}