{
  "type": "Feature",
  "properties": {
    "addr:full":"1718 Cary Macedonia Rd Cary NC 27511",
    "addr:housenumber":"1718",
    "addr:postcode":"27511",
    "addr:street":"Macedonia Rd",
    "iso:country":"US",
    "sg:address":"1718 Cary Macedonia Rd",
    "sg:city":"Cary",
    "sg:classifiers":[
        {
            "category":"Restaurant",
            "type":"Food & Drink"
        }
    ],
    "sg:phone":"+1 919 467 5950",
    "sg:postcode":"27511",
    "sg:province":"NC",
    "wof:name":"Waffle House",
    "wof:placetype":"venue"
},
  "geometry": {"coordinates":[-78.778198,35.752602],"type":"Point"}
}