{
  "type": "Feature",
  "properties": {
    "iso:country":"US",
    "sg:address":"14 N French Broad Ave",
    "sg:city":"Asheville",
    "sg:classifiers":[
        {
            "category":"Professional",
            "subcategory":"Business Services",
            "type":"Services"
        }
    ],
    "sg:phone":"+1 828 232 4314",
    "sg:postcode":"28801",
    "sg:province":"NC",
    "sg:tags":[
        "recording",
        "studio"
    ],
    "wof:name":"Echo Mountain",
    "wof:placetype":"venue"
},
  "geometry": {"coordinates":[-82.558722,35.594627],"type":"Point"}
}