{
  "type": "Feature",
  "properties": {
    "addr:full":"142 Bermuda Village Dr Advance NC 27006",
    "addr:housenumber":"142",
    "addr:postcode":"27006",
    "addr:street":"Bermuda Village Dr",
    "iso:country":"US",
    "sg:address":"142 Bermuda Village Dr",
    "sg:city":"Advance",
    "sg:classifiers":[
        {
            "category":"Organizations",
            "subcategory":"Community Association",
            "type":"Services"
        }
    ],
    "sg:phone":"+1   ",
    "sg:postcode":"27006",
    "sg:province":"NC",
    "wof:name":"Stanley S Resnick Ltcol",
    "wof:placetype":"venue"
},
  "geometry": {"coordinates":[-80.431749,35.995622],"type":"Point"}
}