{
  "type": "Feature",
  "properties": {
    "iso:country":"US",
    "sg:address":"1415 Willow Ln",
    "sg:city":"North Wilkesboro",
    "sg:classifiers":[
        {
            "category":"Building & Trades",
            "subcategory":"Electrical",
            "type":"Services"
        }
    ],
    "sg:phone":"+1 336 667 6151",
    "sg:postcode":"28659",
    "sg:province":"NC",
    "sg:tags":[
        "electric",
        "contractor"
    ],
    "wof:name":"Duncan Electric Co",
    "wof:placetype":"venue"
},
  "geometry": {"coordinates":[-81.16053100000001,36.15398],"type":"Point"}
}