{
  "type": "Feature",
  "properties": {
    "addr:full":"400 McGill Ave NW Concord NC 28027",
    "addr:housenumber":"400",
    "addr:postcode":"28027",
    "addr:street":"Mcgill Ave Nw",
    "iso:country":"US",
    "sg:address":"400 McGill Ave NW",
    "sg:city":"Concord",
    "sg:classifiers":[
        {
            "category":"Insurance",
            "subcategory":"Insurance Agent",
            "type":"Services"
        }
    ],
    "sg:phone":"+1 704 721 5400",
    "sg:postcode":"28027",
    "sg:province":"NC",
    "wof:name":"DSB Insurance LLC",
    "wof:placetype":"venue"
},
  "geometry": {"coordinates":[-80.605521,35.415962],"type":"Point"}
}