{
  "type": "Feature",
  "properties": {
    "addr:full":"122 Ivy Hill Rd Weaverville NC 28787",
    "addr:housenumber":"122",
    "addr:postcode":"28787",
    "addr:street":"Ivy Hill Rd",
    "iso:country":"US",
    "sg:address":"122 Ivy Hill Rd",
    "sg:city":"Weaverville",
    "sg:classifiers":[
        {
            "category":"Banks & Credit Unions",
            "subcategory":"Investment Brokerage",
            "type":"Services"
        }
    ],
    "sg:phone":"+1 828 658 1742",
    "sg:postcode":"28787",
    "sg:province":"NC",
    "sg:tags":[
        "advisory"
    ],
    "wof:name":"Donna L Emory Family Ltd",
    "wof:placetype":"venue"
},
  "geometry": {"coordinates":[-82.51311800000001,35.778015],"type":"Point"}
}