{
  "type": "Feature",
  "properties": {
    "iso:country":"US",
    "sg:address":"319 Grandin Rd",
    "sg:city":"Charlotte",
    "sg:classifiers":[
        {
            "category":"Professional",
            "subcategory":"Computer Services",
            "type":"Services"
        }
    ],
    "sg:phone":"+1 704 817 0866",
    "sg:postcode":"28208",
    "sg:province":"NC",
    "sg:website":"http://cltblog.com/",
    "wof:name":"CLT Blog",
    "wof:placetype":"venue"
},
  "geometry": {"coordinates":[-80.861541,35.234136],"type":"Point"}
}