{
  "type": "Feature",
  "properties": {
    "addr:full":"815 E Innes St Salisbury NC 28144",
    "addr:housenumber":"815",
    "addr:postcode":"28144",
    "addr:street":"E Innes St",
    "iso:country":"US",
    "sg:address":"815 E Innes St",
    "sg:city":"Salisbury",
    "sg:classifiers":[
        {
            "category":"Professional",
            "subcategory":"Accounting & Tax Preparation",
            "type":"Services"
        }
    ],
    "sg:phone":"+1 704 638 5892",
    "sg:postcode":"28144",
    "sg:province":"NC",
    "sg:tags":[
        "return",
        "filing"
    ],
    "sg:website":"www.jacksonhewitt.com",
    "wof:name":"Jackson Hewitt Tax Svc",
    "wof:placetype":"venue"
},
  "geometry": {"coordinates":[-80.461972,35.660029],"type":"Point"}
}