{
  "type": "Feature",
  "properties": {
    "iso:country":"US",
    "sg:address":"119 Woodside Dr",
    "sg:city":"Rockingham",
    "sg:classifiers":[
        {
            "category":"Professional",
            "type":"Services"
        }
    ],
    "sg:phone":"+1 910 997 2027",
    "sg:postcode":"28379",
    "sg:province":"NC",
    "wof:name":"Tuck H Douglas Jr Rev",
    "wof:placetype":"venue"
},
  "geometry": {"coordinates":[-79.76294,34.971956],"type":"Point"}
}