{
  "type": "Feature",
  "properties": {
    "iso:country":"US",
    "sg:address":"4 Park Rd",
    "sg:city":"Asheville",
    "sg:classifiers":[
        {
            "category":"Health Services",
            "subcategory":"Doctor",
            "type":"Services"
        }
    ],
    "sg:phone":"+1 828 277 7770",
    "sg:postcode":"28803",
    "sg:province":"NC",
    "wof:name":"National Maxillofacial Surgeon",
    "wof:placetype":"venue"
},
  "geometry": {"coordinates":[-82.53957200000001,35.537657],"type":"Point"}
}