{
  "type": "Feature",
  "properties": {
    "addr:full":"1215 Link Rd Winston Salem NC 27103",
    "addr:housenumber":"1215",
    "addr:postcode":"27103",
    "addr:street":"Link Rd",
    "iso:country":"US",
    "sg:address":"1215 Link Rd",
    "sg:city":"Winston Salem",
    "sg:classifiers":[
        {
            "category":"Home & Garden",
            "subcategory":"Household Appliances",
            "type":"Retail Goods"
        }
    ],
    "sg:phone":"+1 336 724 5578",
    "sg:postcode":"27103",
    "sg:province":"NC",
    "sg:tags":[
        "cleaners",
        "vacuum"
    ],
    "sg:website":"www.aerusonline.com",
    "wof:name":"Aerus Electrolux",
    "wof:placetype":"venue"
},
  "geometry": {"coordinates":[-80.256693,36.07446],"type":"Point"}
}