{
  "type": "Feature",
  "properties": {
    "addr:full":"200 Powell Dr Raleigh NC 27606",
    "addr:housenumber":"200",
    "addr:postcode":"27606",
    "addr:street":"Powell Dr",
    "iso:country":"US",
    "sg:address":"200 Powell Dr",
    "sg:city":"Raleigh",
    "sg:classifiers":[
        {
            "category":"Arts & Performance",
            "subcategory":"Theater",
            "type":"Entertainment"
        }
    ],
    "sg:phone":"+1 919 852 2020",
    "sg:postcode":"27606",
    "sg:province":"NC",
    "sg:tags":[
        "group",
        "bureau"
    ],
    "wof:name":"Ultimate Entertainment Inc",
    "wof:placetype":"venue"
},
  "geometry": {"coordinates":[-78.71338,35.788672],"type":"Point"}
}