{
  "type": "Feature",
  "properties": {
    "addr:full":"200 E Wendover Ave Greensboro NC 27401",
    "addr:housenumber":"200",
    "addr:postcode":"27401",
    "addr:street":"E Wendover Ave",
    "iso:country":"US",
    "sg:address":"200 E Wendover Ave",
    "sg:city":"Greensboro",
    "sg:classifiers":[
        {
            "category":"Health Services",
            "subcategory":"Dentist",
            "type":"Services"
        }
    ],
    "sg:phone":"+1 336 275 4747",
    "sg:postcode":"27401",
    "sg:province":"NC",
    "sg:tags":[
        "dentists-cosmetic",
        "dentistry"
    ],
    "sg:website":"http://www.dentalgreensboro.com",
    "wof:name":"Mango & Langdon DDS",
    "wof:placetype":"venue"
},
  "geometry": {"coordinates":[-79.78780399999999,36.087841],"type":"Point"}
}