{
  "type": "Feature",
  "properties": {
    "addr:full":"200 Green St Williamston NC 27892",
    "addr:housenumber":"200",
    "addr:postcode":"27892",
    "addr:street":"Green St",
    "iso:country":"US",
    "sg:address":"200 Green St",
    "sg:city":"Williamston",
    "sg:classifiers":[
        {
            "category":"Building & Trades",
            "subcategory":"Construction",
            "type":"Services"
        }
    ],
    "sg:phone":"+1 252 809 4997",
    "sg:postcode":"27892",
    "sg:province":"NC",
    "sg:tags":[
        "house",
        "commercial"
    ],
    "wof:name":"Quality Home Staffing",
    "wof:placetype":"venue"
},
  "geometry": {"coordinates":[-77.04831799999999,35.846951],"type":"Point"}
}