{
  "type": "Feature",
  "properties": {
    "addr:full":"124 Creekside Dr Oxford NC 27501",
    "addr:housenumber":"124",
    "addr:postcode":"27501",
    "addr:street":"Creekside Dr",
    "iso:country":"US",
    "sg:address":"124 Creekside Dr",
    "sg:city":"Oxford",
    "sg:classifiers":[
        {
            "category":"Professional",
            "type":"Services"
        }
    ],
    "sg:phone":"+1 919 603 9646",
    "sg:postcode":"27501",
    "sg:province":"NC",
    "sg:tags":[
        "establishment"
    ],
    "wof:name":"Watkins RE",
    "wof:placetype":"venue"
},
  "geometry": {"coordinates":[-78.766704,35.5139],"type":"Point"}
}