{
  "type": "Feature",
  "properties": {
    "addr:full":"211 S 3rd St Highlands NC 28741",
    "addr:housenumber":"211",
    "addr:postcode":"28741",
    "addr:street":"S 3Rd St",
    "iso:country":"US",
    "sg:address":"211 S 3rd St",
    "sg:city":"Highlands",
    "sg:classifiers":[
        {
            "category":"Wholesale",
            "subcategory":"Books, Periodicals, & Newspapers",
            "type":"Manufacturing & Wholesale Goods"
        }
    ],
    "sg:phone":"+1 828 526 0147",
    "sg:postcode":"28741",
    "sg:province":"NC",
    "wof:name":"Mountain Laurel Magazine",
    "wof:placetype":"venue"
},
  "geometry": {"coordinates":[-83.199613,35.052828],"type":"Point"}
}