{
  "type": "Feature",
  "properties": {
    "addr:full":"201 W Wilson St Tarboro NC 27886",
    "addr:housenumber":"201",
    "addr:postcode":"27886",
    "addr:street":"W Wilson St",
    "iso:country":"US",
    "sg:address":"201 W Wilson St",
    "sg:city":"Tarboro",
    "sg:classifiers":[
        {
            "category":"Building & Trades",
            "subcategory":"Construction",
            "type":"Services"
        }
    ],
    "sg:phone":"+1 252 823 8071",
    "sg:postcode":"27886",
    "sg:province":"NC",
    "wof:name":"Nashco Inc",
    "wof:placetype":"venue"
},
  "geometry": {"coordinates":[-77.53736000000001,35.899281],"type":"Point"}
}