{
  "type": "Feature",
  "properties": {
    "iso:country":"US",
    "sg:address":"5614 US Hwy 70",
    "sg:city":"Goldsboro",
    "sg:classifiers":[
        {
            "category":"Retail",
            "subcategory":"Auto Repair",
            "type":"Services"
        }
    ],
    "sg:phone":"+1 919 751 0065",
    "sg:postcode":"27534",
    "sg:province":"NC",
    "sg:tags":[
        "automotive",
        "vehicle"
    ],
    "wof:name":"Hines Used Cars",
    "wof:placetype":"venue"
},
  "geometry": {"coordinates":[-77.89477100000001,35.337176],"type":"Point"}
}