{
  "type": "Feature",
  "properties": {
    "iso:country":"US",
    "sg:address":"1041 Davis Dr",
    "sg:city":"Apex",
    "sg:classifiers":[
        {
            "category":"Shopping",
            "subcategory":"Computers & Home Electronics",
            "type":"Retail Goods"
        }
    ],
    "sg:phone":"+1 919 481 1616",
    "sg:postcode":"27523",
    "sg:province":"NC",
    "sg:tags":[
        "software"
    ],
    "sg:website":"www.cashlesssystems.com",
    "wof:name":"Cashless Systems Inc",
    "wof:placetype":"venue"
},
  "geometry": {"coordinates":[-78.846558,35.754483],"type":"Point"}
}