{
  "type": "Feature",
  "properties": {
    "addr:full":"3308 Harbour Pointe Pl Fayetteville NC 28314",
    "addr:housenumber":"3308",
    "addr:postcode":"28314",
    "addr:street":"Harbour Pointe Pl",
    "iso:country":"US",
    "sg:address":"3308 Harbour Pointe Pl",
    "sg:city":"Fayetteville",
    "sg:classifiers":[
        {
            "category":"Real Estate",
            "subcategory":"Real Estate Operator",
            "type":"Services"
        }
    ],
    "sg:phone":"+1 910 864 7116",
    "sg:postcode":"28314",
    "sg:province":"NC",
    "sg:tags":[
        "condominium"
    ],
    "wof:name":"Harbour Point Condominiums",
    "wof:placetype":"venue"
},
  "geometry": {"coordinates":[-78.986647,35.064582],"type":"Point"}
}