{
  "type": "Feature",
  "properties": {
    "addr:full":"2111 Beatties Ford Rd Charlotte NC 28216",
    "addr:housenumber":"2111",
    "addr:postcode":"28216",
    "addr:street":"Beatties Ford Rd",
    "iso:country":"US",
    "sg:address":"2111 Beatties Ford Rd",
    "sg:city":"Charlotte",
    "sg:classifiers":[
        {
            "category":"Shopping",
            "subcategory":"Beauty & Cosmetics",
            "type":"Retail Goods"
        },
        {
            "category":"Personal",
            "subcategory":"Beauty Salon",
            "type":"Services"
        }
    ],
    "sg:phone":"+1 704 393 7355",
    "sg:postcode":"28216",
    "sg:province":"NC",
    "sg:tags":[
        "perfume",
        "cosmetics-wholesale",
        "manufacturer"
    ],
    "wof:name":"Kizzy Beauty Supply",
    "wof:placetype":"venue"
},
  "geometry": {"coordinates":[-80.85470100000001,35.263116],"type":"Point"}
}