{
  "type": "Feature",
  "properties": {
    "addr:full":"270 Holden Beach Rd Shallotte NC 28470",
    "addr:housenumber":"270",
    "addr:postcode":"28470",
    "addr:street":"Holden Beach Rd",
    "iso:country":"US",
    "sg:address":"270 Holden Beach Rd",
    "sg:city":"Shallotte",
    "sg:classifiers":[
        {
            "category":"Restaurant",
            "type":"Food & Drink"
        }
    ],
    "sg:phone":"+1 910 754 9096",
    "sg:postcode":"28470",
    "sg:province":"NC",
    "sg:tags":[
        "eating"
    ],
    "wof:name":"Carmellas Restaurant",
    "wof:placetype":"venue"
},
  "geometry": {"coordinates":[-78.362736,33.978252],"type":"Point"}
}