{
  "type": "Feature",
  "properties": {
    "iso:country":"US",
    "sg:address":"602 S Main St",
    "sg:city":"Farmville",
    "sg:classifiers":[
        {
            "category":"Personal",
            "subcategory":"Barber",
            "type":"Services"
        }
    ],
    "sg:phone":"+1 252 753 5682",
    "sg:postcode":"27828",
    "sg:province":"NC",
    "wof:name":"Blount's Sanitary Barber Shop",
    "wof:placetype":"venue"
},
  "geometry": {"coordinates":[-77.589535,35.592758],"type":"Point"}
}