{
  "type": "Feature",
  "properties": {
    "iso:country":"US",
    "sg:address":"1521 S Morgan St",
    "sg:city":"Shelby",
    "sg:classifiers":[
        {
            "category":"Shopping",
            "subcategory":"Used Merchandise",
            "type":"Retail Goods"
        }
    ],
    "sg:phone":"+1 704 471 2754",
    "sg:postcode":"28152",
    "sg:province":"NC",
    "wof:name":"Camerons Antique",
    "wof:placetype":"venue"
},
  "geometry": {"coordinates":[-81.542755,35.262869],"type":"Point"}
}