{
  "type": "Feature",
  "properties": {
    "iso:country":"US",
    "sg:address":"490 State Hwy 42 W",
    "sg:city":"Clayton",
    "sg:classifiers":[
        {
            "category":"Professional",
            "subcategory":"Lawyer & Legal Services",
            "type":"Services"
        }
    ],
    "sg:phone":"+1 919 359 3093",
    "sg:postcode":"27520",
    "sg:province":"NC",
    "sg:tags":[
        "attorney"
    ],
    "wof:name":"Hales & Conaway Pllc",
    "wof:placetype":"venue"
},
  "geometry": {"coordinates":[-78.473106,35.64147],"type":"Point"}
}