{
  "type": "Feature",
  "properties": {
    "addr:full":"1000 Upper Asbury Ave Charlotte NC 28206",
    "addr:housenumber":"1000",
    "addr:postcode":"28206",
    "addr:street":"Upper Asbury Ave",
    "iso:country":"US",
    "sg:address":"1000 Upper Asbury Ave",
    "sg:city":"Charlotte",
    "sg:classifiers":[
        {
            "category":"Wholesale",
            "subcategory":"Machinery & Supplies",
            "type":"Manufacturing & Wholesale Goods"
        },
        {
            "category":"Wholesale",
            "subcategory":"Durable Goods & Equipment",
            "type":"Manufacturing & Wholesale Goods"
        }
    ],
    "sg:phone":"+1 704 334 2377",
    "sg:postcode":"28206",
    "sg:province":"NC",
    "sg:tags":[
        "valve"
    ],
    "wof:name":"Eastern Industrial Supplies",
    "wof:placetype":"venue"
},
  "geometry": {"coordinates":[-80.82121600000001,35.262881],"type":"Point"}
}