{
  "type": "Feature",
  "properties": {
    "iso:country":"US",
    "sg:address":"640 Matthews-Mint Hill Rd",
    "sg:city":"Matthews",
    "sg:classifiers":[
        {
            "category":"Freight",
            "type":"Transportation"
        }
    ],
    "sg:phone":"+1 704 841 7001",
    "sg:postcode":"28105",
    "sg:province":"NC",
    "sg:tags":[
        "mover"
    ],
    "wof:name":"Citywide Moving",
    "wof:placetype":"venue"
},
  "geometry": {"coordinates":[-80.712963,35.117602],"type":"Point"}
}