{
  "type": "Feature",
  "properties": {
    "iso:country":"US",
    "sg:address":"1206 E Walnut St",
    "sg:city":"Goldsboro",
    "sg:classifiers":[
        {
            "category":"Organizations",
            "subcategory":"Religious Organization",
            "type":"Services"
        }
    ],
    "sg:phone":"+1   ",
    "sg:postcode":"27530",
    "sg:province":"NC",
    "wof:name":"Wayside Fellowship Home",
    "wof:placetype":"venue"
},
  "geometry": {"coordinates":[-77.978212,35.377792],"type":"Point"}
}