{
  "type": "Feature",
  "properties": {
    "addr:full":"1212 W Roosevelt Blvd Monroe NC 28110",
    "addr:housenumber":"1212",
    "addr:postcode":"28110",
    "addr:street":"W Roosevelt Blvd",
    "iso:country":"US",
    "sg:address":"1212 W Roosevelt Blvd",
    "sg:city":"Monroe",
    "sg:classifiers":[
        {
            "category":"Government",
            "subcategory":"Office",
            "type":"Public Place"
        }
    ],
    "sg:phone":"+1 704 296 4300",
    "sg:postcode":"28110",
    "sg:province":"NC",
    "sg:tags":[
        "county",
        "resource"
    ],
    "wof:name":"Union County Social Svc",
    "wof:placetype":"venue"
},
  "geometry": {"coordinates":[-80.54205,34.995122],"type":"Point"}
}