{
  "type": "Feature",
  "properties": {
    "iso:country":"US",
    "sg:address":"138 N Main St",
    "sg:city":"Spring Lake",
    "sg:classifiers":[
        {
            "category":"Food & Beverages",
            "subcategory":"Groceries & Convenience Stores",
            "type":"Retail Goods"
        }
    ],
    "sg:phone":"+1 910 497 6900",
    "sg:postcode":"28390",
    "sg:province":"NC",
    "wof:name":"Spanish & Far Eastern Market",
    "wof:placetype":"venue"
},
  "geometry": {"coordinates":[-78.97663799999999,35.167611],"type":"Point"}
}