{
  "type": "Feature",
  "properties": {
    "iso:country":"US",
    "sg:address":"205 S Berkeley Blvd",
    "sg:city":"Goldsboro",
    "sg:classifiers":[
        {
            "category":"Personal",
            "subcategory":"Beauty Salon",
            "type":"Services"
        }
    ],
    "sg:phone":"+1 919 751 5557",
    "sg:postcode":"27534",
    "sg:province":"NC",
    "wof:name":"Cut N Up Hair Clinic",
    "wof:placetype":"venue"
},
  "geometry": {"coordinates":[-77.95629099999999,35.368706],"type":"Point"}
}