{
  "type": "Feature",
  "properties": {
    "addr:full":"15 Bailey Rd Asheville NC 28806",
    "addr:housenumber":"15",
    "addr:postcode":"28806",
    "addr:street":"Bailey Rd",
    "iso:country":"US",
    "sg:address":"15 Bailey Rd",
    "sg:city":"Asheville",
    "sg:classifiers":[
        {
            "category":"Utilities",
            "type":"Services"
        }
    ],
    "sg:phone":"+1 828 670 3505",
    "sg:postcode":"28806",
    "sg:province":"NC",
    "sg:tags":[
        "other",
        "electric",
        "combined"
    ],
    "wof:name":"Psnc Energy",
    "wof:placetype":"venue"
},
  "geometry": {"coordinates":[-82.637637,35.585898],"type":"Point"}
}