{
  "type": "Feature",
  "properties": {
    "iso:country":"US",
    "sg:address":"2511 Wood Star Ct",
    "sg:city":"Matthews",
    "sg:classifiers":[
        {
            "category":"Professional",
            "type":"Services"
        }
    ],
    "sg:phone":"+1 704 847 8134",
    "sg:postcode":"28105",
    "sg:province":"NC",
    "sg:tags":[
        "establishment"
    ],
    "wof:name":"Hispano American Bridge Inc",
    "wof:placetype":"venue"
},
  "geometry": {"coordinates":[-80.69313099999999,35.131413],"type":"Point"}
}