{
  "type": "Feature",
  "properties": {
    "addr:full":"308 W Windsor St Monroe NC 28112",
    "addr:housenumber":"308",
    "addr:postcode":"28112",
    "addr:street":"W Windsor",
    "iso:country":"US",
    "sg:address":"308 W Windsor St",
    "sg:city":"Monroe",
    "sg:classifiers":[
        {
            "category":"Retail",
            "subcategory":"Laundry & Dry Cleaning",
            "type":"Services"
        }
    ],
    "sg:phone":"+1 704 218 3416",
    "sg:postcode":"28112",
    "sg:province":"NC",
    "sg:tags":[
        "cleaners",
        "rug",
        "carpet"
    ],
    "wof:name":"Jamps Carpet Cleaning Sales",
    "wof:placetype":"venue"
},
  "geometry": {"coordinates":[-80.551663,34.981336],"type":"Point"}
}