{
  "type": "Feature",
  "properties": {
    "iso:country":"US",
    "sg:address":"10724 Park Rd Ste 504",
    "sg:city":"Charlotte",
    "sg:classifiers":[
        {
            "category":"Health Services",
            "subcategory":"Doctor",
            "type":"Services"
        }
    ],
    "sg:phone":"+1 704 543 1600",
    "sg:postcode":"28210",
    "sg:province":"NC",
    "sg:tags":[
        "physician",
        "surgeon",
        "radiology",
        "surgeons",
        "pediatrics-radiology"
    ],
    "wof:name":"Breast Cancer Detection Center",
    "wof:placetype":"venue"
},
  "geometry": {"coordinates":[-80.869871,35.090703],"type":"Point"}
}