{
  "type": "Feature",
  "properties": {
    "addr:full":"6205 Salem Chapel Rd Walnut Cove NC 27052",
    "addr:housenumber":"6205",
    "addr:postcode":"27052",
    "addr:street":"Salem Chapel Rd",
    "iso:country":"US",
    "sg:address":"6205 Salem Chapel Rd",
    "sg:city":"Walnut Cove",
    "sg:classifiers":[
        {
            "category":"Organizations",
            "subcategory":"Religious Organization",
            "type":"Services"
        }
    ],
    "sg:phone":"+1 336 591 3621",
    "sg:postcode":"27052",
    "sg:province":"NC",
    "sg:tags":[
        "church"
    ],
    "wof:name":"Baux Mountain Baptist Church",
    "wof:placetype":"venue"
},
  "geometry": {"coordinates":[-80.137286,36.224692],"type":"Point"}
}