{
  "type": "Feature",
  "properties": {
    "iso:country":"US",
    "sg:address":"940 Main Campus Dr",
    "sg:city":"Raleigh",
    "sg:classifiers":[
        {
            "category":"Professional",
            "subcategory":"Research",
            "type":"Services"
        }
    ],
    "sg:phone":"+1 919 834 5797",
    "sg:postcode":"27606",
    "sg:province":"NC",
    "wof:name":"NDRI",
    "wof:placetype":"venue"
},
  "geometry": {"coordinates":[-78.676958,35.773582],"type":"Point"}
}