{
  "type": "Feature",
  "properties": {
    "addr:full":"5624 Waxhaw Indian Trail Rd Matthews NC 28104",
    "addr:postcode":"5624;28104",
    "addr:street":"Indian Trail Rd",
    "iso:country":"US",
    "sg:address":"5624 Waxhaw Indian Trail Rd",
    "sg:city":"Matthews",
    "sg:classifiers":[
        {
            "category":"Wholesale",
            "subcategory":"Farm Supplies",
            "type":"Manufacturing & Wholesale Goods"
        }
    ],
    "sg:phone":"+1 704 821 7556",
    "sg:postcode":"28104",
    "sg:province":"NC",
    "sg:tags":[
        "livestock"
    ],
    "wof:name":"Danny Baker Farm",
    "wof:placetype":"venue"
},
  "geometry": {"coordinates":[-80.697737,35.006406],"type":"Point"}
}