{
  "type": "Feature",
  "properties": {
    "addr:full":"3044 E Franklin Blvd Gastonia NC 28056",
    "addr:housenumber":"3044",
    "addr:postcode":"28056",
    "addr:street":"E Franklin Blvd",
    "iso:country":"US",
    "sg:address":"3044 E Franklin Blvd",
    "sg:city":"Gastonia",
    "sg:classifiers":[
        {
            "category":"Food & Beverages",
            "subcategory":"Specialty",
            "type":"Retail Goods"
        },
        {
            "category":"Food & Beverages",
            "subcategory":"Fruits & Vegetables",
            "type":"Retail Goods"
        },
        {
            "category":"Shopping",
            "subcategory":"Pharmacy",
            "type":"Retail Goods"
        }
    ],
    "sg:phone":"+1 704 867 6141",
    "sg:postcode":"28056",
    "sg:province":"NC",
    "sg:tags":[
        "product",
        "wellness",
        "vitamin",
        "diet",
        "supplement",
        "health",
        "herb"
    ],
    "sg:website":"http://www.gnc.com",
    "wof:name":"GNC",
    "wof:placetype":"venue"
},
  "geometry": {"coordinates":[-81.12470999999999,35.25898],"type":"Point"}
}