{
  "type": "Feature",
  "properties": {
    "addr:full":"120 Northway Ct Raleigh NC 27615",
    "addr:housenumber":"120",
    "addr:postcode":"27615",
    "addr:street":"Northway Ct",
    "iso:country":"US",
    "sg:address":"120 Northway Ct",
    "sg:city":"Raleigh",
    "sg:classifiers":[
        {
            "category":"Health Services",
            "subcategory":"Medical Lab",
            "type":"Services"
        }
    ],
    "sg:phone":"+1   ",
    "sg:postcode":"27615",
    "sg:province":"NC",
    "sg:tags":[
        "laboratory",
        "dental"
    ],
    "wof:name":"Creative Dental Arts",
    "wof:placetype":"venue"
},
  "geometry": {"coordinates":[-78.647186,35.882512],"type":"Point"}
}