{
  "type": "Feature",
  "properties": {
    "iso:country":"US",
    "sg:address":"4996 Indiana Ave",
    "sg:city":"Winston Salem",
    "sg:classifiers":[
        {
            "category":"Manufacturing",
            "subcategory":"Building Materials",
            "type":"Manufacturing & Wholesale Goods"
        }
    ],
    "sg:phone":"+1 336 661 0730",
    "sg:postcode":"27106",
    "sg:province":"NC",
    "wof:name":"Brown Millwork LLC",
    "wof:placetype":"venue"
},
  "geometry": {"coordinates":[-80.278053,36.155301],"type":"Point"}
}