{
  "type": "Feature",
  "properties": {
    "addr:full":"1503 Hooker Rd Greenville NC 27834",
    "addr:housenumber":"1503",
    "addr:postcode":"27834",
    "addr:street":"Hooker Rd",
    "iso:country":"US",
    "sg:address":"1503 Hooker Rd",
    "sg:city":"Greenville",
    "sg:classifiers":[
        {
            "category":"Organizations",
            "subcategory":"Religious Organization",
            "type":"Services"
        }
    ],
    "sg:phone":"+1 252 757 3585",
    "sg:postcode":"27834",
    "sg:province":"NC",
    "sg:tags":[
        "church"
    ],
    "sg:website":"www.progressivefreewillbaptistchurch.com",
    "wof:name":"Progressive Free Wl Baptist Ch",
    "wof:placetype":"venue"
},
  "geometry": {"coordinates":[-77.39002600000001,35.579045],"type":"Point"}
}