{
  "type": "Feature",
  "properties": {
    "iso:country":"US",
    "sg:address":"263 Haywood St",
    "sg:city":"Asheville",
    "sg:classifiers":[
        {
            "category":"Professional",
            "type":"Services"
        }
    ],
    "sg:phone":"+1 828 253 2666",
    "sg:postcode":"28801",
    "sg:province":"NC",
    "sg:tags":[
        "establishment"
    ],
    "wof:name":"263 Haywood Street LLC",
    "wof:placetype":"venue"
},
  "geometry": {"coordinates":[-82.561353,35.594878],"type":"Point"}
}