{
  "type": "Feature",
  "properties": {
    "addr:full":"151 Avon Ave Washington NC 27889",
    "addr:housenumber":"151",
    "addr:postcode":"27889",
    "addr:street":"Avon Ave",
    "iso:country":"US",
    "sg:address":"151 Avon Ave",
    "sg:city":"Washington",
    "sg:classifiers":[
        {
            "category":"Education",
            "subcategory":"Dance Studio",
            "type":"Public Place"
        }
    ],
    "sg:phone":"+1   ",
    "sg:postcode":"27889",
    "sg:province":"NC",
    "wof:name":"Le Moulin Rouge De Danse Inc",
    "wof:placetype":"venue"
},
  "geometry": {"coordinates":[-77.03311600000001,35.550922],"type":"Point"}
}