{
  "type": "Feature",
  "properties": {
    "addr:full":"923 Union St S Concord NC 28025",
    "addr:housenumber":"923",
    "addr:postcode":"28025",
    "addr:street":"Union St S",
    "iso:country":"US",
    "sg:address":"923 Union St S",
    "sg:city":"Concord",
    "sg:classifiers":[
        {
            "category":"Social Services",
            "type":"Services"
        }
    ],
    "sg:phone":"+1 704 786 9711",
    "sg:postcode":"28025",
    "sg:province":"NC",
    "sg:tags":[
        "counseling"
    ],
    "wof:name":"Cabarrus Counseling Assoc",
    "wof:placetype":"venue"
},
  "geometry": {"coordinates":[-80.561196,35.388589],"type":"Point"}
}