{
  "type": "Feature",
  "properties": {
    "iso:country":"US",
    "sg:address":"201 E Ash St",
    "sg:city":"Goldsboro",
    "sg:classifiers":[
        {
            "category":"Banks & Credit Unions",
            "subcategory":"Bank",
            "type":"Services"
        }
    ],
    "sg:phone":"+1 919 731 7830",
    "sg:postcode":"27530",
    "sg:province":"NC",
    "sg:tags":[
        "state",
        "commercial"
    ],
    "sg:website":"www.centura.com",
    "wof:name":"RBC Centura Bank",
    "wof:placetype":"venue"
},
  "geometry": {"coordinates":[-77.992532,35.384751],"type":"Point"}
}