{
  "type": "Feature",
  "properties": {
    "addr:full":"9810 Gilead Rd Huntersville NC 28078",
    "addr:housenumber":"9810",
    "addr:postcode":"28078",
    "addr:street":"Gilead Rd",
    "iso:country":"US",
    "sg:address":"9810 Gilead Rd",
    "sg:city":"Huntersville",
    "sg:classifiers":[
        {
            "category":"Education",
            "subcategory":"Special Training",
            "type":"Public Place"
        },
        {
            "category":"Sports & Exercise",
            "subcategory":"Gym",
            "type":"Entertainment"
        },
        {
            "category":"Personal",
            "type":"Services"
        },
        {
            "category":"Arena",
            "subcategory":"Sports Club",
            "type":"Entertainment"
        }
    ],
    "sg:phone":"+1 704 234 6427",
    "sg:postcode":"28078",
    "sg:province":"NC",
    "sg:tags":[
        "trainer",
        "consultant",
        "instruction",
        "equipment",
        "self defense",
        "health",
        "fitness",
        "physical"
    ],
    "sg:website":"http://charlotte.citysearch.com/profile/external/649750050/huntersville_nc/the_little_gym_huntersville.html?publisher=yellowpages&reference_id=7&placement=ypwebsitemip",
    "wof:name":"The Little Gym Huntersville",
    "wof:placetype":"venue"
},
  "geometry": {"coordinates":[-80.863923,35.406676],"type":"Point"}
}