{
  "type": "Feature",
  "properties": {
    "iso:country":"US",
    "sg:address":"403 W Main St",
    "sg:city":"Spindale",
    "sg:classifiers":[
        {
            "category":"Food & Beverages",
            "subcategory":"Bakery",
            "type":"Retail Goods"
        }
    ],
    "sg:phone":"+1 828 286 9012",
    "sg:postcode":"28160",
    "sg:province":"NC",
    "sg:tags":[
        "baker"
    ],
    "wof:name":"Granny's Bakery & Sub Shop",
    "wof:placetype":"venue"
},
  "geometry": {"coordinates":[-81.935284,35.359181],"type":"Point"}
}