{
  "type": "Feature",
  "properties": {
    "addr:full":"255 Anthony Cir Charlotte NC 28211",
    "addr:housenumber":"255",
    "addr:postcode":"28211",
    "addr:street":"Anthony Cir",
    "iso:country":"US",
    "sg:address":"255 Anthony Cir",
    "sg:city":"Charlotte",
    "sg:classifiers":[
        {
            "category":"Wholesale",
            "subcategory":"Machinery & Supplies",
            "type":"Manufacturing & Wholesale Goods"
        }
    ],
    "sg:phone":"+1 704 366 7411",
    "sg:postcode":"28211",
    "sg:province":"NC",
    "sg:tags":[
        "tool"
    ],
    "wof:name":"Munkforssagar",
    "wof:placetype":"venue"
},
  "geometry": {"coordinates":[-80.802268,35.18409],"type":"Point"}
}