{
  "type": "Feature",
  "properties": {
    "iso:country":"US",
    "sg:address":"3778 N State Hwy 150",
    "sg:city":"Lexington",
    "sg:classifiers":[
        {
            "category":"Food & Beverages",
            "subcategory":"Groceries & Convenience Stores",
            "type":"Retail Goods"
        }
    ],
    "sg:phone":"+1 336 787 4448",
    "sg:postcode":"27295",
    "sg:province":"NC",
    "wof:name":"Reedy Creek Food Mart",
    "wof:placetype":"venue"
},
  "geometry": {"coordinates":[-80.322935,35.905515],"type":"Point"}
}