{
  "type": "Feature",
  "properties": {
    "addr:full":"1151 Horseshoe Rd Durham NC 27703",
    "addr:housenumber":"1151",
    "addr:postcode":"27703",
    "addr:street":"Horseshoe Rd",
    "iso:country":"US",
    "sg:address":"1151 Horseshoe Rd",
    "sg:city":"Durham",
    "sg:classifiers":[
        {
            "category":"Building & Trades",
            "subcategory":"Construction",
            "type":"Services"
        }
    ],
    "sg:phone":"+1 919 596 4997",
    "sg:postcode":"27703",
    "sg:province":"NC",
    "sg:tags":[
        "contractor"
    ],
    "wof:name":"Tyler Pool Construction Inc",
    "wof:placetype":"venue"
},
  "geometry": {"coordinates":[-78.840289,35.964846],"type":"Point"}
}