{
  "type": "Feature",
  "properties": {
    "addr:full":"132 Margaret Turner Rd Charlotte NC 28216",
    "addr:housenumber":"132",
    "addr:postcode":"28216",
    "addr:street":"Margaret Turner Rd",
    "iso:country":"US",
    "sg:address":"132 Margaret Turner Rd",
    "sg:city":"Charlotte",
    "sg:classifiers":[
        {
            "category":"Health Services",
            "subcategory":"Clinic",
            "type":"Services"
        }
    ],
    "sg:phone":"+1 704 398 8858",
    "sg:postcode":"28216",
    "sg:province":"NC",
    "wof:name":"Supernatural Health & Fitness",
    "wof:placetype":"venue"
},
  "geometry": {"coordinates":[-80.900499,35.28443],"type":"Point"}
}