{
  "type": "Feature",
  "properties": {
    "iso:country":"US",
    "sg:address":"4001 South Blvd",
    "sg:city":"Charlotte",
    "sg:classifiers":[
        {
            "category":"Food & Beverages",
            "subcategory":"Groceries & Convenience Stores",
            "type":"Retail Goods"
        }
    ],
    "sg:phone":"+1 704 527 5944",
    "sg:postcode":"28209",
    "sg:province":"NC",
    "wof:name":"Circle K",
    "wof:placetype":"venue"
},
  "geometry": {"coordinates":[-80.875777,35.182094],"type":"Point"}
}