{
  "type": "Feature",
  "properties": {
    "iso:country":"US",
    "sg:address":"109 Circadian Way",
    "sg:city":"Chapel Hill",
    "sg:classifiers":[
        {
            "category":"Travel",
            "subcategory":"Hotels & Motels",
            "type":"Entertainment"
        }
    ],
    "sg:phone":"+1 919 929 5553",
    "sg:postcode":"27516",
    "sg:province":"NC",
    "sg:tags":[
        "breakfast",
        "accommodation",
        "bed"
    ],
    "sg:website":"www.carolinamornings.com",
    "wof:name":"Carolina Mornings",
    "wof:placetype":"venue"
},
  "geometry": {"coordinates":[-79.098198,35.935501],"type":"Point"}
}