{
  "type": "Feature",
  "properties": {
    "addr:full":"2996 Forest Dr Randleman NC 27317",
    "addr:housenumber":"2996",
    "addr:postcode":"27317",
    "addr:street":"Forest Dr",
    "iso:country":"US",
    "sg:address":"2996 Forest Dr",
    "sg:city":"Randleman",
    "sg:classifiers":[
        {
            "category":"Retail",
            "subcategory":"Repair Shop",
            "type":"Services"
        }
    ],
    "sg:phone":"+1 336 498 3889",
    "sg:postcode":"27317",
    "sg:province":"NC",
    "sg:tags":[
        "appliance"
    ],
    "wof:name":"Woody's Service",
    "wof:placetype":"venue"
},
  "geometry": {"coordinates":[-79.80740400000001,35.799851],"type":"Point"}
}