{
  "type": "Feature",
  "properties": {
    "addr:full":"246 New Hope Dr Gastonia NC 28054",
    "addr:housenumber":"246",
    "addr:postcode":"28054",
    "addr:street":"New Hope Dr",
    "iso:country":"US",
    "sg:address":"246 New Hope Dr",
    "sg:city":"Gastonia",
    "sg:classifiers":[
        {
            "category":"Restaurant",
            "type":"Food & Drink"
        }
    ],
    "sg:phone":"+1 704 854 9588",
    "sg:postcode":"28054",
    "sg:province":"NC",
    "wof:name":"Mr Wok",
    "wof:placetype":"venue"
},
  "geometry": {"coordinates":[-81.15422700000001,35.262042],"type":"Point"}
}