{
  "type": "Feature",
  "properties": {
    "addr:full":"902 Fayetteville Rd Durham NC 27701",
    "addr:housenumber":"902",
    "addr:postcode":"27701",
    "addr:street":"Fayetteville Rd",
    "iso:country":"US",
    "sg:address":"902 Fayetteville Rd",
    "sg:city":"Durham",
    "sg:classifiers":[
        {
            "category":"Real Estate",
            "subcategory":"Real Estate Operator",
            "type":"Services"
        }
    ],
    "sg:phone":"+1 919 682 3622",
    "sg:postcode":"27701",
    "sg:province":"NC",
    "sg:tags":[
        "property",
        "management",
        "lessor",
        "ag"
    ],
    "wof:name":"Phoenix Square Associates",
    "wof:placetype":"venue"
},
  "geometry": {"coordinates":[-78.89851899999999,35.986202],"type":"Point"}
}