{
  "type": "Feature",
  "properties": {
    "iso:country":"US",
    "sg:address":"2032 Lightwood Bridge Rd",
    "sg:city":"Wallace",
    "sg:classifiers":[
        {
            "category":"Farming",
            "subcategory":"Farm",
            "type":"Manufacturing & Wholesale Goods"
        }
    ],
    "sg:phone":"+1 910 285 6164",
    "sg:postcode":"28466",
    "sg:province":"NC",
    "sg:tags":[
        "crop",
        "general"
    ],
    "wof:name":"Hendersons Swine Farm Inc",
    "wof:placetype":"venue"
},
  "geometry": {"coordinates":[-77.755304,34.739356],"type":"Point"}
}