{
  "type": "Feature",
  "properties": {
    "iso:country":"US",
    "sg:address":"261 Rag Rd",
    "sg:city":"Mocksville",
    "sg:classifiers":[
        {
            "category":"Professional",
            "subcategory":"Business Services",
            "type":"Services"
        }
    ],
    "sg:phone":"+1 336 998 4162",
    "sg:postcode":"27028",
    "sg:province":"NC",
    "sg:tags":[
        "auctioneer"
    ],
    "wof:name":"Speer Auctions",
    "wof:placetype":"venue"
},
  "geometry": {"coordinates":[-80.491489,35.850147],"type":"Point"}
}