{
  "type": "Feature",
  "properties": {
    "addr:full":"902 Fleming St Hendersonville NC 28791",
    "addr:housenumber":"902",
    "addr:postcode":"28791",
    "addr:street":"Fleming St",
    "iso:country":"US",
    "sg:address":"902 Fleming St",
    "sg:city":"Hendersonville",
    "sg:classifiers":[
        {
            "category":"Health Services",
            "subcategory":"Doctor",
            "type":"Services"
        }
    ],
    "sg:phone":"+1 828 693 4163",
    "sg:postcode":"28791",
    "sg:province":"NC",
    "sg:tags":[
        "dentist"
    ],
    "wof:name":"Ty E Hornsby DDS",
    "wof:placetype":"venue"
},
  "geometry": {"coordinates":[-82.466078,35.323089],"type":"Point"}
}