{
  "type": "Feature",
  "properties": {
    "addr:full":"237 W Front St Statesville NC 28677",
    "addr:housenumber":"237",
    "addr:postcode":"28677",
    "addr:street":"W Front St",
    "iso:country":"US",
    "sg:address":"237 W Front St",
    "sg:city":"Statesville",
    "sg:classifiers":[
        {
            "category":"Personal",
            "subcategory":"Beauty Salon",
            "type":"Services"
        }
    ],
    "sg:phone":"+1   ",
    "sg:postcode":"28677",
    "sg:province":"NC",
    "sg:tags":[
        "shop"
    ],
    "wof:name":"Artistic Endeavor",
    "wof:placetype":"venue"
},
  "geometry": {"coordinates":[-80.889459,35.782044],"type":"Point"}
}