{
  "type": "Feature",
  "properties": {
    "addr:full":"1823 State Hwy 55 Cary NC 27519",
    "addr:housenumber":"1823",
    "addr:postcode":"27519",
    "addr:street":"State Hwy 55",
    "iso:country":"US",
    "sg:address":"1823 State Hwy 55",
    "sg:city":"Cary",
    "sg:classifiers":[
        {
            "category":"Building & Trades",
            "subcategory":"Landscaping Services",
            "type":"Services"
        }
    ],
    "sg:phone":"+1 919 303 9745",
    "sg:postcode":"27519",
    "sg:province":"NC",
    "sg:tags":[
        "designer",
        "landscape"
    ],
    "wof:name":"Natural Stone Sculptures",
    "wof:placetype":"venue"
},
  "geometry": {"coordinates":[-78.875494,35.761671],"type":"Point"}
}