{
  "type": "Feature",
  "properties": {
    "iso:country":"US",
    "sg:address":"10875 Flowes Store Rd",
    "sg:city":"Midland",
    "sg:classifiers":[
        {
            "category":"Building & Trades",
            "subcategory":"Construction",
            "type":"Services"
        }
    ],
    "sg:phone":"+1 704 455 1418",
    "sg:postcode":"28107",
    "sg:province":"NC",
    "sg:tags":[
        "hanging",
        "contractor"
    ],
    "wof:name":"Soots Painting",
    "wof:placetype":"venue"
},
  "geometry": {"coordinates":[-80.576846,35.267717],"type":"Point"}
}