{
  "type": "Feature",
  "properties": {
    "iso:country":"US",
    "sg:address":"4570 Prospect Rd",
    "sg:city":"Maxton",
    "sg:classifiers":[
        {
            "category":"Personal",
            "subcategory":"Beauty Salon",
            "type":"Services"
        }
    ],
    "sg:phone":"+1 910 521 8090",
    "sg:postcode":"28364",
    "sg:province":"NC",
    "wof:name":"Irena's Stlying Salon",
    "wof:placetype":"venue"
},
  "geometry": {"coordinates":[-79.230531,34.733773],"type":"Point"}
}