{
  "type": "Feature",
  "properties": {
    "addr:full":"1117 N 20th St Morehead City NC 28557",
    "addr:housenumber":"1117",
    "addr:postcode":"28557",
    "addr:street":"N 20Th St",
    "iso:country":"US",
    "sg:address":"1117 N 20th St",
    "sg:city":"Morehead City",
    "sg:classifiers":[
        {
            "category":"Building & Trades",
            "subcategory":"Construction",
            "type":"Services"
        }
    ],
    "sg:phone":"+1 252 726 0663",
    "sg:postcode":"28557",
    "sg:province":"NC",
    "sg:tags":[
        "roofing",
        "contractor"
    ],
    "wof:name":"Advanced Roofing",
    "wof:placetype":"venue"
},
  "geometry": {"coordinates":[-76.73044899999999,34.735496],"type":"Point"}
}