{
  "type": "Feature",
  "properties": {
    "iso:country":"US",
    "sg:address":"2891 Gillespie St",
    "sg:city":"Fayetteville",
    "sg:classifiers":[
        {
            "category":"Real Estate",
            "subcategory":"Developer",
            "type":"Services"
        }
    ],
    "sg:phone":"+1 910 323 2933",
    "sg:postcode":"28306",
    "sg:province":"NC",
    "sg:tags":[
        "cemetery"
    ],
    "wof:name":"Fayetteville Memorial Cemetery",
    "wof:placetype":"venue"
},
  "geometry": {"coordinates":[-78.898816,35.003716],"type":"Point"}
}