{
  "type": "Feature",
  "properties": {
    "addr:full":"816 S Reilly Rd Fayetteville NC 28314",
    "addr:housenumber":"816",
    "addr:postcode":"28314",
    "addr:street":"S Reilly Rd",
    "iso:country":"US",
    "sg:address":"816 S Reilly Rd",
    "sg:city":"Fayetteville",
    "sg:classifiers":[
        {
            "category":"Retail",
            "subcategory":"Laundry & Dry Cleaning",
            "type":"Services"
        }
    ],
    "sg:phone":"+1 910 868 6100",
    "sg:postcode":"28314",
    "sg:province":"NC",
    "sg:tags":[
        "cleaners",
        "plant",
        "drycleaning"
    ],
    "wof:name":"J B Cleaners",
    "wof:placetype":"venue"
},
  "geometry": {"coordinates":[-79.015635,35.06094],"type":"Point"}
}