{
  "type": "Feature",
  "properties": {
    "iso:country":"US",
    "sg:address":"3105 Lowell Rd",
    "sg:city":"Gastonia",
    "sg:classifiers":[
        {
            "category":"Professional",
            "subcategory":"Business Services",
            "type":"Services"
        }
    ],
    "sg:phone":"+1   ",
    "sg:postcode":"28054",
    "sg:province":"NC",
    "wof:name":"Johnny H Bolick",
    "wof:placetype":"venue"
},
  "geometry": {"coordinates":[-81.11438699999999,35.274412],"type":"Point"}
}