{
  "type": "Feature",
  "properties": {
    "iso:country":"US",
    "sg:address":"942 S Cox St",
    "sg:city":"Asheboro",
    "sg:classifiers":[
        {
            "category":"Insurance",
            "subcategory":"Insurance Agent",
            "type":"Services"
        }
    ],
    "sg:phone":"+1 336 629 3660",
    "sg:postcode":"27203",
    "sg:province":"NC",
    "wof:name":"John C Andrews Insurance",
    "wof:placetype":"venue"
},
  "geometry": {"coordinates":[-79.813849,35.694418],"type":"Point"}
}