{
  "type": "Feature",
  "properties": {
    "iso:country":"US",
    "sg:address":"4008 Brevard Pl",
    "sg:city":"Raleigh",
    "sg:classifiers":[
        {
            "category":"Retail",
            "subcategory":"Animal Services",
            "type":"Services"
        }
    ],
    "sg:phone":"+1 919 782 5050",
    "sg:postcode":"27609",
    "sg:province":"NC",
    "sg:tags":[
        "pet"
    ],
    "wof:name":"Your Pet Id Ctr",
    "wof:placetype":"venue"
},
  "geometry": {"coordinates":[-78.629614,35.837695],"type":"Point"}
}