{
  "type": "Feature",
  "properties": {
    "iso:country":"US",
    "sg:address":"1010 Lexington Ave",
    "sg:city":"Thomasville",
    "sg:classifiers":[
        {
            "category":"Organizations",
            "subcategory":"Religious Organization",
            "type":"Services"
        }
    ],
    "sg:phone":"+1 336 472 7314",
    "sg:postcode":"27360",
    "sg:province":"NC",
    "sg:tags":[
        "church"
    ],
    "wof:name":"Greenwood Baptist Church",
    "wof:placetype":"venue"
},
  "geometry": {"coordinates":[-80.104894,35.882267],"type":"Point"}
}