{
  "type": "Feature",
  "properties": {
    "iso:country":"US",
    "sg:address":"2010 N Kerr Ave",
    "sg:city":"Wilmington",
    "sg:classifiers":[
        {
            "category":"Home & Garden",
            "subcategory":"Building Materials",
            "type":"Retail Goods"
        }
    ],
    "sg:phone":"+1 910 799 3448",
    "sg:postcode":"28405",
    "sg:province":"NC",
    "sg:tags":[
        "door"
    ],
    "wof:name":"Cape Fear Glass & Hardware",
    "wof:placetype":"venue"
},
  "geometry": {"coordinates":[-77.87662400000001,34.287815],"type":"Point"}
}