{
  "type": "Feature",
  "properties": {
    "addr:full":"3401 Autumn Mist Pl Fuquay Varina NC 27526",
    "addr:housenumber":"3401",
    "addr:postcode":"27526",
    "addr:street":"Autumn Mist Pl",
    "iso:country":"US",
    "sg:address":"3401 Autumn Mist Pl",
    "sg:city":"Fuquay Varina",
    "sg:classifiers":[
        {
            "category":"Professional",
            "subcategory":"Computer Services",
            "type":"Services"
        }
    ],
    "sg:phone":"+1   ",
    "sg:postcode":"27526",
    "sg:province":"NC",
    "sg:tags":[
        "datum"
    ],
    "wof:name":"Thomas E Cherry",
    "wof:placetype":"venue"
},
  "geometry": {"coordinates":[-78.76813,35.634107],"type":"Point"}
}