{
  "type": "Feature",
  "properties": {
    "addr:full":"7853 Old Beulah Rd Kenly NC 27542",
    "addr:housenumber":"7853",
    "addr:postcode":"27542",
    "addr:street":"Old Beulah Rd",
    "iso:country":"US",
    "sg:address":"7853 Old Beulah Rd",
    "sg:city":"Kenly",
    "sg:classifiers":[
        {
            "category":"Farming",
            "subcategory":"Livestock Farm",
            "type":"Manufacturing & Wholesale Goods"
        }
    ],
    "sg:phone":"+1 919 284 2646",
    "sg:postcode":"27542",
    "sg:province":"NC",
    "sg:tags":[
        "beef",
        "feedlot",
        "cattle"
    ],
    "wof:name":"Cloverdale Farm",
    "wof:placetype":"venue"
},
  "geometry": {"coordinates":[-78.207634,35.623976],"type":"Point"}
}