{
  "type": "Feature",
  "properties": {
    "iso:country":"US",
    "sg:address":"3380 Freedom Way",
    "sg:city":"Hubert",
    "sg:classifiers":[
        {
            "category":"Building & Trades",
            "subcategory":"Plumbing",
            "type":"Services"
        }
    ],
    "sg:phone":"+1 910 326 2412",
    "sg:postcode":"28539",
    "sg:province":"NC",
    "sg:tags":[
        "plumbing",
        "contractor"
    ],
    "wof:name":"Boot's Plumbing",
    "wof:placetype":"venue"
},
  "geometry": {"coordinates":[-77.195999,34.716764],"type":"Point"}
}