{
  "type": "Feature",
  "properties": {
    "addr:full":"1203 S Holden Rd Greensboro NC 27407",
    "addr:housenumber":"1203",
    "addr:postcode":"27407",
    "addr:street":"S Holden Rd",
    "iso:country":"US",
    "sg:address":"1203 S Holden Rd",
    "sg:city":"Greensboro",
    "sg:classifiers":[
        {
            "category":"Insurance",
            "subcategory":"Insurance Agent",
            "type":"Services"
        }
    ],
    "sg:phone":"+1 336 299 3029",
    "sg:postcode":"27407",
    "sg:province":"NC",
    "wof:name":"State Farm Insurance",
    "wof:placetype":"venue"
},
  "geometry": {"coordinates":[-79.841769,36.056961],"type":"Point"}
}