{
  "type": "Feature",
  "properties": {
    "addr:full":"2075 N Marine Blvd Jacksonville NC 28546",
    "addr:housenumber":"2075",
    "addr:postcode":"28546",
    "addr:street":"N Marine Blvd",
    "iso:country":"US",
    "sg:address":"2075 N Marine Blvd",
    "sg:city":"Jacksonville",
    "sg:classifiers":[
        {
            "category":"Shopping",
            "subcategory":"Computers & Home Electronics",
            "type":"Retail Goods"
        }
    ],
    "sg:phone":"+1 910 347 7554",
    "sg:postcode":"28546",
    "sg:province":"NC",
    "sg:tags":[
        "equipment",
        "electronic",
        "supply"
    ],
    "wof:name":"Radio Shack",
    "wof:placetype":"venue"
},
  "geometry": {"coordinates":[-77.388796,34.780283],"type":"Point"}
}