{
  "type": "Feature",
  "properties": {
    "iso:country":"US",
    "sg:address":"2517 Horne Dr",
    "sg:city":"Charlotte",
    "sg:classifiers":[
        {
            "category":"Professional",
            "subcategory":"Secretarial Services",
            "type":"Services"
        }
    ],
    "sg:phone":"+1   ",
    "sg:postcode":"28206",
    "sg:province":"NC",
    "sg:tags":[
        "publisher",
        "specialty"
    ],
    "wof:name":"Word In Season Publications",
    "wof:placetype":"venue"
},
  "geometry": {"coordinates":[-80.838183,35.256133],"type":"Point"}
}