{
  "type": "Feature",
  "properties": {
    "addr:full":"2447 Shell Point Rd SW South Brunswick NC 28470",
    "addr:housenumber":"2447",
    "addr:postcode":"28470",
    "addr:street":"Shell Point Rd Sw",
    "iso:country":"US",
    "sg:address":"2447 Shell Point Rd SW",
    "sg:city":"South Brunswick",
    "sg:classifiers":[
        {
            "category":"Freight",
            "type":"Transportation"
        }
    ],
    "sg:phone":"+1 910 754 7780",
    "sg:postcode":"28470",
    "sg:province":"NC",
    "sg:tags":[
        "operator",
        "local",
        "hauling",
        "trucking"
    ],
    "wof:name":"Theodore R Johnson Sr Trucking",
    "wof:placetype":"venue"
},
  "geometry": {"coordinates":[-78.33429099999999,33.96134],"type":"Point"}
}