{
  "type": "Feature",
  "properties": {
    "iso:country":"US",
    "sg:address":"215 Washboard Rd",
    "sg:city":"Thomasville",
    "sg:classifiers":[
        {
            "category":"Manufacturing",
            "subcategory":"Lumber",
            "type":"Manufacturing & Wholesale Goods"
        }
    ],
    "sg:phone":"+1 336 475 8173",
    "sg:postcode":"27360",
    "sg:province":"NC",
    "sg:tags":[
        "manufacture",
        "wooden",
        "frame",
        "furniture"
    ],
    "wof:name":"Frame Builders Inc",
    "wof:placetype":"venue"
},
  "geometry": {"coordinates":[-80.06380799999999,35.915178],"type":"Point"}
}