{
  "type": "Feature",
  "properties": {
    "iso:country":"US",
    "sg:address":"514 S Kerr Ave",
    "sg:city":"Wilmington",
    "sg:classifiers":[
        {
            "category":"Building & Trades",
            "subcategory":"Construction",
            "type":"Services"
        }
    ],
    "sg:phone":"+1 910 793 1207",
    "sg:postcode":"28403",
    "sg:province":"NC",
    "sg:tags":[
        "house"
    ],
    "wof:name":"Dan Martin Construction",
    "wof:placetype":"venue"
},
  "geometry": {"coordinates":[-77.887106,34.230319],"type":"Point"}
}