{
  "type": "Feature",
  "properties": {
    "addr:full":"2814 Reid Meadows Dr Charlotte NC 28208",
    "addr:housenumber":"2814",
    "addr:postcode":"28208",
    "addr:street":"Reid Meadows Dr",
    "iso:country":"US",
    "sg:address":"2814 Reid Meadows Dr",
    "sg:city":"Charlotte",
    "sg:classifiers":[
        {
            "category":"Cinema",
            "subcategory":"Movie Rental",
            "type":"Entertainment"
        }
    ],
    "sg:phone":"+1 704 391 0223",
    "sg:postcode":"28208",
    "sg:province":"NC",
    "sg:tags":[
        "motion",
        "picture",
        "distributor",
        "film",
        "exchange"
    ],
    "wof:name":"Big Keyz Productions",
    "wof:placetype":"venue"
},
  "geometry": {"coordinates":[-80.913147,35.245449],"type":"Point"}
}