{
  "type": "Feature",
  "properties": {
    "iso:country":"US",
    "sg:address":"6133 River Landings Dr",
    "sg:city":"Raleigh",
    "sg:classifiers":[
        {
            "category":"Professional",
            "type":"Services"
        }
    ],
    "sg:phone":"+1 919 878 7248",
    "sg:postcode":"27604",
    "sg:province":"NC",
    "wof:name":"Creative Covers Inc",
    "wof:placetype":"venue"
},
  "geometry": {"coordinates":[-78.535268,35.84537],"type":"Point"}
}