{
  "type": "Feature",
  "properties": {
    "iso:country":"US",
    "sg:address":"76 Mountain View Rd",
    "sg:city":"Asheville",
    "sg:classifiers":[
        {
            "category":"Building & Trades",
            "subcategory":"Construction",
            "type":"Services"
        }
    ],
    "sg:phone":"+1 828 665 9776",
    "sg:postcode":"28806",
    "sg:province":"NC",
    "sg:tags":[
        "contractor"
    ],
    "wof:name":"Genesis Construction Co",
    "wof:placetype":"venue"
},
  "geometry": {"coordinates":[-82.648911,35.581584],"type":"Point"}
}