{
  "type": "Feature",
  "properties": {
    "iso:country":"US",
    "sg:address":"283 T Johnson Rd",
    "sg:city":"Carthage",
    "sg:classifiers":[
        {
            "category":"Building & Trades",
            "subcategory":"Construction",
            "type":"Services"
        }
    ],
    "sg:phone":"+1 910 947 2188",
    "sg:postcode":"28327",
    "sg:province":"NC",
    "sg:tags":[
        "house",
        "electrical",
        "contractor"
    ],
    "wof:name":"Powerhouse Enterprises",
    "wof:placetype":"venue"
},
  "geometry": {"coordinates":[-79.320711,35.351447],"type":"Point"}
}