{
  "type": "Feature",
  "properties": {
    "iso:country":"US",
    "sg:address":"107 Barnes St W",
    "sg:city":"Wilson",
    "sg:classifiers":[
        {
            "category":"Parking",
            "type":"Transportation"
        }
    ],
    "sg:phone":"+1   ",
    "sg:postcode":"27893",
    "sg:province":"NC",
    "sg:tags":[
        "automobile"
    ],
    "wof:name":"Wilson City Parking Lot",
    "wof:placetype":"venue"
},
  "geometry": {"coordinates":[-77.913263,35.725718],"type":"Point"}
}