{
  "type": "Feature",
  "properties": {
    "iso:country":"US",
    "sg:address":"160 Shue Rd",
    "sg:city":"China Grove",
    "sg:classifiers":[
        {
            "category":"Professional",
            "subcategory":"Business Services",
            "type":"Services"
        }
    ],
    "sg:phone":"+1 704 857 1500",
    "sg:postcode":"28023",
    "sg:province":"NC",
    "sg:tags":[
        "ornamental",
        "nursery"
    ],
    "wof:name":"Surf & Turf Sales & Marketing",
    "wof:placetype":"venue"
},
  "geometry": {"coordinates":[-80.56670800000001,35.578675],"type":"Point"}
}