{
  "type": "Feature",
  "properties": {
    "iso:country":"US",
    "sg:address":"403 Peninsula Dr",
    "sg:city":"Carolina Beach",
    "sg:classifiers":[
        {
            "category":"Real Estate",
            "subcategory":"Real Estate Agent",
            "type":"Services"
        }
    ],
    "sg:phone":"+1 910 458 7815",
    "sg:postcode":"28428",
    "sg:province":"NC",
    "wof:name":"April McDavid Realtor Inc",
    "wof:placetype":"venue"
},
  "geometry": {"coordinates":[-77.89649799999999,34.053034],"type":"Point"}
}