{
  "type": "Feature",
  "properties": {
    "addr:full":"2507 Wilson Rd Chapel Hill NC 27516",
    "addr:housenumber":"2507",
    "addr:postcode":"27516",
    "addr:street":"Wilson Rd",
    "iso:country":"US",
    "sg:address":"2507 Wilson Rd",
    "sg:city":"Chapel Hill",
    "sg:classifiers":[
        {
            "category":"Building & Trades",
            "subcategory":"Construction",
            "type":"Services"
        }
    ],
    "sg:phone":"+1 919 929 5724",
    "sg:postcode":"27516",
    "sg:province":"NC",
    "wof:name":"Reclamation Services Inc",
    "wof:placetype":"venue"
},
  "geometry": {"coordinates":[-79.122624,35.878942],"type":"Point"}
}