{
  "type": "Feature",
  "properties": {
    "addr:full":"2215 Waterford Forest Cir Cary NC 27513",
    "addr:housenumber":"2215",
    "addr:postcode":"27513",
    "addr:street":"Waterford Forest Cir",
    "iso:country":"US",
    "sg:address":"2215 Waterford Forest Cir",
    "sg:city":"Cary",
    "sg:classifiers":[
        {
            "category":"Professional",
            "type":"Services"
        }
    ],
    "sg:phone":"+1 919 467 3914",
    "sg:postcode":"27513",
    "sg:province":"NC",
    "sg:tags":[
        "establishment"
    ],
    "wof:name":"Railinc Oc",
    "wof:placetype":"venue"
},
  "geometry": {"coordinates":[-78.80708199999999,35.787172],"type":"Point"}
}