{
  "type": "Feature",
  "properties": {
    "iso:country":"US",
    "sg:address":"207 E Rosemary St",
    "sg:city":"Chapel Hill",
    "sg:classifiers":[
        {
            "category":"Retail",
            "subcategory":"Laundry & Dry Cleaning",
            "type":"Services"
        }
    ],
    "sg:phone":"+1 919 929 1500",
    "sg:postcode":"27514",
    "sg:province":"NC",
    "sg:tags":[
        "cleaners",
        "rug",
        "carpet"
    ],
    "wof:name":"Bright & Clear Floor Care",
    "wof:placetype":"venue"
},
  "geometry": {"coordinates":[-79.053104,35.915333],"type":"Point"}
}