{
  "type": "Feature",
  "properties": {
    "iso:country":"US",
    "sg:address":"1624 Mc Knight Mill Rd",
    "sg:city":"Greensboro",
    "sg:classifiers":[
        {
            "category":"Building & Trades",
            "subcategory":"Construction",
            "type":"Services"
        }
    ],
    "sg:phone":"+1 336 451 4111",
    "sg:postcode":"27405",
    "sg:province":"NC",
    "sg:tags":[
        "carpenter"
    ],
    "wof:name":"Sosa Carpentry",
    "wof:placetype":"venue"
},
  "geometry": {"coordinates":[-79.76070199999999,36.117627],"type":"Point"}
}