{
  "type": "Feature",
  "properties": {
    "iso:country":"US",
    "sg:address":"301 E Washington St",
    "sg:city":"Greensboro",
    "sg:classifiers":[
        {
            "category":"Social Services",
            "type":"Services"
        }
    ],
    "sg:phone":"+1 336 333 6890",
    "sg:postcode":"27401",
    "sg:province":"NC",
    "wof:name":"Family Life Cnl of Grtr Grnsbr",
    "wof:placetype":"venue"
},
  "geometry": {"coordinates":[-79.785399,36.069989],"type":"Point"}
}