{
  "type": "Feature",
  "properties": {
    "addr:full":"608 Airport Rd Kinston NC 28504",
    "addr:housenumber":"608",
    "addr:postcode":"28504",
    "addr:street":"Airport Rd",
    "iso:country":"US",
    "sg:address":"608 Airport Rd",
    "sg:city":"Kinston",
    "sg:classifiers":[
        {
            "category":"Health Services",
            "subcategory":"Doctor",
            "type":"Services"
        }
    ],
    "sg:phone":"+1 252 523 8513",
    "sg:postcode":"28504",
    "sg:province":"NC",
    "sg:tags":[
        "physician",
        "surgeon"
    ],
    "wof:name":"Nawaf G Atassi MD",
    "wof:placetype":"venue"
},
  "geometry": {"coordinates":[-77.589135,35.301118],"type":"Point"}
}