{
  "type": "Feature",
  "properties": {
    "addr:full":"560 Malcolm Blvd Rutherford Clg NC 28671",
    "addr:housenumber":"560",
    "addr:postcode":"28671",
    "addr:street":"Malcolm Blvd",
    "iso:country":"US",
    "sg:address":"560 Malcolm Blvd",
    "sg:city":"Rutherford Clg",
    "sg:classifiers":[
        {
            "category":"Health Services",
            "subcategory":"Medical Lab",
            "type":"Services"
        }
    ],
    "sg:phone":"+1 828 874 2291",
    "sg:postcode":"28671",
    "sg:province":"NC",
    "sg:tags":[
        "x"
    ],
    "wof:name":"Western Piedmont Imaging Ctr",
    "wof:placetype":"venue"
},
  "geometry": {"coordinates":[-81.526201,35.743503],"type":"Point"}
}