{
  "type": "Feature",
  "properties": {
    "addr:full":"201 Waters Cir Goldsboro NC 27534",
    "addr:housenumber":"201",
    "addr:postcode":"27534",
    "addr:street":"Waters Cir",
    "iso:country":"US",
    "sg:address":"201 Waters Cir",
    "sg:city":"Goldsboro",
    "sg:classifiers":[
        {
            "category":"Professional",
            "subcategory":"Business Services",
            "type":"Services"
        }
    ],
    "sg:phone":"+1   ",
    "sg:postcode":"27534",
    "sg:province":"NC",
    "wof:name":"Ad Agency Online",
    "wof:placetype":"venue"
},
  "geometry": {"coordinates":[-77.909375,35.379722],"type":"Point"}
}