{
  "type": "Feature",
  "properties": {
    "addr:full":"925 S Kerr Ave Wilmington NC 28403",
    "addr:housenumber":"925",
    "addr:postcode":"28403",
    "addr:street":"S Kerr Ave",
    "iso:country":"US",
    "sg:address":"925 S Kerr Ave",
    "sg:city":"Wilmington",
    "sg:classifiers":[
        {
            "category":"Restaurant",
            "type":"Food & Drink"
        }
    ],
    "sg:phone":"+1 910 799 7363",
    "sg:postcode":"28403",
    "sg:province":"NC",
    "wof:name":"Coastal Carolina Food Corp",
    "wof:placetype":"venue"
},
  "geometry": {"coordinates":[-77.886842,34.217718],"type":"Point"}
}