{
  "type": "Feature",
  "properties": {
    "iso:country":"US",
    "sg:address":"1017 Burke St NW",
    "sg:city":"Winston Salem",
    "sg:classifiers":[
        {
            "category":"Building & Trades",
            "subcategory":"Electrical",
            "type":"Services"
        }
    ],
    "sg:phone":"+1 336 722 9721",
    "sg:postcode":"27101",
    "sg:province":"NC",
    "sg:tags":[
        "electrical",
        "contractor"
    ],
    "wof:name":"Tom Wood Electric Co",
    "wof:placetype":"venue"
},
  "geometry": {"coordinates":[-80.258388,36.094444],"type":"Point"}
}