{
  "type": "Feature",
  "properties": {
    "iso:country":"US",
    "sg:address":"2395 Stone Chimney Rd SW",
    "sg:city":"Supply",
    "sg:classifiers":[
        {
            "category":"Real Estate",
            "subcategory":"Real Estate Agent",
            "type":"Services"
        }
    ],
    "sg:phone":"+1 910 842 6681",
    "sg:postcode":"28462",
    "sg:province":"NC",
    "wof:name":"Frederick Raines",
    "wof:placetype":"venue"
},
  "geometry": {"coordinates":[-78.25709500000001,33.94949],"type":"Point"}
}