{
  "type": "Feature",
  "properties": {
    "iso:country":"US",
    "sg:address":"10198 Red Hill Rd",
    "sg:city":"Clarkton",
    "sg:classifiers":[
        {
            "category":"Real Estate",
            "subcategory":"Real Estate Operator",
            "type":"Services"
        }
    ],
    "sg:phone":"+1 910 647 1261",
    "sg:postcode":"28433",
    "sg:province":"NC",
    "sg:tags":[
        "property",
        "lessor"
    ],
    "wof:name":"Austin Baldwin",
    "wof:placetype":"venue"
},
  "geometry": {"coordinates":[-78.66310199999999,34.43304],"type":"Point"}
}