{
  "type": "Feature",
  "properties": {
    "iso:country":"US",
    "sg:address":"213 E Main St",
    "sg:city":"Lincolnton",
    "sg:classifiers":[
        {
            "category":"Shopping",
            "subcategory":"Jewelry",
            "type":"Retail Goods"
        }
    ],
    "sg:phone":"+1 704 735 6313",
    "sg:postcode":"28092",
    "sg:province":"NC",
    "sg:tags":[
        "jeweler"
    ],
    "wof:name":"Rankin's Jewelers",
    "wof:placetype":"venue"
},
  "geometry": {"coordinates":[-81.254295,35.472296],"type":"Point"}
}