{
  "type": "Feature",
  "properties": {
    "addr:full":"2642 Carolina Beach Rd Wilmington NC 28412",
    "addr:housenumber":"2642",
    "addr:postcode":"28412",
    "addr:street":"Carolina Beach Rd",
    "iso:country":"US",
    "sg:address":"2642 Carolina Beach Rd",
    "sg:city":"Wilmington",
    "sg:classifiers":[
        {
            "category":"Retail",
            "subcategory":"Auto Rental",
            "type":"Services"
        }
    ],
    "sg:phone":"+1 910 397 9110",
    "sg:postcode":"28412",
    "sg:province":"NC",
    "sg:tags":[
        "passenger",
        "car"
    ],
    "wof:name":"Elrac Inc",
    "wof:placetype":"venue"
},
  "geometry": {"coordinates":[-77.933435,34.189904],"type":"Point"}
}