{
  "type": "Feature",
  "properties": {
    "addr:full":"141 S Powell St Forest City NC 28043",
    "addr:housenumber":"141",
    "addr:postcode":"28043",
    "addr:street":"S Powell St",
    "iso:country":"US",
    "sg:address":"141 S Powell St",
    "sg:city":"Forest City",
    "sg:classifiers":[
        {
            "category":"Real Estate",
            "subcategory":"Real Estate Agent",
            "type":"Services"
        }
    ],
    "sg:phone":"+1 828 248 1612",
    "sg:postcode":"28043",
    "sg:province":"NC",
    "sg:tags":[
        "appraiser"
    ],
    "wof:name":"Mellnik Real Estate Svc",
    "wof:placetype":"venue"
},
  "geometry": {"coordinates":[-81.863449,35.332402],"type":"Point"}
}