{
  "type": "Feature",
  "properties": {
    "addr:full":"102 W Mountain Rd Spruce Pine NC 28777",
    "addr:housenumber":"102",
    "addr:postcode":"28777",
    "addr:street":"W Mountain Rd",
    "iso:country":"US",
    "sg:address":"102 W Mountain Rd",
    "sg:city":"Spruce Pine",
    "sg:classifiers":[
        {
            "category":"Freight",
            "type":"Transportation"
        }
    ],
    "sg:phone":"+1 828 765 1944",
    "sg:postcode":"28777",
    "sg:province":"NC",
    "sg:tags":[
        "operator",
        "local",
        "trucking"
    ],
    "wof:name":"Staton Trucking Co Inc",
    "wof:placetype":"venue"
},
  "geometry": {"coordinates":[-82.032954,35.927518],"type":"Point"}
}