{
  "type": "Feature",
  "properties": {
    "iso:country":"US",
    "sg:address":"2641 Appliance Ct",
    "sg:city":"Raleigh",
    "sg:classifiers":[
        {
            "category":"Travel",
            "subcategory":"Hotels & Motels",
            "type":"Entertainment"
        }
    ],
    "sg:phone":"+1 800 424 6423",
    "sg:postcode":"27604",
    "sg:province":"NC",
    "sg:website":"http://www.econolodge.com/hotel-raleigh-north_carolina-NC487?promo=yplocal",
    "wof:name":"Econo Lodge Raleigh",
    "wof:placetype":"venue"
},
  "geometry": {"coordinates":[-78.602058,35.813141],"type":"Point"}
}