{
  "type": "Feature",
  "properties": {
    "addr:full":"5591 Dwight Dr Mc Leansville NC 27301",
    "addr:housenumber":"5591",
    "addr:postcode":"27301",
    "addr:street":"Dwight Dr",
    "iso:country":"US",
    "sg:address":"5591 Dwight Dr",
    "sg:city":"Mc Leansville",
    "sg:classifiers":[
        {
            "category":"Building & Trades",
            "subcategory":"Construction",
            "type":"Services"
        }
    ],
    "sg:phone":"+1 336 656 3279",
    "sg:postcode":"27301",
    "sg:province":"NC",
    "sg:tags":[
        "house"
    ],
    "wof:name":"Tran Home Improvement Inc",
    "wof:placetype":"venue"
},
  "geometry": {"coordinates":[-79.688086,36.157849],"type":"Point"}
}