{
  "type": "Feature",
  "properties": {
    "iso:country":"US",
    "sg:address":"70 Crape Myrtle Dr",
    "sg:city":"Benson",
    "sg:classifiers":[
        {
            "category":"Health Services",
            "subcategory":"Hospital",
            "type":"Services"
        },
        {
            "category":"Health Services",
            "subcategory":"Doctor",
            "type":"Services"
        }
    ],
    "sg:phone":"+1 919 938 0260",
    "sg:postcode":"27504",
    "sg:province":"NC",
    "sg:tags":[
        "physician",
        "surgeon",
        "general"
    ],
    "wof:name":"Johnston Family Care Center",
    "wof:placetype":"venue"
},
  "geometry": {"coordinates":[-78.554557,35.516737],"type":"Point"}
}