{
  "type": "Feature",
  "properties": {
    "addr:full":"303 Ross St Asheboro NC 27203",
    "addr:housenumber":"303",
    "addr:postcode":"27203",
    "addr:street":"Ross St",
    "iso:country":"US",
    "sg:address":"303 Ross St",
    "sg:city":"Asheboro",
    "sg:classifiers":[
        {
            "category":"Health Services",
            "subcategory":"Doctor",
            "type":"Services"
        }
    ],
    "sg:phone":"+1 336 318 1014",
    "sg:postcode":"27203",
    "sg:province":"NC",
    "sg:tags":[
        "dentist"
    ],
    "wof:name":"Marina C Bonaventura DDS",
    "wof:placetype":"venue"
},
  "geometry": {"coordinates":[-79.818806,35.711064],"type":"Point"}
}