{
  "type": "Feature",
  "properties": {
    "addr:full":"1610 E Dixon Blvd Shelby NC 28152",
    "addr:housenumber":"1610",
    "addr:postcode":"28152",
    "addr:street":"E Dixon Blvd",
    "iso:country":"US",
    "sg:address":"1610 E Dixon Blvd",
    "sg:city":"Shelby",
    "sg:classifiers":[
        {
            "category":"Home & Garden",
            "subcategory":"Building Materials",
            "type":"Retail Goods"
        }
    ],
    "sg:phone":"+1 704 482 7431",
    "sg:postcode":"28152",
    "sg:province":"NC",
    "wof:name":"Roundup Store",
    "wof:placetype":"venue"
},
  "geometry": {"coordinates":[-81.511253,35.272812],"type":"Point"}
}