{
  "type": "Feature",
  "properties": {
    "iso:country":"US",
    "sg:address":"2024 W 5th St",
    "sg:city":"Washington",
    "sg:classifiers":[
        {
            "category":"Manufacturing",
            "subcategory":"Rubber & Plastics",
            "type":"Manufacturing & Wholesale Goods"
        }
    ],
    "sg:phone":"+1 252 940 0900",
    "sg:postcode":"27889",
    "sg:province":"NC",
    "sg:tags":[
        "forming"
    ],
    "wof:name":"Maxwell Industries",
    "wof:placetype":"venue"
},
  "geometry": {"coordinates":[-77.08759999999999,35.577849],"type":"Point"}
}