{
  "type": "Feature",
  "properties": {
    "addr:full":"1204 Red Ash Cir Durham NC 27704",
    "addr:housenumber":"1204",
    "addr:postcode":"27704",
    "addr:street":"Red Ash Cir",
    "iso:country":"US",
    "sg:address":"1204 Red Ash Cir",
    "sg:city":"Durham",
    "sg:classifiers":[
        {
            "category":"Organizations",
            "subcategory":"Religious Organization",
            "type":"Services"
        }
    ],
    "sg:phone":"+1 919 477 1038",
    "sg:postcode":"27704",
    "sg:province":"NC",
    "wof:name":"Gives Truth Center",
    "wof:placetype":"venue"
},
  "geometry": {"coordinates":[-78.920993,36.057984],"type":"Point"}
}