{
  "type": "Feature",
  "properties": {
    "iso:country":"US",
    "sg:address":"107 Tuscarora Nation Rd",
    "sg:city":"Maxton",
    "sg:classifiers":[
        {
            "category":"Organizations",
            "subcategory":"Non-profit Organization",
            "type":"Services"
        }
    ],
    "sg:phone":"+1 910 844 3352",
    "sg:postcode":"28364",
    "sg:province":"NC",
    "wof:name":"Tuscarora Indian Handcraft Shp",
    "wof:placetype":"venue"
},
  "geometry": {"coordinates":[-79.319419,34.75213],"type":"Point"}
}