{
  "type": "Feature",
  "properties": {
    "addr:full":"714 N College Rd Wilmington NC 28405",
    "addr:housenumber":"714",
    "addr:postcode":"28405",
    "addr:street":"N College Rd",
    "iso:country":"US",
    "sg:address":"714 N College Rd",
    "sg:city":"Wilmington",
    "sg:classifiers":[
        {
            "category":"Health Services",
            "subcategory":"Chiropractor",
            "type":"Services"
        }
    ],
    "sg:phone":"+1   ",
    "sg:postcode":"28405",
    "sg:province":"NC",
    "wof:name":"Health Care Clinic",
    "wof:placetype":"venue"
},
  "geometry": {"coordinates":[-77.870248,34.258646],"type":"Point"}
}