{
  "type": "Feature",
  "properties": {
    "iso:country":"US",
    "sg:address":"80 28th St NW",
    "sg:city":"Hickory",
    "sg:classifiers":[
        {
            "category":"Organizations",
            "subcategory":"Religious Organization",
            "type":"Services"
        }
    ],
    "sg:phone":"+1   ",
    "sg:postcode":"28601",
    "sg:province":"NC",
    "wof:name":"Bethel United Methodist",
    "wof:placetype":"venue"
},
  "geometry": {"coordinates":[-81.385034,35.730208],"type":"Point"}
}