{
  "type": "Feature",
  "properties": {
    "iso:country":"US",
    "sg:address":"1200 Branch St",
    "sg:city":"Rocky Mount",
    "sg:classifiers":[
        {
            "category":"Organizations",
            "subcategory":"Religious Organization",
            "type":"Services"
        }
    ],
    "sg:phone":"+1 252 446 4776",
    "sg:postcode":"27801",
    "sg:province":"NC",
    "sg:tags":[
        "church"
    ],
    "wof:name":"Salvation & Praise Tabernacle",
    "wof:placetype":"venue"
},
  "geometry": {"coordinates":[-77.79231799999999,35.927125],"type":"Point"}
}