{
  "type": "Feature",
  "properties": {
    "addr:full":"861 Old Knight Rd Knightdale NC 27545",
    "addr:housenumber":"861",
    "addr:postcode":"27545",
    "addr:street":"Old Knight Rd",
    "iso:country":"US",
    "sg:address":"861 Old Knight Rd",
    "sg:city":"Knightdale",
    "sg:classifiers":[
        {
            "category":"Personal",
            "subcategory":"Beauty Salon",
            "type":"Services"
        }
    ],
    "sg:phone":"+1 919 266 2025",
    "sg:postcode":"27545",
    "sg:province":"NC",
    "wof:name":"Chajuan Cox Agency",
    "wof:placetype":"venue"
},
  "geometry": {"coordinates":[-78.473643,35.803849],"type":"Point"}
}