{
  "type": "Feature",
  "properties": {
    "iso:country":"US",
    "sg:address":"200 N Bragg Blvd",
    "sg:city":"Spring Lake",
    "sg:classifiers":[
        {
            "category":"Autos & Motor Vehicles",
            "subcategory":"Fuel & Gas Station",
            "type":"Retail Goods"
        }
    ],
    "sg:phone":"+1 910 497 2152",
    "sg:postcode":"28390",
    "sg:province":"NC",
    "sg:tags":[
        "oil"
    ],
    "wof:name":"Darden's Exxon",
    "wof:placetype":"venue"
},
  "geometry": {"coordinates":[-78.973448,35.169083],"type":"Point"}
}