{
  "type": "Feature",
  "properties": {
    "iso:country":"US",
    "sg:address":"7529 Mariner Cove Dr",
    "sg:city":"Cornelius",
    "sg:classifiers":[
        {
            "category":"Building & Trades",
            "subcategory":"Construction",
            "type":"Services"
        }
    ],
    "sg:phone":"+1 704 763 8809",
    "sg:postcode":"28031",
    "sg:province":"NC",
    "sg:tags":[
        "boring",
        "drilling",
        "contractor"
    ],
    "wof:name":"Fast Tap Of North Carolina",
    "wof:placetype":"venue"
},
  "geometry": {"coordinates":[-80.895296,35.44773],"type":"Point"}
}