{
  "type": "Feature",
  "properties": {
    "iso:country":"US",
    "sg:address":"4355 Golf Acres Dr",
    "sg:city":"Charlotte",
    "sg:classifiers":[
        {
            "category":"Professional",
            "subcategory":"Art Services",
            "type":"Services"
        }
    ],
    "sg:phone":"+1 704 393 8873",
    "sg:postcode":"28208",
    "sg:province":"NC",
    "sg:tags":[
        "consultant",
        "designer",
        "lighting"
    ],
    "wof:name":"Smith Turf & Irrigation Co",
    "wof:placetype":"venue"
},
  "geometry": {"coordinates":[-80.916009,35.22421],"type":"Point"}
}