{
  "type": "Feature",
  "properties": {
    "addr:full":"1700 Skibo Rd Fayetteville NC 28303",
    "addr:housenumber":"1700",
    "addr:postcode":"28303",
    "addr:street":"Skibo Rd",
    "iso:country":"US",
    "sg:address":"1700 Skibo Rd",
    "sg:city":"Fayetteville",
    "sg:classifiers":[
        {
            "category":"Travel",
            "subcategory":"Hotels & Motels",
            "type":"Entertainment"
        }
    ],
    "sg:phone":"+1 910 864 1006",
    "sg:postcode":"28303",
    "sg:province":"NC",
    "wof:name":"Hampton Inn",
    "wof:placetype":"venue"
},
  "geometry": {"coordinates":[-78.961078,35.07616],"type":"Point"}
}