{
  "type": "Feature",
  "properties": {
    "iso:country":"US",
    "sg:address":"11 Pine St",
    "sg:city":"Knightdale",
    "sg:classifiers":[
        {
            "category":"Building & Trades",
            "subcategory":"Construction",
            "type":"Services"
        }
    ],
    "sg:phone":"+1 919 369 4499",
    "sg:postcode":"27545",
    "sg:province":"NC",
    "sg:tags":[
        "roofing",
        "contractor"
    ],
    "wof:name":"J & E Roofing",
    "wof:placetype":"venue"
},
  "geometry": {"coordinates":[-78.47901899999999,35.792223],"type":"Point"}
}