{
  "type": "Feature",
  "properties": {
    "iso:country":"US",
    "sg:address":"3941 Lake Wilson Rd",
    "sg:city":"Wilson",
    "sg:classifiers":[
        {
            "category":"Freight",
            "type":"Transportation"
        }
    ],
    "sg:phone":"+1 252 399 1337",
    "sg:postcode":"27893",
    "sg:province":"NC",
    "sg:tags":[
        "commercial",
        "storage"
    ],
    "wof:name":"Storage One Inc",
    "wof:placetype":"venue"
},
  "geometry": {"coordinates":[-77.93659700000001,35.775475],"type":"Point"}
}