{
  "type": "Feature",
  "properties": {
    "iso:country":"US",
    "sg:address":"11201 Old Statesville Rd",
    "sg:city":"Huntersville",
    "sg:classifiers":[
        {
            "category":"Education",
            "subcategory":"School",
            "type":"Public Place"
        }
    ],
    "sg:phone":"+1 980 343 3840",
    "sg:postcode":"28078",
    "sg:province":"NC",
    "sg:tags":[
        "high"
    ],
    "sg:website":"http://www.cms.k12.nc.us",
    "wof:name":"North Mecklenburg High School",
    "wof:placetype":"venue"
},
  "geometry": {"coordinates":[-80.83243,35.371678],"type":"Point"}
}