{
  "type": "Feature",
  "properties": {
    "iso:country":"US",
    "sg:address":"330 S Burlington St",
    "sg:city":"Saint Pauls",
    "sg:classifiers":[
        {
            "category":"Restaurant",
            "type":"Food & Drink"
        }
    ],
    "sg:phone":"+1 910 865 4619",
    "sg:postcode":"28384",
    "sg:province":"NC",
    "sg:tags":[
        "f",
        "residential",
        "real estate",
        "operator"
    ],
    "wof:name":"Fergusons Grocery & Lunch",
    "wof:placetype":"venue"
},
  "geometry": {"coordinates":[-78.97028299999999,34.803639],"type":"Point"}
}