{
  "type": "Feature",
  "properties": {
    "addr:full":"2315 N Davidson St Charlotte NC 28205",
    "addr:housenumber":"2315",
    "addr:postcode":"28205",
    "addr:street":"N Davidson St",
    "iso:country":"US",
    "sg:address":"2315 N Davidson St",
    "sg:city":"Charlotte",
    "sg:classifiers":[
        {
            "category":"Professional",
            "subcategory":"Advertising",
            "type":"Services"
        }
    ],
    "sg:phone":"+1 704 377 1288",
    "sg:postcode":"28205",
    "sg:province":"NC",
    "sg:tags":[
        "designer",
        "display",
        "producer"
    ],
    "wof:name":"Creatrix",
    "wof:placetype":"venue"
},
  "geometry": {"coordinates":[-80.813439,35.240984],"type":"Point"}
}