{
  "type": "Feature",
  "properties": {
    "iso:country":"US",
    "sg:address":"1808 Treyburn Ln",
    "sg:city":"High Point",
    "sg:classifiers":[
        {
            "category":"Sports & Exercise",
            "subcategory":"Gym",
            "type":"Entertainment"
        }
    ],
    "sg:phone":"+1 336 889 0401",
    "sg:postcode":"27265",
    "sg:province":"NC",
    "sg:tags":[
        "club",
        "health",
        "studio",
        "gymnasium"
    ],
    "wof:name":"Positive Body Image",
    "wof:placetype":"venue"
},
  "geometry": {"coordinates":[-80.01240900000001,36.031589],"type":"Point"}
}