{
  "type": "Feature",
  "properties": {
    "iso:country":"US",
    "sg:address":"710 Ashe St",
    "sg:city":"Hendersonville",
    "sg:classifiers":[
        {
            "category":"Wholesale",
            "subcategory":"Machinery & Supplies",
            "type":"Manufacturing & Wholesale Goods"
        },
        {
            "category":"Wholesale",
            "subcategory":"Non-durable Goods",
            "type":"Manufacturing & Wholesale Goods"
        }
    ],
    "sg:phone":"+1 828 696 9565",
    "sg:postcode":"28792",
    "sg:province":"NC",
    "sg:tags":[
        "packaging",
        "material"
    ],
    "wof:name":"Anderson Packaging Inc",
    "wof:placetype":"venue"
},
  "geometry": {"coordinates":[-82.456929,35.323455],"type":"Point"}
}