{
  "type": "Feature",
  "properties": {
    "addr:full":"1896 W Mountain St Kernersville NC 27284",
    "addr:housenumber":"1896",
    "addr:postcode":"27284",
    "addr:street":"W Mountain St",
    "iso:country":"US",
    "sg:address":"1896 W Mountain St",
    "sg:city":"Kernersville",
    "sg:classifiers":[
        {
            "category":"Wholesale",
            "subcategory":"Construction Materials",
            "type":"Manufacturing & Wholesale Goods"
        }
    ],
    "sg:phone":"+1 336 996 5322",
    "sg:postcode":"27284",
    "sg:province":"NC",
    "sg:tags":[
        "lumber"
    ],
    "sg:website":"www.south-eastlumber.com",
    "wof:name":"South-East Lumber Co",
    "wof:placetype":"venue"
},
  "geometry": {"coordinates":[-80.11349800000001,36.135514],"type":"Point"}
}