{
  "type": "Feature",
  "properties": {
    "addr:full":"2611 Greengate Dr Greensboro NC 27406",
    "addr:housenumber":"2611",
    "addr:postcode":"27406",
    "addr:street":"Greengate Dr",
    "iso:country":"US",
    "sg:address":"2611 Greengate Dr",
    "sg:city":"Greensboro",
    "sg:classifiers":[
        {
            "category":"Utilities",
            "subcategory":"Natural Gas",
            "type":"Services"
        }
    ],
    "sg:phone":"+1 336 378 1831",
    "sg:postcode":"27406",
    "sg:province":"NC",
    "sg:tags":[
        "company"
    ],
    "sg:website":"www.piedmontng.com",
    "wof:name":"Piedmont Natural Gas Co Inc",
    "wof:placetype":"venue"
},
  "geometry": {"coordinates":[-79.800253,36.02644],"type":"Point"}
}