{
  "type": "Feature",
  "properties": {
    "addr:full":"3313 Dawnshire Ave Charlotte NC 28216",
    "addr:housenumber":"3313",
    "addr:postcode":"28216",
    "addr:street":"Dawnshire Ave",
    "iso:country":"US",
    "sg:address":"3313 Dawnshire Ave",
    "sg:city":"Charlotte",
    "sg:classifiers":[
        {
            "category":"Retail",
            "subcategory":"Repair Shop",
            "type":"Services"
        }
    ],
    "sg:phone":"+1   ",
    "sg:postcode":"28216",
    "sg:province":"NC",
    "wof:name":"B H F Cleaning",
    "wof:placetype":"venue"
},
  "geometry": {"coordinates":[-80.85938299999999,35.280758],"type":"Point"}
}