{
  "type": "Feature",
  "properties": {
    "iso:country":"US",
    "sg:address":"210 N Poindexter St",
    "sg:city":"Elizabeth City",
    "sg:classifiers":[
        {
            "category":"Organizations",
            "subcategory":"Religious Organization",
            "type":"Services"
        }
    ],
    "sg:phone":"+1   ",
    "sg:postcode":"27909",
    "sg:province":"NC",
    "wof:name":"Grace & Truth Community Church",
    "wof:placetype":"venue"
},
  "geometry": {"coordinates":[-76.21923099999999,36.301335],"type":"Point"}
}