{
  "type": "Feature",
  "properties": {
    "iso:country":"US",
    "sg:address":"3702 Brookstone Trl",
    "sg:city":"Indian Trail",
    "sg:classifiers":[
        {
            "category":"Building & Trades",
            "subcategory":"Construction",
            "type":"Services"
        }
    ],
    "sg:phone":"+1 704 882 1179",
    "sg:postcode":"28079",
    "sg:province":"NC",
    "sg:tags":[
        "insulation",
        "heat",
        "contractor"
    ],
    "wof:name":"Carolina Panel Technologies",
    "wof:placetype":"venue"
},
  "geometry": {"coordinates":[-80.63921000000001,35.082696],"type":"Point"}
}