{
  "type": "Feature",
  "properties": {
    "iso:country":"US",
    "sg:address":"7530 Nichols Rd",
    "sg:city":"Raleigh",
    "sg:classifiers":[
        {
            "category":"Building & Trades",
            "subcategory":"Landscaping Services",
            "type":"Services"
        }
    ],
    "sg:phone":"+1 919 855 0404",
    "sg:postcode":"27615",
    "sg:province":"NC",
    "sg:tags":[
        "landscape"
    ],
    "wof:name":"George Of The Jungle",
    "wof:placetype":"venue"
},
  "geometry": {"coordinates":[-78.595986,35.883662],"type":"Point"}
}