{
  "type": "Feature",
  "properties": {
    "addr:full":"304 S Green St Morganton NC 28655",
    "addr:housenumber":"304",
    "addr:postcode":"28655",
    "addr:street":"S Green St",
    "iso:country":"US",
    "sg:address":"304 S Green St",
    "sg:city":"Morganton",
    "sg:classifiers":[
        {
            "category":"Autos & Motor Vehicles",
            "subcategory":"Automobile Sales",
            "type":"Retail Goods"
        }
    ],
    "sg:phone":"+1 828 437 0671",
    "sg:postcode":"28655",
    "sg:province":"NC",
    "sg:tags":[
        "new",
        "car"
    ],
    "wof:name":"Bowers Greene Motor Co Inc",
    "wof:placetype":"venue"
},
  "geometry": {"coordinates":[-81.685097,35.74462],"type":"Point"}
}