{
  "type": "Feature",
  "properties": {
    "addr:full":"3785 Guess Rd Durham NC 27705",
    "addr:housenumber":"3785",
    "addr:postcode":"27705",
    "addr:street":"Guess Rd",
    "iso:country":"US",
    "sg:address":"3785 Guess Rd",
    "sg:city":"Durham",
    "sg:classifiers":[
        {
            "category":"Wholesale",
            "subcategory":"Auto Parts",
            "type":"Manufacturing & Wholesale Goods"
        }
    ],
    "sg:phone":"+1 919 682 6101",
    "sg:postcode":"27705",
    "sg:province":"NC",
    "sg:tags":[
        "supply"
    ],
    "sg:website":"www.napa.com",
    "wof:name":"NAPA Auto Parts",
    "wof:placetype":"venue"
},
  "geometry": {"coordinates":[-78.92936899999999,36.055146],"type":"Point"}
}