{
  "type": "Feature",
  "properties": {
    "addr:full":"5679 Harrisburg Industrial Park Dr Harrisburg NC 28075",
    "addr:housenumber":"5679",
    "addr:postcode":"28075",
    "addr:street":"Harrisburg Industrial Park Dr",
    "iso:country":"US",
    "sg:address":"5679 Harrisburg Industrial Park Dr",
    "sg:city":"Harrisburg",
    "sg:classifiers":[
        {
            "category":"Manufacturing",
            "subcategory":"Metals",
            "type":"Manufacturing & Wholesale Goods"
        }
    ],
    "sg:phone":"+1 704 455 9400",
    "sg:postcode":"28075",
    "sg:province":"NC",
    "sg:tags":[
        "hardware",
        "mfg"
    ],
    "wof:name":"Keyper Systems",
    "wof:placetype":"venue"
},
  "geometry": {"coordinates":[-80.670221,35.313416],"type":"Point"}
}