{
  "type": "Feature",
  "properties": {
    "iso:country":"US",
    "sg:address":"110 N Greene St",
    "sg:city":"Wadesboro",
    "sg:classifiers":[
        {
            "category":"Insurance",
            "subcategory":"Hazard Insurance",
            "type":"Services"
        }
    ],
    "sg:phone":"+1 704 694 3425",
    "sg:postcode":"28170",
    "sg:province":"NC",
    "sg:tags":[
        "bond"
    ],
    "wof:name":"D & D Bail Bonding",
    "wof:placetype":"venue"
},
  "geometry": {"coordinates":[-80.071243,34.979266],"type":"Point"}
}