{
  "type": "Feature",
  "properties": {
    "addr:full":"7824 Mayfaire Crest Ln Raleigh NC 27615",
    "addr:housenumber":"7824",
    "addr:postcode":"27615",
    "addr:street":"Mayfaire Crest Ln",
    "iso:country":"US",
    "sg:address":"7824 Mayfaire Crest Ln",
    "sg:city":"Raleigh",
    "sg:classifiers":[
        {
            "category":"Professional",
            "subcategory":"Computer Services",
            "type":"Services"
        }
    ],
    "sg:phone":"+1   ",
    "sg:postcode":"27615",
    "sg:province":"NC",
    "sg:tags":[
        "programing",
        "custom"
    ],
    "wof:name":"J N JS Computer World Inc",
    "wof:placetype":"venue"
},
  "geometry": {"coordinates":[-78.663489,35.890478],"type":"Point"}
}