{
  "type": "Feature",
  "properties": {
    "addr:full":"4735 State Hwy 107 Glenville NC 28736",
    "addr:housenumber":"4735",
    "addr:postcode":"28736",
    "addr:street":"State Hwy 107",
    "iso:country":"US",
    "sg:address":"4735 State Hwy 107",
    "sg:city":"Glenville",
    "sg:classifiers":[
        {
            "category":"Autos & Motor Vehicles",
            "subcategory":"Boat Sales",
            "type":"Retail Goods"
        }
    ],
    "sg:phone":"+1 828 743 2143",
    "sg:postcode":"28736",
    "sg:province":"NC",
    "sg:tags":[
        "dealer",
        "sales"
    ],
    "sg:website":"www.signalridgemarina.com",
    "wof:name":"Signal Ridge Marina",
    "wof:placetype":"venue"
},
  "geometry": {"coordinates":[-83.125981,35.163584],"type":"Point"}
}