{
  "type": "Feature",
  "properties": {
    "addr:full":"529 S Elm St Greensboro NC 27406",
    "addr:housenumber":"529",
    "addr:postcode":"27406",
    "addr:street":"S Elm St",
    "iso:country":"US",
    "sg:address":"529 S Elm St",
    "sg:city":"Greensboro",
    "sg:classifiers":[
        {
            "category":"Food & Beverages",
            "subcategory":"Groceries & Convenience Stores",
            "type":"Retail Goods"
        }
    ],
    "sg:phone":"+1 336 272 4954",
    "sg:postcode":"27406",
    "sg:province":"NC",
    "sg:tags":[
        "grocer",
        "merchandise"
    ],
    "wof:name":"Coe Grocery & Seed Company",
    "wof:placetype":"venue"
},
  "geometry": {"coordinates":[-79.79068700000001,36.066282],"type":"Point"}
}