{
  "type": "Feature",
  "properties": {
    "addr:full":"113 W 3rd Ave Gastonia NC 28052",
    "addr:housenumber":"113",
    "addr:postcode":"28052",
    "addr:street":"W 3Rd Ave",
    "iso:country":"US",
    "sg:address":"113 W 3rd Ave",
    "sg:city":"Gastonia",
    "sg:classifiers":[
        {
            "category":"Professional",
            "subcategory":"Credit Reporting & Collection",
            "type":"Services"
        }
    ],
    "sg:phone":"+1 704 864 4341",
    "sg:postcode":"28052",
    "sg:province":"NC",
    "sg:tags":[
        "agency"
    ],
    "sg:website":"www.parkdansan.com",
    "wof:name":"Park Dansan",
    "wof:placetype":"venue"
},
  "geometry": {"coordinates":[-81.18360699999999,35.259047],"type":"Point"}
}