{
  "type": "Feature",
  "properties": {
    "iso:country":"US",
    "sg:address":"208 Wall St",
    "sg:city":"Oxford",
    "sg:classifiers":[
        {
            "category":"Education",
            "subcategory":"College",
            "type":"Public Place"
        }
    ],
    "sg:phone":"+1 919 693 7218",
    "sg:postcode":"27565",
    "sg:province":"NC",
    "sg:tags":[
        "academic",
        "school"
    ],
    "wof:name":"Nc State University",
    "wof:placetype":"venue"
},
  "geometry": {"coordinates":[-78.58870400000001,36.309675],"type":"Point"}
}