{
  "type": "Feature",
  "properties": {
    "iso:country":"US",
    "sg:address":"313 N Berkeley Blvd",
    "sg:city":"Goldsboro",
    "sg:classifiers":[
        {
            "category":"Banks & Credit Unions",
            "subcategory":"Bank",
            "type":"Services"
        }
    ],
    "sg:phone":"+1 919 778 3432",
    "sg:postcode":"27534",
    "sg:province":"NC",
    "sg:tags":[
        "loan"
    ],
    "wof:name":"Home Credit Corp",
    "wof:placetype":"venue"
},
  "geometry": {"coordinates":[-77.94586200000001,35.374392],"type":"Point"}
}