{
  "type": "Feature",
  "properties": {
    "addr:full":"613 W Roosevelt Blvd Monroe NC 28110",
    "addr:housenumber":"613",
    "addr:postcode":"28110",
    "addr:street":"W Roosevelt Blvd",
    "iso:country":"US",
    "sg:address":"613 W Roosevelt Blvd",
    "sg:city":"Monroe",
    "sg:classifiers":[
        {
            "category":"Utilities",
            "subcategory":"Cable",
            "type":"Services"
        }
    ],
    "sg:phone":"+1 704 289 6007",
    "sg:postcode":"28110",
    "sg:province":"NC",
    "sg:tags":[
        "television"
    ],
    "wof:name":"Cable Innovations",
    "wof:placetype":"venue"
},
  "geometry": {"coordinates":[-80.534488,34.990803],"type":"Point"}
}