{
  "type": "Feature",
  "properties": {
    "addr:full":"70 Lovers Leap Dr Murphy NC 28906",
    "addr:housenumber":"70",
    "addr:postcode":"28906",
    "addr:street":"Lovers Leap Dr",
    "iso:country":"US",
    "sg:address":"70 Lovers Leap Dr",
    "sg:city":"Murphy",
    "sg:classifiers":[
        {
            "category":"Food & Beverages",
            "subcategory":"Candy",
            "type":"Retail Goods"
        }
    ],
    "sg:phone":"+1 828 835 8821",
    "sg:postcode":"28906",
    "sg:province":"NC",
    "wof:name":"Gum Drop Stop",
    "wof:placetype":"venue"
},
  "geometry": {"coordinates":[-84.04732,35.099307],"type":"Point"}
}