{
  "type": "Feature",
  "properties": {
    "iso:country":"US",
    "sg:address":"1500 Tunnel Rd",
    "sg:city":"Asheville",
    "sg:classifiers":[
        {
            "category":"Restaurant",
            "type":"Food & Drink"
        }
    ],
    "sg:phone":"+1 828 299 8186",
    "sg:postcode":"28805",
    "sg:province":"NC",
    "sg:tags":[
        "eating"
    ],
    "wof:name":"San Miguel International Rest",
    "wof:placetype":"venue"
},
  "geometry": {"coordinates":[-82.461051,35.584759],"type":"Point"}
}