{
  "type": "Feature",
  "properties": {
    "iso:country":"US",
    "sg:address":"429 Grosvenor Dr",
    "sg:city":"Raleigh",
    "sg:classifiers":[
        {
            "category":"Utilities",
            "subcategory":"Telephone",
            "type":"Services"
        }
    ],
    "sg:phone":"+1 919 870 9418",
    "sg:postcode":"27615",
    "sg:province":"NC",
    "sg:tags":[
        "communications"
    ],
    "wof:name":"Ewees Inc",
    "wof:placetype":"venue"
},
  "geometry": {"coordinates":[-78.643602,35.908653],"type":"Point"}
}