{
  "type": "Feature",
  "properties": {
    "addr:full":"105 Hanford Rd Chapel Hill NC 27516",
    "addr:housenumber":"105",
    "addr:postcode":"27516",
    "addr:street":"Hanford Rd",
    "iso:country":"US",
    "sg:address":"105 Hanford Rd",
    "sg:city":"Chapel Hill",
    "sg:classifiers":[
        {
            "category":"Wholesale",
            "subcategory":"Jewelry",
            "type":"Manufacturing & Wholesale Goods"
        }
    ],
    "sg:phone":"+1 919 942 1260",
    "sg:postcode":"27516",
    "sg:province":"NC",
    "sg:tags":[
        "stone"
    ],
    "wof:name":"Krzysztof Grochowski",
    "wof:placetype":"venue"
},
  "geometry": {"coordinates":[-79.086664,35.9291],"type":"Point"}
}