{
  "type": "Feature",
  "properties": {
    "addr:full":"5803 Hunt Club Rd Greensboro NC 27410",
    "addr:housenumber":"5803",
    "addr:postcode":"27410",
    "addr:street":"Hunt Club Rd",
    "iso:country":"US",
    "sg:address":"5803 Hunt Club Rd",
    "sg:city":"Greensboro",
    "sg:classifiers":[
        {
            "category":"Personal",
            "subcategory":"Barber",
            "type":"Services"
        }
    ],
    "sg:phone":"+1 336 292 1188",
    "sg:postcode":"27410",
    "sg:province":"NC",
    "sg:website":"www.greatclips.com",
    "wof:name":"Great Clips",
    "wof:placetype":"venue"
},
  "geometry": {"coordinates":[-79.891575,36.087954],"type":"Point"}
}