{
  "type": "Feature",
  "properties": {
    "addr:full":"315 N Moore St Sanford NC 27330",
    "addr:housenumber":"315",
    "addr:postcode":"27330",
    "addr:street":"N Moore St",
    "iso:country":"US",
    "sg:address":"315 N Moore St",
    "sg:city":"Sanford",
    "sg:classifiers":[
        {
            "category":"Real Estate",
            "subcategory":"Real Estate Agent",
            "type":"Services"
        }
    ],
    "sg:phone":"+1 919 775 5536",
    "sg:postcode":"27330",
    "sg:province":"NC",
    "wof:name":"Amer-Realty",
    "wof:placetype":"venue"
},
  "geometry": {"coordinates":[-79.18013999999999,35.483608],"type":"Point"}
}