{
  "type": "Feature",
  "properties": {
    "addr:full":"1114 W Dalton Rd King NC 27021",
    "addr:housenumber":"1114",
    "addr:postcode":"27021",
    "addr:street":"W Dalton Rd",
    "iso:country":"US",
    "sg:address":"1114 W Dalton Rd",
    "sg:city":"King",
    "sg:classifiers":[
        {
            "category":"Home & Garden",
            "subcategory":"Furniture",
            "type":"Retail Goods"
        }
    ],
    "sg:phone":"+1 336 983 9905",
    "sg:postcode":"27021",
    "sg:province":"NC",
    "sg:tags":[
        "top",
        "counter"
    ],
    "wof:name":"Signature Custom Woodworking",
    "wof:placetype":"venue"
},
  "geometry": {"coordinates":[-80.390263,36.298735],"type":"Point"}
}