{
  "type": "Feature",
  "properties": {
    "iso:country":"US",
    "sg:address":"7920 Neal Rd",
    "sg:city":"Charlotte",
    "sg:classifiers":[
        {
            "category":"Professional",
            "type":"Services"
        }
    ],
    "sg:phone":"+1 980 343 5796",
    "sg:postcode":"28262",
    "sg:province":"NC",
    "sg:tags":[
        "establishment"
    ],
    "wof:name":"Charlotte Mecklenburg Sch",
    "wof:placetype":"venue"
},
  "geometry": {"coordinates":[-80.777011,35.297277],"type":"Point"}
}