{
  "type": "Feature",
  "properties": {
    "addr:full":"1126 Upper Thomas Branch Rd Marshall NC 28753",
    "addr:housenumber":"1126",
    "addr:postcode":"28753",
    "addr:street":"Upper Thomas Branch Rd",
    "iso:country":"US",
    "sg:address":"1126 Upper Thomas Branch Rd",
    "sg:city":"Marshall",
    "sg:classifiers":[
        {
            "category":"Farming",
            "subcategory":"Farm",
            "type":"Manufacturing & Wholesale Goods"
        }
    ],
    "sg:phone":"+1 828 649 2194",
    "sg:postcode":"28753",
    "sg:province":"NC",
    "sg:tags":[
        "primarily",
        "crop",
        "general"
    ],
    "wof:name":"Mulberry Gap Farm LLC",
    "wof:placetype":"venue"
},
  "geometry": {"coordinates":[-82.72906999999999,35.85773],"type":"Point"}
}