{
  "type": "Feature",
  "properties": {
    "iso:country":"US",
    "sg:address":"2819 Iron Gate Ln",
    "sg:city":"Charlotte",
    "sg:classifiers":[
        {
            "category":"Shopping",
            "subcategory":"Catalog Store",
            "type":"Retail Goods"
        }
    ],
    "sg:phone":"+1 704 568 5582",
    "sg:postcode":"28212",
    "sg:province":"NC",
    "sg:tags":[
        "on",
        "internet",
        "design",
        "page",
        "web"
    ],
    "wof:name":"Clydes Sports Cards Inc",
    "wof:placetype":"venue"
},
  "geometry": {"coordinates":[-80.75653200000001,35.198881],"type":"Point"}
}