{
  "type": "Feature",
  "properties": {
    "addr:full":"430 Davis Dr Morrisville NC 27560",
    "addr:housenumber":"430",
    "addr:postcode":"27560",
    "addr:street":"Davis Dr",
    "iso:country":"US",
    "sg:address":"430 Davis Dr",
    "sg:city":"Morrisville",
    "sg:classifiers":[
        {
            "category":"Professional",
            "subcategory":"Lawyer & Legal Services",
            "type":"Services"
        }
    ],
    "sg:phone":"+1 919 472 5300",
    "sg:postcode":"27560",
    "sg:province":"NC",
    "sg:tags":[
        "attorney"
    ],
    "sg:website":"www.boozallen.com",
    "wof:name":"Booz Allen Hamilton",
    "wof:placetype":"venue"
},
  "geometry": {"coordinates":[-78.86276599999999,35.873846],"type":"Point"}
}