{
  "type": "Feature",
  "properties": {
    "iso:country":"US",
    "sg:address":"437 S Moore St",
    "sg:city":"Clayton",
    "sg:classifiers":[
        {
            "category":"Social Services",
            "subcategory":"Child Care",
            "type":"Services"
        }
    ],
    "sg:phone":"+1 919 553 8958",
    "sg:postcode":"27520",
    "sg:province":"NC",
    "wof:name":"Creative Child Development Ctr",
    "wof:placetype":"venue"
},
  "geometry": {"coordinates":[-78.469238,35.656463],"type":"Point"}
}