{
  "type": "Feature",
  "properties": {
    "addr:full":"221 Summit Ave Mount Holly NC 28120",
    "addr:housenumber":"221",
    "addr:postcode":"28120",
    "addr:street":"Summit Ave",
    "iso:country":"US",
    "sg:address":"221 Summit Ave",
    "sg:city":"Mount Holly",
    "sg:classifiers":[
        {
            "category":"Manufacturing",
            "subcategory":"Tools & Machinery",
            "type":"Manufacturing & Wholesale Goods"
        }
    ],
    "sg:phone":"+1 704 827 4503",
    "sg:postcode":"28120",
    "sg:province":"NC",
    "sg:tags":[
        "operator",
        "bridge",
        "crane",
        "overhead",
        "retailer"
    ],
    "wof:name":"Eagle Crane Co",
    "wof:placetype":"venue"
},
  "geometry": {"coordinates":[-81.016209,35.291972],"type":"Point"}
}