{
  "type": "Feature",
  "properties": {
    "iso:country":"US",
    "sg:address":"106 W Clemmonsville Rd",
    "sg:city":"Winston Salem",
    "sg:classifiers":[
        {
            "category":"Professional",
            "type":"Services"
        }
    ],
    "sg:phone":"+1 336 650 0431",
    "sg:postcode":"27127",
    "sg:province":"NC",
    "wof:name":"Randy M McKnight",
    "wof:placetype":"venue"
},
  "geometry": {"coordinates":[-80.24049100000001,36.047657],"type":"Point"}
}