{
  "type": "Feature",
  "properties": {
    "addr:full":"3500 Oleander Dr Wilmington NC 28403",
    "addr:housenumber":"3500",
    "addr:postcode":"28403",
    "addr:street":"Oleander Dr",
    "iso:country":"US",
    "sg:address":"3500 Oleander Dr",
    "sg:city":"Wilmington",
    "sg:classifiers":[
        {
            "category":"Shopping",
            "subcategory":"Clothing, Apparel, & Fashions",
            "type":"Retail Goods"
        }
    ],
    "sg:phone":"+1 910 799 7774",
    "sg:postcode":"28403",
    "sg:province":"NC",
    "sg:website":"www.nyandcompany.com",
    "wof:name":"New York & Co",
    "wof:placetype":"venue"
},
  "geometry": {"coordinates":[-77.904348,34.216027],"type":"Point"}
}