{
  "type": "Feature",
  "properties": {
    "iso:country":"US",
    "sg:address":"110 Depot St",
    "sg:city":"Waynesville",
    "sg:classifiers":[
        {
            "category":"Retail",
            "subcategory":"Repair Shop",
            "type":"Services"
        }
    ],
    "sg:phone":"+1 828 456 9314",
    "sg:postcode":"28786",
    "sg:province":"NC",
    "sg:tags":[
        "cleaners",
        "parts",
        "vacuum"
    ],
    "wof:name":"Jim's Sew & Vac Shop",
    "wof:placetype":"venue"
},
  "geometry": {"coordinates":[-82.988085,35.492699],"type":"Point"}
}