{
  "type": "Feature",
  "properties": {
    "iso:country":"US",
    "sg:address":"204 S Center St",
    "sg:city":"Goldsboro",
    "sg:classifiers":[
        {
            "category":"Manufacturing",
            "subcategory":"Lumber",
            "type":"Manufacturing & Wholesale Goods"
        },
        {
            "category":"Government",
            "subcategory":"Fire Station",
            "type":"Public Place"
        }
    ],
    "sg:phone":"+1 919 580 4262",
    "sg:postcode":"27530",
    "sg:province":"NC",
    "sg:tags":[
        "department"
    ],
    "sg:website":"www.ci.goldsboro.nc.us",
    "wof:name":"Goldsboro Fire Department",
    "wof:placetype":"venue"
},
  "geometry": {"coordinates":[-77.998019,35.380484],"type":"Point"}
}