{
  "type": "Feature",
  "properties": {
    "addr:full":"6608 Silver Fox Rd Charlotte NC 28270",
    "addr:housenumber":"6608",
    "addr:postcode":"28270",
    "addr:street":"Silver Fox Rd",
    "iso:country":"US",
    "sg:address":"6608 Silver Fox Rd",
    "sg:city":"Charlotte",
    "sg:classifiers":[
        {
            "category":"Health Services",
            "subcategory":"Doctor",
            "type":"Services"
        }
    ],
    "sg:phone":"+1   ",
    "sg:postcode":"28270",
    "sg:province":"NC",
    "sg:tags":[
        "medical"
    ],
    "wof:name":"Obgyn Ultrasound",
    "wof:placetype":"venue"
},
  "geometry": {"coordinates":[-80.76281899999999,35.091685],"type":"Point"}
}