{
  "type": "Feature",
  "properties": {
    "iso:country":"US",
    "sg:address":"723 Knightdale Ave",
    "sg:city":"High Point",
    "sg:classifiers":[
        {
            "category":"Building & Trades",
            "subcategory":"Electrical",
            "type":"Services"
        },
        {
            "category":"Building & Trades",
            "subcategory":"Plumbing",
            "type":"Services"
        }
    ],
    "sg:phone":"+1 336 861 5775",
    "sg:postcode":"27263",
    "sg:province":"NC",
    "sg:tags":[
        "electrical",
        "heating",
        "contractor"
    ],
    "wof:name":"Callahan & Callahan Electric",
    "wof:placetype":"venue"
},
  "geometry": {"coordinates":[-79.96977699999999,35.927476],"type":"Point"}
}