{
  "type": "Feature",
  "properties": {
    "addr:full":"120 Club Dr Mooresville NC 28115",
    "addr:housenumber":"120",
    "addr:postcode":"28115",
    "addr:street":"Club Dr",
    "iso:country":"US",
    "sg:address":"120 Club Dr",
    "sg:city":"Mooresville",
    "sg:classifiers":[
        {
            "category":"Professional",
            "subcategory":"Business Services",
            "type":"Services"
        }
    ],
    "sg:phone":"+1   ",
    "sg:postcode":"28115",
    "sg:province":"NC",
    "wof:name":"Paraladies of Lake",
    "wof:placetype":"venue"
},
  "geometry": {"coordinates":[-80.83022,35.572962],"type":"Point"}
}