{
  "type": "Feature",
  "properties": {
    "addr:full":"4100 Carmel Rd Charlotte NC 28226",
    "addr:housenumber":"4100",
    "addr:postcode":"28226",
    "addr:street":"Carmel Rd",
    "iso:country":"US",
    "sg:address":"4100 Carmel Rd",
    "sg:city":"Charlotte",
    "sg:classifiers":[
        {
            "category":"Personal",
            "subcategory":"Beauty Salon",
            "type":"Services"
        }
    ],
    "sg:phone":"+1 704 543 1007",
    "sg:postcode":"28226",
    "sg:province":"NC",
    "sg:tags":[
        "manicuring"
    ],
    "wof:name":"Elegant Nails",
    "wof:placetype":"venue"
},
  "geometry": {"coordinates":[-80.822429,35.11777],"type":"Point"}
}