{
  "type": "Feature",
  "properties": {
    "addr:full":"525 Delburg St Davidson NC 28036",
    "addr:housenumber":"525",
    "addr:postcode":"28036",
    "addr:street":"Delburg St",
    "iso:country":"US",
    "sg:address":"525 Delburg St",
    "sg:city":"Davidson",
    "sg:classifiers":[
        {
            "category":"Autos & Motor Vehicles",
            "subcategory":"Auto Supplies",
            "type":"Retail Goods"
        }
    ],
    "sg:phone":"+1 704 987 0070",
    "sg:postcode":"28036",
    "sg:province":"NC",
    "wof:name":"Tire Doc Inc",
    "wof:placetype":"venue"
},
  "geometry": {"coordinates":[-80.85462200000001,35.505328],"type":"Point"}
}