{
  "type": "Feature",
  "properties": {
    "addr:full":"135 Center St Jacksonville NC 28546",
    "addr:housenumber":"135",
    "addr:postcode":"28546",
    "addr:street":"Center St",
    "iso:country":"US",
    "sg:address":"135 Center St",
    "sg:city":"Jacksonville",
    "sg:classifiers":[
        {
            "category":"Retail",
            "subcategory":"Auto Rental",
            "type":"Services"
        }
    ],
    "sg:phone":"+1 910 455 2718",
    "sg:postcode":"28546",
    "sg:province":"NC",
    "sg:tags":[
        "renting",
        "truck",
        "leasing"
    ],
    "wof:name":"U-Haul Co",
    "wof:placetype":"venue"
},
  "geometry": {"coordinates":[-77.382085,34.747484],"type":"Point"}
}