{
  "type": "Feature",
  "properties": {
    "iso:country":"US",
    "sg:address":"6118 Petra Mill Rd",
    "sg:city":"Granite Falls",
    "sg:classifiers":[
        {
            "category":"Building & Trades",
            "subcategory":"Construction",
            "type":"Services"
        }
    ],
    "sg:phone":"+1 828 396 8052",
    "sg:postcode":"28630",
    "sg:province":"NC",
    "sg:tags":[
        "house"
    ],
    "wof:name":"Carrigan Construction",
    "wof:placetype":"venue"
},
  "geometry": {"coordinates":[-81.35945,35.851994],"type":"Point"}
}