{
  "type": "Feature",
  "properties": {
    "iso:country":"US",
    "sg:address":"14111 Idlewild Rd",
    "sg:city":"Matthews",
    "sg:classifiers":[
        {
            "category":"Building & Trades",
            "subcategory":"Construction",
            "type":"Services"
        }
    ],
    "sg:phone":"+1 704 847 2888",
    "sg:postcode":"28105",
    "sg:province":"NC",
    "sg:tags":[
        "roof",
        "deck"
    ],
    "wof:name":"David Tetrick & Son",
    "wof:placetype":"venue"
},
  "geometry": {"coordinates":[-80.66298,35.13101],"type":"Point"}
}