{
  "type": "Feature",
  "properties": {
    "addr:full":"1604 E Ozark Ave Gastonia NC 28054",
    "addr:housenumber":"1604",
    "addr:postcode":"28054",
    "addr:street":"E Ozark Ave",
    "iso:country":"US",
    "sg:address":"1604 E Ozark Ave",
    "sg:city":"Gastonia",
    "sg:classifiers":[
        {
            "category":"Food & Beverages",
            "subcategory":"Groceries & Convenience Stores",
            "type":"Retail Goods"
        },
        {
            "category":"Shopping",
            "subcategory":"Used Merchandise",
            "type":"Retail Goods"
        }
    ],
    "sg:phone":"+1 704 813 2070",
    "sg:postcode":"28054",
    "sg:province":"NC",
    "sg:tags":[
        "furniture"
    ],
    "wof:name":"Shirley's Furniture Store",
    "wof:placetype":"venue"
},
  "geometry": {"coordinates":[-81.157068,35.275062],"type":"Point"}
}