{
  "type": "Feature",
  "properties": {
    "iso:country":"US",
    "sg:address":"310 Old Fox Trl",
    "sg:city":"Durham",
    "sg:classifiers":[
        {
            "category":"Wholesale",
            "subcategory":"Seafood",
            "type":"Manufacturing & Wholesale Goods"
        }
    ],
    "sg:phone":"+1 919 308 9990",
    "sg:postcode":"27713",
    "sg:province":"NC",
    "sg:tags":[
        "frozen",
        "both",
        "distributes",
        "fresh"
    ],
    "wof:name":"Simply Fresh",
    "wof:placetype":"venue"
},
  "geometry": {"coordinates":[-78.944812,35.922242],"type":"Point"}
}