{
  "type": "Feature",
  "properties": {
    "iso:country":"US",
    "sg:address":"405 Southview Ln",
    "sg:city":"Flat Rock",
    "sg:classifiers":[
        {
            "category":"Banks & Credit Unions",
            "subcategory":"Financial Services",
            "type":"Services"
        }
    ],
    "sg:phone":"+1 828 697 9496",
    "sg:postcode":"28731",
    "sg:province":"NC",
    "sg:tags":[
        "company",
        "holding"
    ],
    "wof:name":"Black Dog Enterprises Inc",
    "wof:placetype":"venue"
},
  "geometry": {"coordinates":[-82.427126,35.252545],"type":"Point"}
}