{
  "type": "Feature",
  "properties": {
    "addr:full":"8 Allwood Ct Greensboro NC 27410",
    "addr:housenumber":"8",
    "addr:postcode":"27410",
    "addr:street":"Allwood Ct",
    "iso:country":"US",
    "sg:address":"8 Allwood Ct",
    "sg:city":"Greensboro",
    "sg:classifiers":[
        {
            "category":"Professional",
            "subcategory":"Computer Services",
            "type":"Services"
        }
    ],
    "sg:phone":"+1   ",
    "sg:postcode":"27410",
    "sg:province":"NC",
    "sg:tags":[
        "programming"
    ],
    "wof:name":"Factory Automators Inc",
    "wof:placetype":"venue"
},
  "geometry": {"coordinates":[-79.861186,36.076767],"type":"Point"}
}