{
  "type": "Feature",
  "properties": {
    "addr:full":"9473 Perry Rd Graham NC 27253",
    "addr:housenumber":"9473",
    "addr:postcode":"27253",
    "addr:street":"Perry Rd",
    "iso:country":"US",
    "sg:address":"9473 Perry Rd",
    "sg:city":"Graham",
    "sg:classifiers":[
        {
            "category":"Retail",
            "subcategory":"Repair Shop",
            "type":"Services"
        }
    ],
    "sg:phone":"+1 336 376 6000",
    "sg:postcode":"27253",
    "sg:province":"NC",
    "sg:tags":[
        "related"
    ],
    "wof:name":"Advanced Metalworks & & Repair",
    "wof:placetype":"venue"
},
  "geometry": {"coordinates":[-79.258066,35.86751],"type":"Point"}
}