{
  "type": "Feature",
  "properties": {
    "iso:country":"US",
    "sg:address":"2182 N Church St",
    "sg:city":"Burlington",
    "sg:classifiers":[
        {
            "category":"Retail",
            "subcategory":"Laundry & Dry Cleaning",
            "type":"Services"
        }
    ],
    "sg:phone":"+1 336 226 9803",
    "sg:postcode":"27217",
    "sg:province":"NC",
    "sg:tags":[
        "drycleaning",
        "plant",
        "agent",
        "garment"
    ],
    "wof:name":"Boston Cleaners & Laundry",
    "wof:placetype":"venue"
},
  "geometry": {"coordinates":[-79.40115299999999,36.094393],"type":"Point"}
}