{
  "type": "Feature",
  "properties": {
    "iso:country":"US",
    "sg:address":"2912 Wake Forest Rd",
    "sg:city":"Raleigh",
    "sg:classifiers":[
        {
            "category":"Banks & Credit Unions",
            "subcategory":"Financial Services",
            "type":"Services"
        }
    ],
    "sg:phone":"+1 919 876 7878",
    "sg:postcode":"27608",
    "sg:province":"NC",
    "sg:tags":[
        "company",
        "holding"
    ],
    "wof:name":"ITB Holdings",
    "wof:placetype":"venue"
},
  "geometry": {"coordinates":[-78.622473,35.822771],"type":"Point"}
}