{
  "type": "Feature",
  "properties": {
    "iso:country":"US",
    "sg:address":"3005 High Point Rd",
    "sg:city":"Greensboro",
    "sg:classifiers":[
        {
            "category":"Travel",
            "subcategory":"Hotels & Motels",
            "type":"Entertainment"
        }
    ],
    "sg:phone":"+1 336 294 4565",
    "sg:postcode":"27407",
    "sg:province":"NC",
    "wof:name":"Park Lane Hotel-Four Seasons",
    "wof:placetype":"venue"
},
  "geometry": {"coordinates":[-79.83524199999999,36.049128],"type":"Point"}
}