{
  "type": "Feature",
  "properties": {
    "addr:full":"5146 Princess St Charlotte NC 28269",
    "addr:housenumber":"5146",
    "addr:postcode":"28269",
    "addr:street":"Princess St",
    "iso:country":"US",
    "sg:address":"5146 Princess St",
    "sg:city":"Charlotte",
    "sg:classifiers":[
        {
            "category":"Professional",
            "type":"Services"
        }
    ],
    "sg:phone":"+1 704 596 2541",
    "sg:postcode":"28269",
    "sg:province":"NC",
    "wof:name":"Eric F Harris",
    "wof:placetype":"venue"
},
  "geometry": {"coordinates":[-80.79986,35.286209],"type":"Point"}
}