{
  "type": "Feature",
  "properties": {
    "iso:country":"US",
    "sg:address":"429 Clarice Ave",
    "sg:city":"Charlotte",
    "sg:classifiers":[
        {
            "category":"Shopping",
            "type":"Retail Goods"
        }
    ],
    "sg:phone":"+1 704 376 6066",
    "sg:postcode":"28204",
    "sg:province":"NC",
    "sg:tags":[
        "equipment",
        "telephone",
        "supply"
    ],
    "wof:name":"Strategic Integrated Systems",
    "wof:placetype":"venue"
},
  "geometry": {"coordinates":[-80.81615499999999,35.212216],"type":"Point"}
}