{
  "type": "Feature",
  "properties": {
    "iso:country":"US",
    "sg:address":"46136 Berry Hill Dr",
    "sg:city":"Norwood",
    "sg:classifiers":[
        {
            "category":"Recreation",
            "subcategory":"Marina",
            "type":"Entertainment"
        }
    ],
    "sg:phone":"+1 704 474 0121",
    "sg:postcode":"28128",
    "sg:province":"NC",
    "wof:name":"J & J Marine Repair",
    "wof:placetype":"venue"
},
  "geometry": {"coordinates":[-80.107724,35.242389],"type":"Point"}
}