{
  "type": "Feature",
  "properties": {
    "iso:country":"US",
    "sg:address":"1202 S Evans St",
    "sg:city":"Greenville",
    "sg:classifiers":[
        {
            "category":"Shopping",
            "type":"Retail Goods"
        }
    ],
    "sg:phone":"+1 252 754 2502",
    "sg:postcode":"27834",
    "sg:province":"NC",
    "sg:tags":[
        "cosmetic",
        "perfume"
    ],
    "wof:name":"Herbal & Beauty Consultants",
    "wof:placetype":"venue"
},
  "geometry": {"coordinates":[-77.375001,35.60379],"type":"Point"}
}