{
  "type": "Feature",
  "properties": {
    "iso:country":"US",
    "sg:address":"236 W Montgomery St",
    "sg:city":"Henderson",
    "sg:classifiers":[
        {
            "category":"Shopping",
            "subcategory":"Used Merchandise",
            "type":"Retail Goods"
        }
    ],
    "sg:phone":"+1 252 492 6861",
    "sg:postcode":"27536",
    "sg:province":"NC",
    "sg:tags":[
        "shop",
        "thrift"
    ],
    "wof:name":"True Thrift Shop",
    "wof:placetype":"venue"
},
  "geometry": {"coordinates":[-78.40406299999999,36.328646],"type":"Point"}
}