{
  "type": "Feature",
  "properties": {
    "iso:country":"US",
    "sg:address":"4125 Johnson St",
    "sg:city":"High Point",
    "sg:classifiers":[
        {
            "category":"Organizations",
            "subcategory":"Religious Organization",
            "type":"Services"
        }
    ],
    "sg:phone":"+1 336 841 4480",
    "sg:postcode":"27265",
    "sg:province":"NC",
    "sg:tags":[
        "church"
    ],
    "sg:website":"www.cbchurch.org",
    "wof:name":"Community Bible Church",
    "wof:placetype":"venue"
},
  "geometry": {"coordinates":[-80.019183,36.032396],"type":"Point"}
}