{
  "type": "Feature",
  "properties": {
    "addr:full":"991 S McPherson Church Rd Fayetteville NC 28303",
    "addr:housenumber":"991",
    "addr:postcode":"28303",
    "addr:street":"S Mcpherson Church Rd",
    "iso:country":"US",
    "sg:address":"991 S McPherson Church Rd",
    "sg:city":"Fayetteville",
    "sg:classifiers":[
        {
            "category":"Banks & Credit Unions",
            "subcategory":"Bank",
            "type":"Services"
        }
    ],
    "sg:phone":"+1 910 860 5160",
    "sg:postcode":"28303",
    "sg:province":"NC",
    "sg:tags":[
        "state",
        "commercial"
    ],
    "wof:name":"Rbc Centura",
    "wof:placetype":"venue"
},
  "geometry": {"coordinates":[-78.937062,35.048032],"type":"Point"}
}