{
  "type": "Feature",
  "properties": {
    "iso:country":"US",
    "sg:address":"804 Fowler Rd",
    "sg:city":"Mount Airy",
    "sg:classifiers":[
        {
            "category":"Recreation",
            "type":"Entertainment"
        }
    ],
    "sg:phone":"+1   ",
    "sg:postcode":"27030",
    "sg:province":"NC",
    "wof:name":"Starlite Skate Center",
    "wof:placetype":"venue"
},
  "geometry": {"coordinates":[-80.62615599999999,36.514763],"type":"Point"}
}