{
  "type": "Feature",
  "properties": {
    "addr:full":"104 Heatherly Creek Dr Pilot Mountain NC 27041",
    "addr:housenumber":"104",
    "addr:postcode":"27041",
    "addr:street":"Heatherly Creek Dr",
    "iso:country":"US",
    "sg:address":"104 Heatherly Creek Dr",
    "sg:city":"Pilot Mountain",
    "sg:classifiers":[
        {
            "category":"Shopping",
            "subcategory":"Florist",
            "type":"Retail Goods"
        }
    ],
    "sg:phone":"+1 336 368 9795",
    "sg:postcode":"27041",
    "sg:province":"NC",
    "wof:name":"Pilot Mountain Flower Shop",
    "wof:placetype":"venue"
},
  "geometry": {"coordinates":[-80.479141,36.378072],"type":"Point"}
}