{
  "type": "Feature",
  "properties": {
    "addr:full":"102 Hidden Spring Cary NC 27513",
    "addr:housenumber":"102",
    "addr:postcode":"27513",
    "addr:street":"Hidden Spring",
    "iso:country":"US",
    "sg:address":"102 Hidden Spring",
    "sg:city":"Cary",
    "sg:classifiers":[
        {
            "category":"Building & Trades",
            "subcategory":"Construction",
            "type":"Services"
        }
    ],
    "sg:phone":"+1 919 360 1555",
    "sg:postcode":"27513",
    "sg:province":"NC",
    "sg:tags":[
        "house"
    ],
    "wof:name":"Richland Builders",
    "wof:placetype":"venue"
},
  "geometry": {"coordinates":[-78.783627,35.810738],"type":"Point"}
}