{
  "type": "Feature",
  "properties": {
    "addr:full":"550 Fleming St Hendersonville NC 28739",
    "addr:housenumber":"550",
    "addr:postcode":"28739",
    "addr:street":"Fleming St",
    "iso:country":"US",
    "sg:address":"550 Fleming St",
    "sg:city":"Hendersonville",
    "sg:classifiers":[
        {
            "category":"Personal",
            "subcategory":"Beauty Salon",
            "type":"Services"
        }
    ],
    "sg:phone":"+1   ",
    "sg:postcode":"28739",
    "sg:province":"NC",
    "sg:tags":[
        "shop"
    ],
    "wof:name":"Hair Kutters",
    "wof:placetype":"venue"
},
  "geometry": {"coordinates":[-82.466369,35.317694],"type":"Point"}
}