{
  "type": "Feature",
  "properties": {
    "iso:country":"US",
    "sg:address":"1003 N Berkeley Blvd",
    "sg:city":"Goldsboro",
    "sg:classifiers":[
        {
            "category":"Shopping",
            "subcategory":"Clothing, Apparel, & Fashions",
            "type":"Retail Goods"
        }
    ],
    "sg:phone":"+1 919 778 9373",
    "sg:postcode":"27534",
    "sg:province":"NC",
    "sg:tags":[
        "alteration"
    ],
    "wof:name":"Sonny's Alteration",
    "wof:placetype":"venue"
},
  "geometry": {"coordinates":[-77.936662,35.378337],"type":"Point"}
}