{
  "type": "Feature",
  "properties": {
    "addr:full":"692 Odom Rd Clinton NC 28328",
    "addr:housenumber":"692",
    "addr:postcode":"28328",
    "addr:street":"Odom Rd",
    "iso:country":"US",
    "sg:address":"692 Odom Rd",
    "sg:city":"Clinton",
    "sg:classifiers":[
        {
            "category":"Organizations",
            "subcategory":"Religious Organization",
            "type":"Services"
        }
    ],
    "sg:phone":"+1   ",
    "sg:postcode":"28328",
    "sg:province":"NC",
    "wof:name":"Mt Moriah Methodist Church",
    "wof:placetype":"venue"
},
  "geometry": {"coordinates":[-78.42039800000001,35.111057],"type":"Point"}
}