{
  "type": "Feature",
  "properties": {
    "addr:full":"10123 Whitethorn Dr Charlotte NC 28277",
    "addr:postcode":"10123;28277",
    "addr:street":"Whitethorn Dr",
    "iso:country":"US",
    "sg:address":"10123 Whitethorn Dr",
    "sg:city":"Charlotte",
    "sg:classifiers":[
        {
            "category":"Shopping",
            "type":"Retail Goods"
        }
    ],
    "sg:phone":"+1 704 847 0408",
    "sg:postcode":"28277",
    "sg:province":"NC",
    "sg:tags":[
        "merchandise"
    ],
    "wof:name":"Vh2",
    "wof:placetype":"venue"
},
  "geometry": {"coordinates":[-80.78696600000001,35.077457],"type":"Point"}
}