{
  "type": "Feature",
  "properties": {
    "iso:country":"US",
    "sg:address":"195 Starpoint Plz",
    "sg:city":"Fayetteville",
    "sg:classifiers":[
        {
            "category":"Restaurant",
            "type":"Food & Drink"
        }
    ],
    "sg:menulink":"http://www.allmenus.com/nc/seventy-first/231755-obees-soup-salad-subs/menu/",
    "sg:phone":"+1 910 864 3949",
    "sg:postcode":"28303",
    "sg:province":"NC",
    "sg:tags":[
        "wrap",
        "soup",
        "american",
        "sandwich",
        "salad"
    ],
    "wof:name":"Obee's Soup-Salad-Subs",
    "wof:placetype":"venue"
},
  "geometry": {"coordinates":[-79.009827,35.087441],"type":"Point"}
}