{
  "type": "Feature",
  "properties": {
    "iso:country":"US",
    "sg:address":"1 Crestview Ct",
    "sg:city":"Arden",
    "sg:classifiers":[
        {
            "category":"Organizations",
            "subcategory":"Community Association",
            "type":"Services"
        }
    ],
    "sg:phone":"+1   ",
    "sg:postcode":"28704",
    "sg:province":"NC",
    "wof:name":"International Assoc of LI",
    "wof:placetype":"venue"
},
  "geometry": {"coordinates":[-82.49791399999999,35.475367],"type":"Point"}
}