{
  "type": "Feature",
  "properties": {
    "iso:country":"US",
    "sg:address":"1302 Norwood St SW",
    "sg:city":"Lenoir",
    "sg:classifiers":[
        {
            "category":"Social Services",
            "subcategory":"Child Care",
            "type":"Services"
        }
    ],
    "sg:phone":"+1 828 758 2482",
    "sg:postcode":"28645",
    "sg:province":"NC",
    "wof:name":"Caldwell Academy Child Care",
    "wof:placetype":"venue"
},
  "geometry": {"coordinates":[-81.525432,35.891284],"type":"Point"}
}