{
  "type": "Feature",
  "properties": {
    "addr:full":"4001 New Bern Ave Raleigh NC 27610",
    "addr:housenumber":"4001",
    "addr:postcode":"27610",
    "addr:street":"New Bern Ave",
    "iso:country":"US",
    "sg:address":"4001 New Bern Ave",
    "sg:city":"Raleigh",
    "sg:classifiers":[
        {
            "category":"Retail",
            "subcategory":"Auto Repair",
            "type":"Services"
        }
    ],
    "sg:phone":"+1 919 212 8115",
    "sg:postcode":"27610",
    "sg:province":"NC",
    "sg:tags":[
        "glass",
        "replacement"
    ],
    "wof:name":"Harmon Autoglass",
    "wof:placetype":"venue"
},
  "geometry": {"coordinates":[-78.56670699999999,35.798762],"type":"Point"}
}