{
  "type": "Feature",
  "properties": {
    "iso:country":"US",
    "sg:address":"58 Chestnut Dr SW",
    "sg:city":"Concord",
    "sg:classifiers":[
        {
            "category":"Organizations",
            "subcategory":"Religious Organization",
            "type":"Services"
        }
    ],
    "sg:phone":"+1 704 782 7620",
    "sg:postcode":"28025",
    "sg:province":"NC",
    "sg:tags":[
        "church"
    ],
    "wof:name":"Grace Lutheran Church",
    "wof:placetype":"venue"
},
  "geometry": {"coordinates":[-80.57661299999999,35.404679],"type":"Point"}
}