{
  "type": "Feature",
  "properties": {
    "iso:country":"US",
    "sg:address":"912 Ernest Williams Rd",
    "sg:city":"Roseboro",
    "sg:classifiers":[
        {
            "category":"Farming",
            "subcategory":"Farm",
            "type":"Manufacturing & Wholesale Goods"
        }
    ],
    "sg:phone":"+1 910 564 4228",
    "sg:postcode":"28382",
    "sg:province":"NC",
    "wof:name":"Matthews Turkey Farms",
    "wof:placetype":"venue"
},
  "geometry": {"coordinates":[-78.55870299999999,35.067583],"type":"Point"}
}