{
  "type": "Feature",
  "properties": {
    "iso:country":"US",
    "sg:address":"1402 US Hwy 74 Bus",
    "sg:city":"Forest City",
    "sg:classifiers":[
        {
            "category":"Home & Garden",
            "subcategory":"Building Materials",
            "type":"Retail Goods"
        }
    ],
    "sg:phone":"+1 828 245 8614",
    "sg:postcode":"28043",
    "sg:province":"NC",
    "sg:tags":[
        "center"
    ],
    "wof:name":"Lowes",
    "wof:placetype":"venue"
},
  "geometry": {"coordinates":[-81.900854,35.35198],"type":"Point"}
}