{
  "type": "Feature",
  "properties": {
    "addr:full":"220 Forrest Dr Madison NC 27025",
    "addr:housenumber":"220",
    "addr:postcode":"27025",
    "addr:street":"Forrest Dr",
    "iso:country":"US",
    "sg:address":"220 Forrest Dr",
    "sg:city":"Madison",
    "sg:classifiers":[
        {
            "category":"Farming",
            "subcategory":"Farm",
            "type":"Manufacturing & Wholesale Goods"
        }
    ],
    "sg:phone":"+1 336 427 5342",
    "sg:postcode":"27025",
    "sg:province":"NC",
    "wof:name":"Neal Williams Farms",
    "wof:placetype":"venue"
},
  "geometry": {"coordinates":[-79.975016,36.345174],"type":"Point"}
}