{
  "type": "Feature",
  "properties": {
    "iso:country":"US",
    "sg:address":"113 Lorraine Rd",
    "sg:city":"Clinton",
    "sg:classifiers":[
        {
            "category":"Organizations",
            "subcategory":"Religious Organization",
            "type":"Services"
        }
    ],
    "sg:phone":"+1 910 592 7023",
    "sg:postcode":"28328",
    "sg:province":"NC",
    "sg:tags":[
        "church"
    ],
    "wof:name":"United Pentecostal Church",
    "wof:placetype":"venue"
},
  "geometry": {"coordinates":[-78.32131099999999,35.045624],"type":"Point"}
}