{
  "type": "Feature",
  "properties": {
    "addr:full":"130 E Fisher Ave Greensboro NC 27401",
    "addr:housenumber":"130",
    "addr:postcode":"27401",
    "addr:street":"E Fisher Ave",
    "iso:country":"US",
    "sg:address":"130 E Fisher Ave",
    "sg:city":"Greensboro",
    "sg:classifiers":[
        {
            "category":"Banks & Credit Unions",
            "subcategory":"Investment Brokerage",
            "type":"Services"
        }
    ],
    "sg:phone":"+1 336 272 2552",
    "sg:postcode":"27401",
    "sg:province":"NC",
    "sg:tags":[
        "advisory",
        "financial"
    ],
    "wof:name":"Wealth Advisory Partners",
    "wof:placetype":"venue"
},
  "geometry": {"coordinates":[-79.78745499999999,36.079217],"type":"Point"}
}