{
  "type": "Feature",
  "properties": {
    "addr:full":"3069 Cumberland Rd Fayetteville NC 28306",
    "addr:housenumber":"3069",
    "addr:postcode":"28306",
    "addr:street":"Cumberland Rd",
    "iso:country":"US",
    "sg:address":"3069 Cumberland Rd",
    "sg:city":"Fayetteville",
    "sg:classifiers":[
        {
            "category":"Retail",
            "subcategory":"Animal Services",
            "type":"Services"
        }
    ],
    "sg:phone":"+1 910 425 3558",
    "sg:postcode":"28306",
    "sg:province":"NC",
    "wof:name":"Luv My K9s",
    "wof:placetype":"venue"
},
  "geometry": {"coordinates":[-78.920514,35.017754],"type":"Point"}
}