{
  "type": "Feature",
  "properties": {
    "addr:full":"300 Sir Walter Raleigh St Manteo NC 27954",
    "addr:housenumber":"300",
    "addr:postcode":"27954",
    "addr:street":"Sir Walter Raleigh St",
    "iso:country":"US",
    "sg:address":"300 Sir Walter Raleigh St",
    "sg:city":"Manteo",
    "sg:classifiers":[
        {
            "category":"Professional",
            "subcategory":"Lawyer & Legal Services",
            "type":"Services"
        }
    ],
    "sg:phone":"+1 252 473 2191",
    "sg:postcode":"27954",
    "sg:province":"NC",
    "sg:tags":[
        "attorney"
    ],
    "wof:name":"Mc Cown & Mc Cown Pa",
    "wof:placetype":"venue"
},
  "geometry": {"coordinates":[-75.673199,35.907484],"type":"Point"}
}