{
  "type": "Feature",
  "properties": {
    "addr:full":"9476 Peacock Rd Chadbourn NC 28431",
    "addr:housenumber":"9476",
    "addr:postcode":"28431",
    "addr:street":"Peacock Rd",
    "iso:country":"US",
    "sg:address":"9476 Peacock Rd",
    "sg:city":"Chadbourn",
    "sg:classifiers":[
        {
            "category":"Freight",
            "type":"Transportation"
        }
    ],
    "sg:phone":"+1 910 654 5114",
    "sg:postcode":"28431",
    "sg:province":"NC",
    "sg:tags":[
        "operator",
        "local",
        "trucking"
    ],
    "wof:name":"R&P Trucking Inc",
    "wof:placetype":"venue"
},
  "geometry": {"coordinates":[-78.79956199999999,34.319628],"type":"Point"}
}