{
  "type": "Feature",
  "properties": {
    "iso:country":"US",
    "sg:address":"106 Westminster Ct",
    "sg:city":"Mebane",
    "sg:classifiers":[
        {
            "category":"Real Estate",
            "subcategory":"Real Estate Agent",
            "type":"Services"
        }
    ],
    "sg:phone":"+1 919 536 4200",
    "sg:postcode":"27302",
    "sg:province":"NC",
    "wof:name":"Fiar Oaks Subdivision",
    "wof:placetype":"venue"
},
  "geometry": {"coordinates":[-79.27746,36.082157],"type":"Point"}
}