{
  "type": "Feature",
  "properties": {
    "addr:full":"8359 Chapel Hill Rd Cary NC 27513",
    "addr:housenumber":"8359",
    "addr:postcode":"27513",
    "addr:street":"Chapel Hill Rd",
    "iso:country":"US",
    "sg:address":"8359 Chapel Hill Rd",
    "sg:city":"Cary",
    "sg:classifiers":[
        {
            "category":"Building & Trades",
            "subcategory":"Construction",
            "type":"Services"
        }
    ],
    "sg:phone":"+1 919 667 9500",
    "sg:postcode":"27513",
    "sg:province":"NC",
    "sg:tags":[
        "fire",
        "restoration",
        "damage"
    ],
    "wof:name":"Disaster One",
    "wof:placetype":"venue"
},
  "geometry": {"coordinates":[-78.778294,35.791334],"type":"Point"}
}