{
  "type": "Feature",
  "properties": {
    "iso:country":"US",
    "sg:address":"8 Pine Ridge Trl",
    "sg:city":"Arden",
    "sg:classifiers":[
        {
            "category":"Food & Beverages",
            "subcategory":"Specialty",
            "type":"Retail Goods"
        }
    ],
    "sg:phone":"+1 828 650 0324",
    "sg:postcode":"28704",
    "sg:province":"NC",
    "wof:name":"Jump Start Your Health Inc",
    "wof:placetype":"venue"
},
  "geometry": {"coordinates":[-82.57423,35.455313],"type":"Point"}
}