{
  "type": "Feature",
  "properties": {
    "addr:full":"6230 Beatties Ford Rd Charlotte NC 28216",
    "addr:postcode":"6230;28216",
    "addr:street":"Beatties Ford Rd",
    "iso:country":"US",
    "sg:address":"6230 Beatties Ford Rd",
    "sg:city":"Charlotte",
    "sg:classifiers":[
        {
            "category":"Organizations",
            "subcategory":"Religious Organization",
            "type":"Services"
        }
    ],
    "sg:phone":"+1 704 399 1684",
    "sg:postcode":"28216",
    "sg:province":"NC",
    "sg:tags":[
        "church"
    ],
    "wof:name":"Trinity United Methodist Chr",
    "wof:placetype":"venue"
},
  "geometry": {"coordinates":[-80.864943,35.319857],"type":"Point"}
}