{
  "type": "Feature",
  "properties": {
    "addr:full":"722 Cascade Ave Eden NC 27288",
    "addr:housenumber":"722",
    "addr:postcode":"27288",
    "addr:street":"Cascade Ave",
    "iso:country":"US",
    "sg:address":"722 Cascade Ave",
    "sg:city":"Eden",
    "sg:classifiers":[
        {
            "category":"Autos & Motor Vehicles",
            "subcategory":"Automobile Sales",
            "type":"Retail Goods"
        }
    ],
    "sg:phone":"+1 336 623 8601",
    "sg:postcode":"27288",
    "sg:province":"NC",
    "sg:tags":[
        "used"
    ],
    "wof:name":"Lkh Auto Sales LLC",
    "wof:placetype":"venue"
},
  "geometry": {"coordinates":[-79.691957,36.531188],"type":"Point"}
}