{
  "type": "Feature",
  "properties": {
    "addr:full":"1326 W Craighead Rd Charlotte NC 28206",
    "addr:housenumber":"1326",
    "addr:postcode":"28206",
    "addr:street":"W Craighead Rd",
    "iso:country":"US",
    "sg:address":"1326 W Craighead Rd",
    "sg:city":"Charlotte",
    "sg:classifiers":[
        {
            "category":"Retail",
            "subcategory":"Auto Rental",
            "type":"Services"
        }
    ],
    "sg:phone":"+1 704 598 7977",
    "sg:postcode":"28206",
    "sg:province":"NC",
    "sg:tags":[
        "truck"
    ],
    "wof:name":"Penske",
    "wof:placetype":"venue"
},
  "geometry": {"coordinates":[-80.81229399999999,35.269291],"type":"Point"}
}