{
  "type": "Feature",
  "properties": {
    "iso:country":"US",
    "sg:address":"29 Providence Rd",
    "sg:city":"Asheville",
    "sg:classifiers":[
        {
            "category":"Wholesale",
            "subcategory":"Durable Goods & Equipment",
            "type":"Manufacturing & Wholesale Goods"
        }
    ],
    "sg:phone":"+1 828 254 2901",
    "sg:postcode":"28806",
    "sg:province":"NC",
    "sg:tags":[
        "novelty"
    ],
    "wof:name":"Novelty Clock Co",
    "wof:placetype":"venue"
},
  "geometry": {"coordinates":[-82.605901,35.586842],"type":"Point"}
}