{
  "type": "Feature",
  "properties": {
    "iso:country":"US",
    "sg:address":"1327 N Brightleaf Blvd",
    "sg:city":"Smithfield",
    "sg:classifiers":[
        {
            "category":"Professional",
            "type":"Services"
        }
    ],
    "sg:phone":"+1 919 938 0634",
    "sg:postcode":"27577",
    "sg:province":"NC",
    "sg:tags":[
        "establishment"
    ],
    "wof:name":"Tasc",
    "wof:placetype":"venue"
},
  "geometry": {"coordinates":[-78.304867,35.522254],"type":"Point"}
}