{
  "type": "Feature",
  "properties": {
    "iso:country":"US",
    "sg:address":"718 Montana Dr",
    "sg:city":"Charlotte",
    "sg:classifiers":[
        {
            "category":"Building & Trades",
            "subcategory":"Electrical",
            "type":"Services"
        }
    ],
    "sg:phone":"+1 704 394 1023",
    "sg:postcode":"28216",
    "sg:province":"NC",
    "sg:tags":[
        "electric",
        "contractor"
    ],
    "wof:name":"R L Powers Electrical Contr",
    "wof:placetype":"venue"
},
  "geometry": {"coordinates":[-80.87319100000001,35.266365],"type":"Point"}
}