{
  "type": "Feature",
  "properties": {
    "addr:full":"133 Creek Rd Manteo NC 27909",
    "addr:housenumber":"133",
    "addr:postcode":"27909",
    "addr:street":"Creek Rd",
    "iso:country":"US",
    "sg:address":"133 Creek Rd",
    "sg:city":"Manteo",
    "sg:classifiers":[
        {
            "category":"Organizations",
            "subcategory":"Religious Organization",
            "type":"Services"
        }
    ],
    "sg:phone":"+1 252 473 1248",
    "sg:postcode":"27909",
    "sg:province":"NC",
    "sg:tags":[
        "church"
    ],
    "wof:name":"Haven Creek Baptist Church",
    "wof:placetype":"venue"
},
  "geometry": {"coordinates":[-76.250826,36.310398],"type":"Point"}
}