{
  "type": "Feature",
  "properties": {
    "addr:full":"14001 S Lakes Dr Charlotte NC 28273",
    "addr:housenumber":"14001",
    "addr:postcode":"28273",
    "addr:street":"S Lakes Dr",
    "iso:country":"US",
    "sg:address":"14001 S Lakes Dr",
    "sg:city":"Charlotte",
    "sg:classifiers":[
        {
            "category":"Wholesale",
            "subcategory":"Machinery & Supplies",
            "type":"Manufacturing & Wholesale Goods"
        }
    ],
    "sg:phone":"+1 704 583 0905",
    "sg:postcode":"28273",
    "sg:province":"NC",
    "sg:tags":[
        "equipment",
        "hydraulic"
    ],
    "wof:name":"Rexroth Hydraulics",
    "wof:placetype":"venue"
},
  "geometry": {"coordinates":[-80.957987,35.103453],"type":"Point"}
}