{
  "type": "Feature",
  "properties": {
    "iso:country":"US",
    "sg:address":"6701 Old Lexington Rd",
    "sg:city":"Winston Salem",
    "sg:classifiers":[
        {
            "category":"Freight",
            "type":"Transportation"
        }
    ],
    "sg:phone":"+1 336 882 9422",
    "sg:postcode":"27107",
    "sg:province":"NC",
    "sg:tags":[
        "operator",
        "local",
        "trucking"
    ],
    "wof:name":"Thomasville Trucking Inc",
    "wof:placetype":"venue"
},
  "geometry": {"coordinates":[-80.210612,36.014372],"type":"Point"}
}