{
  "type": "Feature",
  "properties": {
    "iso:country":"US",
    "sg:address":"336 Taylor Rd",
    "sg:city":"Chocowinity",
    "sg:classifiers":[
        {
            "category":"Building & Trades",
            "subcategory":"Electrical",
            "type":"Services"
        }
    ],
    "sg:phone":"+1 252 975 2221",
    "sg:postcode":"27817",
    "sg:province":"NC",
    "sg:tags":[
        "electric",
        "contractor"
    ],
    "wof:name":"C S Mayo Electrical Svc",
    "wof:placetype":"venue"
},
  "geometry": {"coordinates":[-77.12637599999999,35.506111],"type":"Point"}
}