{
  "type": "Feature",
  "properties": {
    "addr:full":"2433 Lewisville Clemmons Rd Clemmons NC 27012",
    "addr:housenumber":"2433",
    "addr:postcode":"27012",
    "addr:street":"Lewisville Clemmons Rd",
    "iso:country":"US",
    "sg:address":"2433 Lewisville Clemmons Rd",
    "sg:city":"Clemmons",
    "sg:classifiers":[
        {
            "category":"Restaurant",
            "type":"Food & Drink"
        }
    ],
    "sg:phone":"+1 336 766 0205",
    "sg:postcode":"27012",
    "sg:province":"NC",
    "sg:website":"www.burgerking.com",
    "wof:name":"Burger King",
    "wof:placetype":"venue"
},
  "geometry": {"coordinates":[-80.38336200000001,36.032337],"type":"Point"}
}