{
  "type": "Feature",
  "properties": {
    "iso:country":"US",
    "sg:address":"4910 Departure Dr",
    "sg:city":"Raleigh",
    "sg:classifiers":[
        {
            "category":"Professional",
            "subcategory":"Computer Services",
            "type":"Services"
        }
    ],
    "sg:phone":"+1 919 790 9800",
    "sg:postcode":"27616",
    "sg:province":"NC",
    "sg:tags":[
        "graphics"
    ],
    "sg:website":"www.impdesigns.com",
    "wof:name":"Impresive Designs",
    "wof:placetype":"venue"
},
  "geometry": {"coordinates":[-78.595547,35.85582],"type":"Point"}
}