{
  "type": "Feature",
  "properties": {
    "iso:country":"US",
    "sg:address":"155 Windsor Cir",
    "sg:city":"Chapel Hill",
    "sg:classifiers":[
        {
            "category":"Personal",
            "type":"Services"
        }
    ],
    "sg:phone":"+1 919 929 6683",
    "sg:postcode":"27516",
    "sg:province":"NC",
    "sg:tags":[
        "mover"
    ],
    "sg:website":"www.chapelhillmoving.com",
    "wof:name":"Chapel Hill Moving Co",
    "wof:placetype":"venue"
},
  "geometry": {"coordinates":[-79.06258800000001,35.944608],"type":"Point"}
}