{
  "type": "Feature",
  "properties": {
    "addr:full":"1639 Barnardsville Hwy Barnardsville NC 28709",
    "addr:housenumber":"1639",
    "addr:postcode":"28709",
    "addr:street":"Barnardsville Hwy",
    "iso:country":"US",
    "sg:address":"1639 Barnardsville Hwy",
    "sg:city":"Barnardsville",
    "sg:classifiers":[
        {
            "category":"Organizations",
            "subcategory":"Religious Organization",
            "type":"Services"
        }
    ],
    "sg:phone":"+1 828 626 2610",
    "sg:postcode":"28709",
    "sg:province":"NC",
    "sg:tags":[
        "church"
    ],
    "wof:name":"Barnardsville Baptist Church",
    "wof:placetype":"venue"
},
  "geometry": {"coordinates":[-82.456802,35.777712],"type":"Point"}
}