{
  "type": "Feature",
  "properties": {
    "iso:country":"US",
    "sg:address":"889 Juanita Hills St",
    "sg:city":"High Point",
    "sg:classifiers":[
        {
            "category":"Utilities",
            "subcategory":"Telephone",
            "type":"Services"
        }
    ],
    "sg:phone":"+1 336 987 0230",
    "sg:postcode":"27262",
    "sg:province":"NC",
    "sg:tags":[
        "telecommunication"
    ],
    "sg:website":"www.philyawsvc.com",
    "wof:name":"Philyaw Communications",
    "wof:placetype":"venue"
},
  "geometry": {"coordinates":[-80.042517,35.932123],"type":"Point"}
}