{
  "type": "Feature",
  "properties": {
    "iso:country":"US",
    "sg:address":"380 Stoney Knob Ln",
    "sg:city":"Salisbury",
    "sg:classifiers":[
        {
            "category":"Building & Trades",
            "subcategory":"Construction",
            "type":"Services"
        }
    ],
    "sg:phone":"+1 704 633 0167",
    "sg:postcode":"28147",
    "sg:province":"NC",
    "sg:tags":[
        "hanging",
        "contractor"
    ],
    "wof:name":"Michael W Webb",
    "wof:placetype":"venue"
},
  "geometry": {"coordinates":[-80.592555,35.714112],"type":"Point"}
}