{
  "type": "Feature",
  "properties": {
    "addr:full":"7250 Senepole Rd Randleman NC 27317",
    "addr:housenumber":"7250",
    "addr:postcode":"27317",
    "addr:street":"Senepole Rd",
    "iso:country":"US",
    "sg:address":"7250 Senepole Rd",
    "sg:city":"Randleman",
    "sg:classifiers":[
        {
            "category":"Building & Trades",
            "subcategory":"Construction",
            "type":"Services"
        }
    ],
    "sg:phone":"+1 336 676 0660",
    "sg:postcode":"27317",
    "sg:province":"NC",
    "sg:tags":[
        "concrete",
        "contractor"
    ],
    "wof:name":"CTI of Pied",
    "wof:placetype":"venue"
},
  "geometry": {"coordinates":[-79.838976,35.911228],"type":"Point"}
}