{
  "type": "Feature",
  "properties": {
    "addr:full":"9037 Walker Mill Rd Randleman NC 27317",
    "addr:housenumber":"9037",
    "addr:postcode":"27317",
    "addr:street":"Walker Mill Rd",
    "iso:country":"US",
    "sg:address":"9037 Walker Mill Rd",
    "sg:city":"Randleman",
    "sg:classifiers":[
        {
            "category":"Manufacturing",
            "subcategory":"Signs",
            "type":"Manufacturing & Wholesale Goods"
        }
    ],
    "sg:phone":"+1 336 674 0346",
    "sg:postcode":"27317",
    "sg:province":"NC",
    "wof:name":"Mike's Metal Letters",
    "wof:placetype":"venue"
},
  "geometry": {"coordinates":[-79.840099,35.894552],"type":"Point"}
}