{
  "type": "Feature",
  "properties": {
    "iso:country":"US",
    "sg:address":"3818 Azalea Ln",
    "sg:city":"Trinity",
    "sg:classifiers":[
        {
            "category":"Retail",
            "subcategory":"Laundry & Dry Cleaning",
            "type":"Services"
        }
    ],
    "sg:phone":"+1   ",
    "sg:postcode":"27370",
    "sg:province":"NC",
    "wof:name":"Quality Carpet Cleaning",
    "wof:placetype":"venue"
},
  "geometry": {"coordinates":[-80.026448,35.8575],"type":"Point"}
}