{
  "type": "Feature",
  "properties": {
    "addr:full":"1314 Ashleybrook Ln Winston Salem NC 27103",
    "addr:housenumber":"1314",
    "addr:postcode":"27103",
    "addr:street":"Ashleybrook Ln",
    "iso:country":"US",
    "sg:address":"1314 Ashleybrook Ln",
    "sg:city":"Winston Salem",
    "sg:classifiers":[
        {
            "category":"Building & Trades",
            "subcategory":"Construction",
            "type":"Services"
        }
    ],
    "sg:phone":"+1 336 774 3952",
    "sg:postcode":"27103",
    "sg:province":"NC",
    "sg:tags":[
        "general",
        "contractor"
    ],
    "wof:name":"Mitch Lowrey Construction Inc",
    "wof:placetype":"venue"
},
  "geometry": {"coordinates":[-80.312116,36.074303],"type":"Point"}
}