{
  "type": "Feature",
  "properties": {
    "addr:full":"15470 US Hwy 17 Hampstead NC 28443",
    "addr:housenumber":"15470",
    "addr:postcode":"28443",
    "addr:street":"Us Hwy 17",
    "iso:country":"US",
    "sg:address":"15470 US Hwy 17",
    "sg:city":"Hampstead",
    "sg:classifiers":[
        {
            "category":"Real Estate",
            "subcategory":"Real Estate Agent",
            "type":"Services"
        }
    ],
    "sg:phone":"+1 910 270 9495",
    "sg:postcode":"28443",
    "sg:province":"NC",
    "wof:name":"Laney Real Estate",
    "wof:placetype":"venue"
},
  "geometry": {"coordinates":[-77.701809,34.375523],"type":"Point"}
}