{
  "type": "Feature",
  "properties": {
    "iso:country":"US",
    "sg:address":"3434 Richlands Hwy",
    "sg:city":"Jacksonville",
    "sg:classifiers":[
        {
            "category":"Museum",
            "type":"Entertainment"
        }
    ],
    "sg:phone":"+1   ",
    "sg:postcode":"28540",
    "sg:province":"NC",
    "sg:tags":[
        "gallery"
    ],
    "wof:name":"Dorretta Art Studio & Gallery",
    "wof:placetype":"venue"
},
  "geometry": {"coordinates":[-77.481645,34.758002],"type":"Point"}
}