{
  "type": "Feature",
  "properties": {
    "iso:country":"US",
    "sg:address":"453 Polkville Rd",
    "sg:city":"Shelby",
    "sg:classifiers":[
        {
            "category":"Professional",
            "subcategory":"Management & Consulting",
            "type":"Services"
        }
    ],
    "sg:phone":"+1 704 471 1070",
    "sg:postcode":"28150",
    "sg:province":"NC",
    "sg:tags":[
        "logistics"
    ],
    "wof:name":"Propak Logistics",
    "wof:placetype":"venue"
},
  "geometry": {"coordinates":[-81.572624,35.304828],"type":"Point"}
}