{
  "type": "Feature",
  "properties": {
    "addr:full":"1672 S Main St Laurinburg NC 28352",
    "addr:housenumber":"1672",
    "addr:postcode":"28352",
    "addr:street":"S Main St",
    "iso:country":"US",
    "sg:address":"1672 S Main St",
    "sg:city":"Laurinburg",
    "sg:classifiers":[
        {
            "category":"Building & Trades",
            "subcategory":"Equipment Rental",
            "type":"Services"
        }
    ],
    "sg:phone":"+1   ",
    "sg:postcode":"28352",
    "sg:province":"NC",
    "wof:name":"Rent-A-Center",
    "wof:placetype":"venue"
},
  "geometry": {"coordinates":[-79.47793799999999,34.753598],"type":"Point"}
}