{
  "type": "Feature",
  "properties": {
    "addr:full":"200 Commerce St Washington NC 27858",
    "addr:housenumber":"200",
    "addr:postcode":"27858",
    "addr:street":"Commerce St",
    "iso:country":"US",
    "sg:address":"200 Commerce St",
    "sg:city":"Washington",
    "sg:classifiers":[
        {
            "category":"Professional",
            "subcategory":"Management & Consulting",
            "type":"Services"
        }
    ],
    "sg:phone":"+1 252 940 1680",
    "sg:postcode":"27858",
    "sg:province":"NC",
    "sg:tags":[
        "consultant",
        "business"
    ],
    "wof:name":"Snowden Associates",
    "wof:placetype":"venue"
},
  "geometry": {"coordinates":[-77.373282,35.587626],"type":"Point"}
}