{
  "type": "Feature",
  "properties": {
    "iso:country":"US",
    "sg:address":"719 N Howe St",
    "sg:city":"Southport",
    "sg:classifiers":[
        {
            "category":"Health Services",
            "subcategory":"Doctor",
            "type":"Services"
        }
    ],
    "sg:phone":"+1   ",
    "sg:postcode":"28461",
    "sg:province":"NC",
    "sg:tags":[
        "medical"
    ],
    "wof:name":"Cole T Boyce MD",
    "wof:placetype":"venue"
},
  "geometry": {"coordinates":[-78.021593,33.926384],"type":"Point"}
}