{
  "type": "Feature",
  "properties": {
    "addr:full":"19809 Coachmans Trce Cornelius NC 28031",
    "addr:postcode":"19809;28031",
    "addr:street":"Coachmans Trce",
    "iso:country":"US",
    "sg:address":"19809 Coachmans Trce",
    "sg:city":"Cornelius",
    "sg:classifiers":[
        {
            "category":"Personal",
            "type":"Services"
        }
    ],
    "sg:phone":"+1 704 400 7900",
    "sg:postcode":"28031",
    "sg:province":"NC",
    "sg:tags":[
        "party",
        "planning",
        "event"
    ],
    "wof:name":"Beary Fun Parties",
    "wof:placetype":"venue"
},
  "geometry": {"coordinates":[-80.86836599999999,35.471151],"type":"Point"}
}