{
  "type": "Feature",
  "properties": {
    "iso:country":"US",
    "sg:address":"2207 W Marlboro Rd",
    "sg:city":"Farmville",
    "sg:classifiers":[
        {
            "category":"Retail",
            "subcategory":"Auto Repair",
            "type":"Services"
        }
    ],
    "sg:phone":"+1 252 753 3900",
    "sg:postcode":"27828",
    "sg:province":"NC",
    "sg:tags":[
        "repairing",
        "automobile"
    ],
    "wof:name":"Road Runner Auto Svc",
    "wof:placetype":"venue"
},
  "geometry": {"coordinates":[-77.615421,35.590132],"type":"Point"}
}