{
  "type": "Feature",
  "properties": {
    "addr:full":"102 Ann St Fayetteville NC 28301",
    "addr:housenumber":"102",
    "addr:postcode":"28301",
    "addr:street":"Ann St",
    "iso:country":"US",
    "sg:address":"102 Ann St",
    "sg:city":"Fayetteville",
    "sg:classifiers":[
        {
            "category":"Organizations",
            "subcategory":"Religious Organization",
            "type":"Services"
        }
    ],
    "sg:phone":"+1 910 483 0121",
    "sg:postcode":"28301",
    "sg:province":"NC",
    "sg:tags":[
        "church"
    ],
    "sg:website":"www.firstprez.com",
    "wof:name":"First Presbyterian Church",
    "wof:placetype":"venue"
},
  "geometry": {"coordinates":[-78.875399,35.055003],"type":"Point"}
}