{
  "type": "Feature",
  "properties": {
    "addr:full":"4040 Doris Dr Hudson NC 28638",
    "addr:housenumber":"4040",
    "addr:postcode":"28638",
    "addr:street":"Doris Dr",
    "iso:country":"US",
    "sg:address":"4040 Doris Dr",
    "sg:city":"Hudson",
    "sg:classifiers":[
        {
            "category":"Building & Trades",
            "subcategory":"Construction",
            "type":"Services"
        }
    ],
    "sg:phone":"+1 828 313 3139",
    "sg:postcode":"28638",
    "sg:province":"NC",
    "sg:tags":[
        "pressure",
        "washing",
        "driveway",
        "exterior"
    ],
    "wof:name":"J & J Pressure Washing Service",
    "wof:placetype":"venue"
},
  "geometry": {"coordinates":[-81.49855599999999,35.831014],"type":"Point"}
}