{
  "type": "Feature",
  "properties": {
    "addr:full":"116 E High Ave High Point NC 27260",
    "addr:housenumber":"116",
    "addr:postcode":"27260",
    "addr:street":"E High Ave",
    "iso:country":"US",
    "sg:address":"116 E High Ave",
    "sg:city":"High Point",
    "sg:classifiers":[
        {
            "category":"Banks & Credit Unions",
            "subcategory":"Investment Brokerage",
            "type":"Services"
        }
    ],
    "sg:phone":"+1 336 841 5822",
    "sg:postcode":"27260",
    "sg:province":"NC",
    "sg:tags":[
        "security"
    ],
    "wof:name":"Edward Jones 16592",
    "wof:placetype":"venue"
},
  "geometry": {"coordinates":[-80.004786,35.957668],"type":"Point"}
}