{
  "type": "Feature",
  "properties": {
    "iso:country":"US",
    "sg:address":"4961 Rushing Rd",
    "sg:city":"Stanfield",
    "sg:classifiers":[
        {
            "category":"Shopping",
            "subcategory":"Musical Instruments",
            "type":"Retail Goods"
        }
    ],
    "sg:phone":"+1 704 888 9961",
    "sg:postcode":"28163",
    "sg:province":"NC",
    "wof:name":"Ron's Pickin' Parlor",
    "wof:placetype":"venue"
},
  "geometry": {"coordinates":[-80.421914,35.195105],"type":"Point"}
}