{
  "type": "Feature",
  "properties": {
    "addr:full":"3721 Mebane Rogers Rd Mebane NC 27302",
    "addr:postcode":"3721;27302",
    "addr:street":"Rogers Rd",
    "iso:country":"US",
    "sg:address":"3721 Mebane Rogers Rd",
    "sg:city":"Mebane",
    "sg:classifiers":[
        {
            "category":"Organizations",
            "subcategory":"Religious Organization",
            "type":"Services"
        }
    ],
    "sg:phone":"+1 919 563 0824",
    "sg:postcode":"27302",
    "sg:province":"NC",
    "sg:tags":[
        "church"
    ],
    "sg:website":"www.watchtower.org",
    "wof:name":"Jehovah's Witnesses",
    "wof:placetype":"venue"
},
  "geometry": {"coordinates":[-79.311522,36.121074],"type":"Point"}
}