{
  "type": "Feature",
  "properties": {
    "iso:country":"US",
    "sg:address":"154 Oak Forest Dr",
    "sg:city":"Kernersville",
    "sg:classifiers":[
        {
            "category":"Professional",
            "subcategory":"Art Services",
            "type":"Services"
        }
    ],
    "sg:phone":"+1   ",
    "sg:postcode":"27284",
    "sg:province":"NC",
    "sg:tags":[
        "photography",
        "printing",
        "retail"
    ],
    "wof:name":"Qwik-Pics & Printing",
    "wof:placetype":"venue"
},
  "geometry": {"coordinates":[-80.091426,36.130175],"type":"Point"}
}