{
  "type": "Feature",
  "properties": {
    "addr:full":"3014 Croasdaile Dr Durham NC 27705",
    "addr:housenumber":"3014",
    "addr:postcode":"27705",
    "addr:street":"Croasdaile Dr",
    "iso:country":"US",
    "sg:address":"3014 Croasdaile Dr",
    "sg:city":"Durham",
    "sg:classifiers":[
        {
            "category":"Manufacturing",
            "subcategory":"Tools & Machinery",
            "type":"Manufacturing & Wholesale Goods"
        }
    ],
    "sg:phone":"+1 919 384 9393",
    "sg:postcode":"27705",
    "sg:province":"NC",
    "sg:tags":[
        "equipment",
        "medical",
        "mfg",
        "instrument"
    ],
    "wof:name":"Tbs",
    "wof:placetype":"venue"
},
  "geometry": {"coordinates":[-78.94263100000001,36.026517],"type":"Point"}
}