{
  "type": "Feature",
  "properties": {
    "iso:country":"US",
    "sg:address":"101 Andrea Dr",
    "sg:city":"Jamestown",
    "sg:classifiers":[
        {
            "category":"Professional",
            "type":"Services"
        }
    ],
    "sg:phone":"+1 336 854 0308",
    "sg:postcode":"27282",
    "sg:province":"NC",
    "wof:name":"ARC of High Point",
    "wof:placetype":"venue"
},
  "geometry": {"coordinates":[-79.90978699999999,36.040538],"type":"Point"}
}