{
  "type": "Feature",
  "properties": {
    "iso:country":"US",
    "sg:address":"114 E Railroad St",
    "sg:city":"La Grange",
    "sg:classifiers":[
        {
            "category":"Health Services",
            "subcategory":"Doctor",
            "type":"Services"
        }
    ],
    "sg:phone":"+1 252 566 5999",
    "sg:postcode":"28551",
    "sg:province":"NC",
    "sg:tags":[
        "physician",
        "surgeon"
    ],
    "wof:name":"LA Grange Pediatrics",
    "wof:placetype":"venue"
},
  "geometry": {"coordinates":[-77.78795100000001,35.306571],"type":"Point"}
}