{
  "type": "Feature",
  "properties": {
    "iso:country":"US",
    "sg:address":"312 S 3rd St",
    "sg:city":"Wilmington",
    "sg:classifiers":[
        {
            "category":"Travel",
            "subcategory":"Hotels & Motels",
            "type":"Entertainment"
        }
    ],
    "sg:phone":"+1 910 342 0849",
    "sg:postcode":"28401",
    "sg:province":"NC",
    "sg:tags":[
        "inn",
        "operation"
    ],
    "wof:name":"4 Porchs Bed and Breakfast",
    "wof:placetype":"venue"
},
  "geometry": {"coordinates":[-77.94560199999999,34.230672],"type":"Point"}
}