{
  "type": "Feature",
  "properties": {
    "iso:country":"US",
    "sg:address":"120 Willow Bend Ct",
    "sg:city":"King",
    "sg:classifiers":[
        {
            "category":"Professional",
            "subcategory":"Business Services",
            "type":"Services"
        }
    ],
    "sg:phone":"+1   ",
    "sg:postcode":"27021",
    "sg:province":"NC",
    "wof:name":"Peak Enterprises Group Inc",
    "wof:placetype":"venue"
},
  "geometry": {"coordinates":[-80.341841,36.292692],"type":"Point"}
}