{
  "type": "Feature",
  "properties": {
    "addr:full":"177 Stillwell Dr Thomasville NC 27360",
    "addr:housenumber":"177",
    "addr:postcode":"27360",
    "addr:street":"Stillwell Dr",
    "iso:country":"US",
    "sg:address":"177 Stillwell Dr",
    "sg:city":"Thomasville",
    "sg:classifiers":[
        {
            "category":"Building & Trades",
            "subcategory":"Construction",
            "type":"Services"
        }
    ],
    "sg:phone":"+1 336 475 7933",
    "sg:postcode":"27360",
    "sg:province":"NC",
    "sg:tags":[
        "grading",
        "contractor"
    ],
    "wof:name":"Hulin Grading",
    "wof:placetype":"venue"
},
  "geometry": {"coordinates":[-80.09462499999999,35.793054],"type":"Point"}
}