{
  "type": "Feature",
  "properties": {
    "addr:full":"1461 Asheville Hwy Brevard SC 28712",
    "addr:housenumber":"1461",
    "addr:postcode":"28712",
    "addr:street":"Asheville Hwy",
    "iso:country":"US",
    "sg:address":"1461 Asheville Hwy",
    "sg:city":"Brevard",
    "sg:classifiers":[
        {
            "category":"Retail",
            "subcategory":"Veterinary Services",
            "type":"Services"
        }
    ],
    "sg:phone":"+1 828 884 4775",
    "sg:postcode":"28712",
    "sg:province":"SC",
    "sg:tags":[
        "hospital",
        "animal"
    ],
    "wof:name":"Mountain View Veterinary Hosp",
    "wof:placetype":"venue"
},
  "geometry": {"coordinates":[-82.709289,35.269522],"type":"Point"}
}