{
  "type": "Feature",
  "properties": {
    "addr:full":"1935 Jake Alexander Blvd N Salisbury NC 28147",
    "addr:housenumber":"1935",
    "addr:postcode":"28147",
    "addr:street":"Jake Alexander Blvd N",
    "iso:country":"US",
    "sg:address":"1935 Jake Alexander Blvd N",
    "sg:city":"Salisbury",
    "sg:classifiers":[
        {
            "category":"Personal",
            "subcategory":"Beauty Salon",
            "type":"Services"
        }
    ],
    "sg:phone":"+1   ",
    "sg:postcode":"28147",
    "sg:province":"NC",
    "sg:tags":[
        "shop"
    ],
    "wof:name":"Super Nails",
    "wof:placetype":"venue"
},
  "geometry": {"coordinates":[-80.511145,35.68991],"type":"Point"}
}