{
  "type": "Feature",
  "properties": {
    "addr:full":"1234 N Wesleyan Blvd Rocky Mount NC 27804",
    "addr:housenumber":"1234",
    "addr:postcode":"27804",
    "addr:street":"N Wesleyan Blvd",
    "iso:country":"US",
    "sg:address":"1234 N Wesleyan Blvd",
    "sg:city":"Rocky Mount",
    "sg:classifiers":[
        {
            "category":"Professional",
            "subcategory":"Computer Services",
            "type":"Services"
        }
    ],
    "sg:phone":"+1 252 212 0090",
    "sg:postcode":"27804",
    "sg:province":"NC",
    "sg:tags":[
        "internet"
    ],
    "wof:name":"Clearview Of Nc",
    "wof:placetype":"venue"
},
  "geometry": {"coordinates":[-77.798908,35.975224],"type":"Point"}
}