{
  "type": "Feature",
  "properties": {
    "addr:full":"3733 Ogburn Ave Winston Salem NC 27105",
    "addr:housenumber":"3733",
    "addr:postcode":"27105",
    "addr:street":"Ogburn Ave",
    "iso:country":"US",
    "sg:address":"3733 Ogburn Ave",
    "sg:city":"Winston Salem",
    "sg:classifiers":[
        {
            "category":"Organizations",
            "subcategory":"Religious Organization",
            "type":"Services"
        }
    ],
    "sg:phone":"+1 336 767 3716",
    "sg:postcode":"27105",
    "sg:province":"NC",
    "sg:tags":[
        "church"
    ],
    "sg:website":"www.mineralspringsbaptistchurch.org",
    "wof:name":"Mineral Springs Baptist Church",
    "wof:placetype":"venue"
},
  "geometry": {"coordinates":[-80.236183,36.139056],"type":"Point"}
}