{
  "type": "Feature",
  "properties": {
    "iso:country":"US",
    "sg:address":"1900 Waughtown St",
    "sg:city":"Winston Salem",
    "sg:classifiers":[
        {
            "category":"Shopping",
            "subcategory":"Used Merchandise",
            "type":"Retail Goods"
        }
    ],
    "sg:phone":"+1 336 771 9058",
    "sg:postcode":"27107",
    "sg:province":"NC",
    "wof:name":"Yard Sale Consignments",
    "wof:placetype":"venue"
},
  "geometry": {"coordinates":[-80.19821399999999,36.071138],"type":"Point"}
}