{
  "type": "Feature",
  "properties": {
    "addr:full":"675 US Hwy 117 N Burgaw NC 28425",
    "addr:housenumber":"675",
    "addr:postcode":"28425",
    "addr:street":"Us Hwy 117 N",
    "iso:country":"US",
    "sg:address":"675 US Hwy 117 N",
    "sg:city":"Burgaw",
    "sg:classifiers":[
        {
            "category":"Building & Trades",
            "subcategory":"Construction",
            "type":"Services"
        }
    ],
    "sg:phone":"+1 910 259 8787",
    "sg:postcode":"28425",
    "sg:province":"NC",
    "sg:tags":[
        "general",
        "contractor"
    ],
    "wof:name":"Good Faith Building Supply",
    "wof:placetype":"venue"
},
  "geometry": {"coordinates":[-77.92201799999999,34.563356],"type":"Point"}
}