{
  "type": "Feature",
  "properties": {
    "addr:full":"1175 Kinglet Dr Morganton NC 28655",
    "addr:housenumber":"1175",
    "addr:postcode":"28655",
    "addr:street":"Kinglet Dr",
    "iso:country":"US",
    "sg:address":"1175 Kinglet Dr",
    "sg:city":"Morganton",
    "sg:classifiers":[
        {
            "category":"Restaurant",
            "type":"Food & Drink"
        }
    ],
    "sg:phone":"+1 828 438 9905",
    "sg:postcode":"28655",
    "sg:province":"NC",
    "sg:tags":[
        "eating"
    ],
    "wof:name":"Leviathan Corp",
    "wof:placetype":"venue"
},
  "geometry": {"coordinates":[-81.77355900000001,35.787028],"type":"Point"}
}