{
  "type": "Feature",
  "properties": {
    "addr:full":"802 N Old Stage Rd Saint Pauls NC 28384",
    "addr:housenumber":"802",
    "addr:postcode":"28384",
    "addr:street":"N Old Stage Rd",
    "iso:country":"US",
    "sg:address":"802 N Old Stage Rd",
    "sg:city":"Saint Pauls",
    "sg:classifiers":[
        {
            "category":"Manufacturing",
            "subcategory":"Motor Vehicles & Parts",
            "type":"Manufacturing & Wholesale Goods"
        }
    ],
    "sg:phone":"+1 910 865 4641",
    "sg:postcode":"28384",
    "sg:province":"NC",
    "sg:tags":[
        "horse",
        "transport"
    ],
    "wof:name":"G & H Horse Transport LLC",
    "wof:placetype":"venue"
},
  "geometry": {"coordinates":[-78.977615,34.818222],"type":"Point"}
}