{
  "type": "Feature",
  "properties": {
    "addr:full":"10600 Leslie Dr Raleigh NC 27615",
    "addr:housenumber":"10600",
    "addr:postcode":"27615",
    "addr:street":"Leslie Dr",
    "iso:country":"US",
    "sg:address":"10600 Leslie Dr",
    "sg:city":"Raleigh",
    "sg:classifiers":[
        {
            "category":"Building & Trades",
            "subcategory":"Construction",
            "type":"Services"
        }
    ],
    "sg:phone":"+1 919 844 3193",
    "sg:postcode":"27615",
    "sg:province":"NC",
    "sg:tags":[
        "designer",
        "dealer",
        "pool",
        "swimming"
    ],
    "wof:name":"Stonecreek Pool",
    "wof:placetype":"venue"
},
  "geometry": {"coordinates":[-78.65979900000001,35.921082],"type":"Point"}
}