{
  "type": "Feature",
  "properties": {
    "iso:country":"US",
    "sg:address":"160 Camelot Dr",
    "sg:city":"Salisbury",
    "sg:classifiers":[
        {
            "category":"Building & Trades",
            "subcategory":"Construction",
            "type":"Services"
        }
    ],
    "sg:phone":"+1 704 642 0867",
    "sg:postcode":"28144",
    "sg:province":"NC",
    "sg:tags":[
        "home",
        "builder"
    ],
    "wof:name":"Rowan Homes Inc",
    "wof:placetype":"venue"
},
  "geometry": {"coordinates":[-80.476675,35.702181],"type":"Point"}
}