{
  "type": "Feature",
  "properties": {
    "iso:country":"US",
    "sg:address":"92 Summit Hill Dr",
    "sg:city":"Franklin",
    "sg:classifiers":[
        {
            "category":"Retail",
            "subcategory":"Animal Services",
            "type":"Services"
        }
    ],
    "sg:phone":"+1 828 524 0700",
    "sg:postcode":"28734",
    "sg:province":"NC",
    "wof:name":"River Ridge Bed & Biscuit",
    "wof:placetype":"venue"
},
  "geometry": {"coordinates":[-83.375681,35.181544],"type":"Point"}
}