{
  "type": "Feature",
  "properties": {
    "iso:country":"US",
    "sg:address":"5315 S College Rd",
    "sg:city":"Wilmington",
    "sg:classifiers":[
        {
            "category":"Banks & Credit Unions",
            "subcategory":"Bank",
            "type":"Services"
        }
    ],
    "sg:phone":"+1 910 791 1717",
    "sg:postcode":"28412",
    "sg:province":"NC",
    "sg:tags":[
        "loan",
        "real estate"
    ],
    "wof:name":"Prestige",
    "wof:placetype":"venue"
},
  "geometry": {"coordinates":[-77.89290699999999,34.142303],"type":"Point"}
}