{
  "type": "Feature",
  "properties": {
    "addr:full":"1426 W Grantham St Goldsboro NC 27530",
    "addr:housenumber":"1426",
    "addr:postcode":"27530",
    "addr:street":"W Grantham St",
    "iso:country":"US",
    "sg:address":"1426 W Grantham St",
    "sg:city":"Goldsboro",
    "sg:classifiers":[
        {
            "category":"Autos & Motor Vehicles",
            "subcategory":"Auto Supplies",
            "type":"Retail Goods"
        }
    ],
    "sg:phone":"+1 919 734 7047",
    "sg:postcode":"27530",
    "sg:province":"NC",
    "wof:name":"Florida Tire Service Inc",
    "wof:placetype":"venue"
},
  "geometry": {"coordinates":[-78.01913399999999,35.402303],"type":"Point"}
}