{
  "type": "Feature",
  "properties": {
    "iso:country":"US",
    "sg:address":"765 Crest Rd",
    "sg:city":"Flat Rock",
    "sg:classifiers":[
        {
            "category":"Autos & Motor Vehicles",
            "subcategory":"Boat Sales",
            "type":"Retail Goods"
        }
    ],
    "sg:phone":"+1 828 698 5778",
    "sg:postcode":"28731",
    "sg:province":"NC",
    "sg:tags":[
        "canoe"
    ],
    "sg:website":"www.liquidlogickayaks.com",
    "wof:name":"Liquid Logic",
    "wof:placetype":"venue"
},
  "geometry": {"coordinates":[-82.39040799999999,35.296026],"type":"Point"}
}