{
  "type": "Feature",
  "properties": {
    "addr:full":"1210 N Centennial St High Point NC 27262",
    "addr:housenumber":"1210",
    "addr:postcode":"27262",
    "addr:street":"N Centennial St",
    "iso:country":"US",
    "sg:address":"1210 N Centennial St",
    "sg:city":"High Point",
    "sg:classifiers":[
        {
            "category":"Professional",
            "subcategory":"Accounting & Tax Preparation",
            "type":"Services"
        }
    ],
    "sg:phone":"+1 336 841 7391",
    "sg:postcode":"27262",
    "sg:province":"NC",
    "sg:tags":[
        "accountant"
    ],
    "wof:name":"C & B Taxes",
    "wof:placetype":"venue"
},
  "geometry": {"coordinates":[-80.00153299999999,35.976117],"type":"Point"}
}