{
  "type": "Feature",
  "properties": {
    "addr:full":"3225 Jay Lynn Dr Greensboro NC 27406",
    "addr:housenumber":"3225",
    "addr:postcode":"27406",
    "addr:street":"Jay Lynn Dr",
    "iso:country":"US",
    "sg:address":"3225 Jay Lynn Dr",
    "sg:city":"Greensboro",
    "sg:classifiers":[
        {
            "category":"Building & Trades",
            "subcategory":"Construction",
            "type":"Services"
        }
    ],
    "sg:phone":"+1 336 274 7580",
    "sg:postcode":"27406",
    "sg:province":"NC",
    "sg:tags":[
        "house",
        "manage"
    ],
    "wof:name":"Johns General Improvements",
    "wof:placetype":"venue"
},
  "geometry": {"coordinates":[-79.721749,36.021335],"type":"Point"}
}