{
  "type": "Feature",
  "properties": {
    "iso:country":"US",
    "sg:address":"734 Tyvola Rd",
    "sg:city":"Charlotte",
    "sg:classifiers":[
        {
            "category":"Wholesale",
            "subcategory":"Non-durable Goods",
            "type":"Manufacturing & Wholesale Goods"
        },
        {
            "category":"Personal",
            "subcategory":"Beauty Salon",
            "type":"Services"
        },
        {
            "category":"Personal",
            "subcategory":"Barber",
            "type":"Services"
        }
    ],
    "sg:phone":"+1 704 523 5766",
    "sg:postcode":"28217",
    "sg:province":"NC",
    "sg:tags":[
        "equipment",
        "manufacturer",
        "supplies-wholesale",
        "salons-equipment",
        "supply"
    ],
    "wof:name":"Davidson Beauty Systems",
    "wof:placetype":"venue"
},
  "geometry": {"coordinates":[-80.88379500000001,35.16446],"type":"Point"}
}