{
  "type": "Feature",
  "properties": {
    "iso:country":"US",
    "sg:address":"181 S Church St",
    "sg:city":"Forest City",
    "sg:classifiers":[
        {
            "category":"Organizations",
            "subcategory":"Religious Organization",
            "type":"Services"
        }
    ],
    "sg:phone":"+1 828 245 1931",
    "sg:postcode":"28043",
    "sg:province":"NC",
    "sg:tags":[
        "church"
    ],
    "wof:name":"Holly Springs Baptist Church",
    "wof:placetype":"venue"
},
  "geometry": {"coordinates":[-81.868905,35.332719],"type":"Point"}
}