{
  "type": "Feature",
  "properties": {
    "addr:full":"5921 Robinhood Rd Pfafftown NC 27040",
    "addr:housenumber":"5921",
    "addr:postcode":"27040",
    "addr:street":"Robinhood Rd",
    "iso:country":"US",
    "sg:address":"5921 Robinhood Rd",
    "sg:city":"Pfafftown",
    "sg:classifiers":[
        {
            "category":"Professional",
            "type":"Services"
        }
    ],
    "sg:phone":"+1   ",
    "sg:postcode":"27040",
    "sg:province":"NC",
    "wof:name":"Basiks Inc",
    "wof:placetype":"venue"
},
  "geometry": {"coordinates":[-80.39167500000001,36.120927],"type":"Point"}
}