{
  "type": "Feature",
  "properties": {
    "iso:country":"US",
    "sg:address":"3483 S Evans St",
    "sg:city":"Greenville",
    "sg:classifiers":[
        {
            "category":"Restaurant",
            "type":"Food & Drink"
        }
    ],
    "sg:phone":"+1 252 353 6549",
    "sg:postcode":"27834",
    "sg:province":"NC",
    "sg:website":"www.chickfila.com",
    "wof:name":"Ben Dixon Restaurant",
    "wof:placetype":"venue"
},
  "geometry": {"coordinates":[-77.38405,35.565477],"type":"Point"}
}