{
  "type": "Feature",
  "properties": {
    "addr:full":"3318 Ridgecrest Ct Raleigh NC 27607",
    "addr:housenumber":"3318",
    "addr:postcode":"27607",
    "addr:street":"Ridgecrest Ct",
    "iso:country":"US",
    "sg:address":"3318 Ridgecrest Ct",
    "sg:city":"Raleigh",
    "sg:classifiers":[
        {
            "category":"Professional",
            "type":"Services"
        }
    ],
    "sg:phone":"+1 919 786 1234",
    "sg:postcode":"27607",
    "sg:province":"NC",
    "wof:name":"Kimberly Gina Whichard",
    "wof:placetype":"venue"
},
  "geometry": {"coordinates":[-78.683303,35.812354],"type":"Point"}
}