{
  "type": "Feature",
  "properties": {
    "iso:country":"US",
    "sg:address":"5816 Triangle Dr",
    "sg:city":"Raleigh",
    "sg:classifiers":[
        {
            "category":"Manufacturing",
            "subcategory":"Building Materials",
            "type":"Manufacturing & Wholesale Goods"
        }
    ],
    "sg:phone":"+1 919 781 8068",
    "sg:postcode":"27617",
    "sg:province":"NC",
    "sg:tags":[
        "kitchen",
        "mfg",
        "wood",
        "w",
        "cabinet"
    ],
    "wof:name":"Jacobs Custom Cabinet Designs",
    "wof:placetype":"venue"
},
  "geometry": {"coordinates":[-78.749178,35.894145],"type":"Point"}
}