{
  "type": "Feature",
  "properties": {
    "addr:full":"5333 Reidsville Rd Walkertown NC 27051",
    "addr:housenumber":"5333",
    "addr:postcode":"27051",
    "addr:street":"Reidsville Rd",
    "iso:country":"US",
    "sg:address":"5333 Reidsville Rd",
    "sg:city":"Walkertown",
    "sg:classifiers":[
        {
            "category":"Retail",
            "subcategory":"Car Wash",
            "type":"Services"
        }
    ],
    "sg:phone":"+1   ",
    "sg:postcode":"27051",
    "sg:province":"NC",
    "sg:tags":[
        "carwash"
    ],
    "wof:name":"Triad Pressure Wash",
    "wof:placetype":"venue"
},
  "geometry": {"coordinates":[-80.12921799999999,36.172273],"type":"Point"}
}