{
  "type": "Feature",
  "properties": {
    "addr:full":"218 K Line Dr Ste D Matthews NC 28104",
    "addr:housenumber":"218",
    "addr:postcode":"28104",
    "addr:street":"K Line Dr Ste D",
    "iso:country":"US",
    "sg:address":"218 K Line Dr Ste D",
    "sg:city":"Matthews",
    "sg:classifiers":[
        {
            "category":"Food & Beverages",
            "subcategory":"Specialty",
            "type":"Retail Goods"
        }
    ],
    "sg:phone":"+1 704 684 1449",
    "sg:postcode":"28104",
    "sg:province":"NC",
    "sg:tags":[
        "sauce",
        "condiment"
    ],
    "wof:name":"Vinegar Souther Style Sweet",
    "wof:placetype":"venue"
},
  "geometry": {"coordinates":[-80.686024,35.073941],"type":"Point"}
}