{
  "type": "Feature",
  "properties": {
    "addr:full":"302 S Wadesboro Blvd Mt Gilead NC 27306",
    "addr:housenumber":"302",
    "addr:postcode":"27306",
    "addr:street":"S Wadesboro Blvd Mt",
    "iso:country":"US",
    "sg:address":"302 S Wadesboro Blvd",
    "sg:city":"Mt Gilead",
    "sg:classifiers":[
        {
            "category":"Autos & Motor Vehicles",
            "subcategory":"Fuel & Gas Station",
            "type":"Retail Goods"
        }
    ],
    "sg:phone":"+1 910 439 4867",
    "sg:postcode":"27306",
    "sg:province":"NC",
    "sg:tags":[
        "oil"
    ],
    "wof:name":"Citgo",
    "wof:placetype":"venue"
},
  "geometry": {"coordinates":[-80.005961,35.21682],"type":"Point"}
}