{
  "type": "Feature",
  "properties": {
    "addr:full":"4611 Piper Glen Dr Charlotte NC 28277",
    "addr:housenumber":"4611",
    "addr:postcode":"28277",
    "addr:street":"Piper Glen Dr",
    "iso:country":"US",
    "sg:address":"4611 Piper Glen Dr",
    "sg:city":"Charlotte",
    "sg:classifiers":[
        {
            "category":"Professional",
            "subcategory":"Business Services",
            "type":"Services"
        }
    ],
    "sg:phone":"+1   ",
    "sg:postcode":"28277",
    "sg:province":"NC",
    "wof:name":"PSL Enterpriser Inc",
    "wof:placetype":"venue"
},
  "geometry": {"coordinates":[-80.80759999999999,35.069665],"type":"Point"}
}