{
  "type": "Feature",
  "properties": {
    "iso:country":"US",
    "sg:address":"20607 Pointe Regatta Dr",
    "sg:city":"Cornelius",
    "sg:classifiers":[
        {
            "category":"Professional",
            "subcategory":"Business Services",
            "type":"Services"
        }
    ],
    "sg:phone":"+1   ",
    "sg:postcode":"28031",
    "sg:province":"NC",
    "wof:name":"Capital Investment G",
    "wof:placetype":"venue"
},
  "geometry": {"coordinates":[-80.898943,35.49266],"type":"Point"}
}