{
  "type": "Feature",
  "properties": {
    "addr:full":"8001 N Point Blvd Winston Salem NC 27106",
    "addr:housenumber":"8001",
    "addr:postcode":"27106",
    "addr:street":"N Point Blvd",
    "iso:country":"US",
    "sg:address":"8001 N Point Blvd",
    "sg:city":"Winston Salem",
    "sg:classifiers":[
        {
            "category":"Organizations",
            "subcategory":"Religious Organization",
            "type":"Services"
        }
    ],
    "sg:phone":"+1 336 896 0010",
    "sg:postcode":"27106",
    "sg:province":"NC",
    "sg:tags":[
        "church"
    ],
    "wof:name":"Redeemed Christian Chr-God",
    "wof:placetype":"venue"
},
  "geometry": {"coordinates":[-80.27136299999999,36.150231],"type":"Point"}
}