{
  "type": "Feature",
  "properties": {
    "addr:full":"31 N Main St Weaverville NC 28787",
    "addr:housenumber":"31",
    "addr:postcode":"28787",
    "addr:street":"N Main St",
    "iso:country":"US",
    "sg:address":"31 N Main St",
    "sg:city":"Weaverville",
    "sg:classifiers":[
        {
            "category":"Home & Garden",
            "subcategory":"Furniture",
            "type":"Retail Goods"
        }
    ],
    "sg:phone":"+1 828 645 3091",
    "sg:postcode":"28787",
    "sg:province":"NC",
    "wof:name":"Shope's Furniture",
    "wof:placetype":"venue"
},
  "geometry": {"coordinates":[-82.56053199999999,35.700317],"type":"Point"}
}