{
  "type": "Feature",
  "properties": {
    "iso:country":"US",
    "sg:address":"3750 N Liberty St",
    "sg:city":"Winston Salem",
    "sg:classifiers":[
        {
            "category":"Retail",
            "subcategory":"Repair Shop",
            "type":"Services"
        }
    ],
    "sg:phone":"+1 336 767 3010",
    "sg:postcode":"27105",
    "sg:province":"NC",
    "sg:tags":[
        "repairing",
        "lawn",
        "mower"
    ],
    "wof:name":"Appliance & Mower Svc",
    "wof:placetype":"venue"
},
  "geometry": {"coordinates":[-80.231824,36.131596],"type":"Point"}
}