{
  "type": "Feature",
  "properties": {
    "iso:country":"US",
    "sg:address":"401 S Tryon St",
    "sg:city":"Charlotte",
    "sg:classifiers":[
        {
            "category":"Professional",
            "subcategory":"Lawyer & Legal Services",
            "type":"Services"
        }
    ],
    "sg:phone":"+1 704 332 1256",
    "sg:postcode":"28202",
    "sg:province":"NC",
    "sg:tags":[
        "attorney"
    ],
    "wof:name":"Edmond R Johnson & Assoc",
    "wof:placetype":"venue"
},
  "geometry": {"coordinates":[-80.847504,35.224157],"type":"Point"}
}