{
  "type": "Feature",
  "properties": {
    "iso:country":"US",
    "sg:address":"70 Woodfin St",
    "sg:city":"Asheville",
    "sg:classifiers":[
        {
            "category":"Professional",
            "subcategory":"Research",
            "type":"Services"
        }
    ],
    "sg:phone":"+1 828 225 8959",
    "sg:postcode":"28801",
    "sg:province":"NC",
    "sg:tags":[
        "environmental",
        "ecological"
    ],
    "wof:name":"Singleton & Jordan Environ",
    "wof:placetype":"venue"
},
  "geometry": {"coordinates":[-82.549284,35.598641],"type":"Point"}
}