{
  "type": "Feature",
  "properties": {
    "addr:full":"7232 Wrightsville Ave Wilmington NC 28403",
    "addr:housenumber":"7232",
    "addr:postcode":"28403",
    "addr:street":"Wrightsville Ave",
    "iso:country":"US",
    "sg:address":"7232 Wrightsville Ave",
    "sg:city":"Wilmington",
    "sg:classifiers":[
        {
            "category":"Professional",
            "subcategory":"Lawyer & Legal Services",
            "type":"Services"
        }
    ],
    "sg:phone":"+1 910 256 5820",
    "sg:postcode":"28403",
    "sg:province":"NC",
    "sg:tags":[
        "attorney"
    ],
    "wof:name":"Jennifer L Umbaugh Law Offices",
    "wof:placetype":"venue"
},
  "geometry": {"coordinates":[-77.81556999999999,34.219955],"type":"Point"}
}