{
  "type": "Feature",
  "properties": {
    "addr:full":"7 Salem Gardens Dr Winston Salem NC 27107",
    "addr:housenumber":"7",
    "addr:postcode":"27107",
    "addr:street":"Salem Gardens Dr",
    "iso:country":"US",
    "sg:address":"7 Salem Gardens Dr",
    "sg:city":"Winston Salem",
    "sg:classifiers":[
        {
            "category":"Real Estate",
            "subcategory":"Real Estate Operator",
            "type":"Services"
        }
    ],
    "sg:phone":"+1 336 784 5611",
    "sg:postcode":"27107",
    "sg:province":"NC",
    "sg:tags":[
        "apartment"
    ],
    "wof:name":"Salem Gardens Apartments",
    "wof:placetype":"venue"
},
  "geometry": {"coordinates":[-80.18273000000001,36.081625],"type":"Point"}
}