{
  "type": "Feature",
  "properties": {
    "iso:country":"US",
    "sg:address":"3022 Windrow Ln",
    "sg:city":"Matthews",
    "sg:classifiers":[
        {
            "category":"Wholesale",
            "subcategory":"Machinery & Supplies",
            "type":"Manufacturing & Wholesale Goods"
        }
    ],
    "sg:phone":"+1 704 847 1614",
    "sg:postcode":"28105",
    "sg:province":"NC",
    "sg:tags":[
        "equipment",
        "identification",
        "system",
        "laminating"
    ],
    "wof:name":"Alltech Laminating",
    "wof:placetype":"venue"
},
  "geometry": {"coordinates":[-80.673807,35.131442],"type":"Point"}
}