{
  "type": "Feature",
  "properties": {
    "iso:country":"US",
    "sg:address":"1258 N Raleigh St",
    "sg:city":"Rocky Mount",
    "sg:classifiers":[
        {
            "category":"Autos & Motor Vehicles",
            "subcategory":"Auto Supplies",
            "type":"Retail Goods"
        }
    ],
    "sg:phone":"+1 252 442 8255",
    "sg:postcode":"27801",
    "sg:province":"NC",
    "sg:tags":[
        "automobile",
        "parts"
    ],
    "wof:name":"Advance Auto Parts Inc",
    "wof:placetype":"venue"
},
  "geometry": {"coordinates":[-77.774618,35.945048],"type":"Point"}
}