{
  "type": "Feature",
  "properties": {
    "addr:full":"2870 Armentrout Dr Concord NC 28025",
    "addr:housenumber":"2870",
    "addr:postcode":"28025",
    "addr:street":"Armentrout Dr",
    "iso:country":"US",
    "sg:address":"2870 Armentrout Dr",
    "sg:city":"Concord",
    "sg:classifiers":[
        {
            "category":"Wholesale",
            "subcategory":"Non-durable Goods",
            "type":"Manufacturing & Wholesale Goods"
        }
    ],
    "sg:phone":"+1 704 782 7952",
    "sg:postcode":"28025",
    "sg:province":"NC",
    "sg:tags":[
        "product",
        "felt"
    ],
    "sg:website":"www.sefelt.com",
    "wof:name":"Southeastern Felt & Supply",
    "wof:placetype":"venue"
},
  "geometry": {"coordinates":[-80.57477400000001,35.379183],"type":"Point"}
}