{
  "type": "Feature",
  "properties": {
    "addr:full":"939 Manchester Dr Cary NC 27511",
    "addr:housenumber":"939",
    "addr:postcode":"27511",
    "addr:street":"Manchester Dr",
    "iso:country":"US",
    "sg:address":"939 Manchester Dr",
    "sg:city":"Cary",
    "sg:classifiers":[
        {
            "category":"Professional",
            "subcategory":"Management & Consulting",
            "type":"Services"
        }
    ],
    "sg:phone":"+1   ",
    "sg:postcode":"27511",
    "sg:province":"NC",
    "wof:name":"Lavern M Grady",
    "wof:placetype":"venue"
},
  "geometry": {"coordinates":[-78.74760499999999,35.774765],"type":"Point"}
}