{
  "type": "Feature",
  "properties": {
    "addr:full":"105 Magnolia Ave Pinehurst NC 28374",
    "addr:housenumber":"105",
    "addr:postcode":"28374",
    "addr:street":"Magnolia Ave",
    "iso:country":"US",
    "sg:address":"105 Magnolia Ave",
    "sg:city":"Pinehurst",
    "sg:classifiers":[
        {
            "category":"Building & Trades",
            "subcategory":"Construction",
            "type":"Services"
        }
    ],
    "sg:phone":"+1 910 215 5775",
    "sg:postcode":"28374",
    "sg:province":"NC",
    "sg:tags":[
        "contractor"
    ],
    "wof:name":"Pinnacle Development Corp",
    "wof:placetype":"venue"
},
  "geometry": {"coordinates":[-79.44621600000001,35.199783],"type":"Point"}
}