{
  "type": "Feature",
  "properties": {
    "iso:country":"US",
    "sg:address":"6624 Lyndonville Dr",
    "sg:city":"Charlotte",
    "sg:classifiers":[
        {
            "category":"Shopping",
            "subcategory":"Clothing, Apparel, & Fashions",
            "type":"Retail Goods"
        }
    ],
    "sg:phone":"+1 704 845 8454",
    "sg:postcode":"28277",
    "sg:province":"NC",
    "sg:tags":[
        "swimwear",
        "accessory"
    ],
    "wof:name":"Ujena Swimwear & Fashions",
    "wof:placetype":"venue"
},
  "geometry": {"coordinates":[-80.796211,35.036312],"type":"Point"}
}