{
  "type": "Feature",
  "properties": {
    "addr:full":"326 E Market St Smithfield NC 27577",
    "addr:housenumber":"326",
    "addr:postcode":"27577",
    "addr:street":"E Market St",
    "iso:country":"US",
    "sg:address":"326 E Market St",
    "sg:city":"Smithfield",
    "sg:classifiers":[
        {
            "category":"Shopping",
            "subcategory":"Computers & Home Electronics",
            "type":"Retail Goods"
        }
    ],
    "sg:phone":"+1 919 934 4358",
    "sg:postcode":"27577",
    "sg:province":"NC",
    "sg:tags":[
        "equipment",
        "satellite",
        "system"
    ],
    "wof:name":"DIRECTV",
    "wof:placetype":"venue"
},
  "geometry": {"coordinates":[-78.345676,35.510981],"type":"Point"}
}