{
  "type": "Feature",
  "properties": {
    "addr:full":"204 E Main St Benson NC 27504",
    "addr:housenumber":"204",
    "addr:postcode":"27504",
    "addr:street":"E Main St",
    "iso:country":"US",
    "sg:address":"204 E Main St",
    "sg:city":"Benson",
    "sg:classifiers":[
        {
            "category":"Real Estate",
            "subcategory":"Real Estate Operator",
            "type":"Services"
        }
    ],
    "sg:phone":"+1 919 894 5850",
    "sg:postcode":"27504",
    "sg:province":"NC",
    "sg:tags":[
        "building",
        "nonresidential"
    ],
    "wof:name":"P & M Properties LLC",
    "wof:placetype":"venue"
},
  "geometry": {"coordinates":[-78.54677,35.380679],"type":"Point"}
}