{
  "type": "Feature",
  "properties": {
    "iso:country":"US",
    "sg:address":"6555 State Hwy 94",
    "sg:city":"Fairfield",
    "sg:classifiers":[
        {
            "category":"Travel",
            "subcategory":"Hotels & Motels",
            "type":"Entertainment"
        }
    ],
    "sg:phone":"+1 252 926 1451",
    "sg:postcode":"27826",
    "sg:province":"NC",
    "wof:name":"Harris Steak & Seafood House",
    "wof:placetype":"venue"
},
  "geometry": {"coordinates":[-76.30398,35.533749],"type":"Point"}
}