{
  "type": "Feature",
  "properties": {
    "iso:country":"US",
    "sg:address":"900 Old Mill Rd",
    "sg:city":"High Point",
    "sg:classifiers":[
        {
            "category":"Organizations",
            "subcategory":"Religious Organization",
            "type":"Services"
        }
    ],
    "sg:phone":"+1 336 869 8928",
    "sg:postcode":"27265",
    "sg:province":"NC",
    "sg:tags":[
        "church"
    ],
    "wof:name":"Church Of God Of Prophecy",
    "wof:placetype":"venue"
},
  "geometry": {"coordinates":[-80.000906,36.027406],"type":"Point"}
}