{
  "type": "Feature",
  "properties": {
    "iso:country":"US",
    "sg:address":"1300 S English St",
    "sg:city":"Greensboro",
    "sg:classifiers":[
        {
            "category":"Building & Trades",
            "subcategory":"Landscaping Services",
            "type":"Services"
        }
    ],
    "sg:phone":"+1 336 987 1351",
    "sg:postcode":"27401",
    "sg:province":"NC",
    "sg:tags":[
        "tree"
    ],
    "wof:name":"Hairston Tree Svc",
    "wof:placetype":"venue"
},
  "geometry": {"coordinates":[-79.75813599999999,36.058909],"type":"Point"}
}