{
  "type": "Feature",
  "properties": {
    "iso:country":"US",
    "sg:address":"1115 John Small Ave",
    "sg:city":"Washington",
    "sg:classifiers":[
        {
            "category":"Restaurant",
            "type":"Food & Drink"
        }
    ],
    "sg:phone":"+1 252 975 6050",
    "sg:postcode":"27889",
    "sg:province":"NC",
    "sg:tags":[
        "drinking",
        "eating"
    ],
    "wof:name":"Franks Pizza & Italian Rest",
    "wof:placetype":"venue"
},
  "geometry": {"coordinates":[-77.03741100000001,35.547146],"type":"Point"}
}