{
  "type": "Feature",
  "properties": {
    "addr:full":"800 Raleigh Rd Rocky Mount NC 27803",
    "addr:housenumber":"800",
    "addr:postcode":"27803",
    "addr:street":"Raleigh Rd",
    "iso:country":"US",
    "sg:address":"800 Raleigh Rd",
    "sg:city":"Rocky Mount",
    "sg:classifiers":[
        {
            "category":"Shopping",
            "subcategory":"Pharmacy",
            "type":"Retail Goods"
        }
    ],
    "sg:phone":"+1 252 446 0391",
    "sg:postcode":"27803",
    "sg:province":"NC",
    "sg:tags":[
        "drug",
        "store"
    ],
    "wof:name":"Eckerd",
    "wof:placetype":"venue"
},
  "geometry": {"coordinates":[-77.810452,35.933023],"type":"Point"}
}