{
  "type": "Feature",
  "properties": {
    "iso:country":"US",
    "sg:address":"806 Eufola Rd",
    "sg:city":"Statesville",
    "sg:classifiers":[
        {
            "category":"Organizations",
            "subcategory":"Religious Organization",
            "type":"Services"
        }
    ],
    "sg:phone":"+1 704 872 6001",
    "sg:postcode":"28677",
    "sg:province":"NC",
    "sg:tags":[
        "church"
    ],
    "wof:name":"Clark's Chapel Baptist Church",
    "wof:placetype":"venue"
},
  "geometry": {"coordinates":[-80.99987900000001,35.733469],"type":"Point"}
}