{
  "type": "Feature",
  "properties": {
    "iso:country":"US",
    "sg:address":"4520 Longworth Dr SE",
    "sg:city":"Kernersville",
    "sg:classifiers":[
        {
            "category":"Building & Trades",
            "subcategory":"Electrical",
            "type":"Services"
        }
    ],
    "sg:phone":"+1 336 784 8909",
    "sg:postcode":"27284",
    "sg:province":"NC",
    "sg:tags":[
        "electrical",
        "contractor"
    ],
    "wof:name":"JD & Merritt Electrical Inc",
    "wof:placetype":"venue"
},
  "geometry": {"coordinates":[-80.156002,36.099566],"type":"Point"}
}