{
  "type": "Feature",
  "properties": {
    "iso:country":"US",
    "sg:address":"4783 High Point Rd",
    "sg:city":"Kernersville",
    "sg:classifiers":[
        {
            "category":"Building & Trades",
            "subcategory":"Plumbing",
            "type":"Services"
        }
    ],
    "sg:phone":"+1 336 884 7371",
    "sg:postcode":"27284",
    "sg:province":"NC",
    "sg:tags":[
        "heating",
        "contractor"
    ],
    "wof:name":"Compton's Electrical Heating",
    "wof:placetype":"venue"
},
  "geometry": {"coordinates":[-80.094286,36.024455],"type":"Point"}
}