{
  "type": "Feature",
  "properties": {
    "addr:full":"1223 Carthage St Sanford NC 27330",
    "addr:housenumber":"1223",
    "addr:postcode":"27330",
    "addr:street":"Carthage St",
    "iso:country":"US",
    "sg:address":"1223 Carthage St",
    "sg:city":"Sanford",
    "sg:classifiers":[
        {
            "category":"Health Services",
            "subcategory":"Doctor",
            "type":"Services"
        }
    ],
    "sg:phone":"+1 919 776 7549",
    "sg:postcode":"27330",
    "sg:province":"NC",
    "sg:tags":[
        "physician",
        "surgeon"
    ],
    "sg:website":"www.carolinaeye.com",
    "wof:name":"Carolina Eye Assoc",
    "wof:placetype":"venue"
},
  "geometry": {"coordinates":[-79.18915,35.467182],"type":"Point"}
}