{
  "type": "Feature",
  "properties": {
    "iso:country":"US",
    "sg:address":"5721 Country Club Rd",
    "sg:city":"Winston Salem",
    "sg:classifiers":[
        {
            "category":"Building & Trades",
            "subcategory":"Construction",
            "type":"Services"
        }
    ],
    "sg:phone":"+1 336 946 2308",
    "sg:postcode":"27104",
    "sg:province":"NC",
    "sg:tags":[
        "waterproofing",
        "contractor"
    ],
    "wof:name":"Amco Services Inc",
    "wof:placetype":"venue"
},
  "geometry": {"coordinates":[-80.375806,36.093656],"type":"Point"}
}