{
  "type": "Feature",
  "properties": {
    "addr:full":"2528 Hankins Rd Marion NC 28752",
    "addr:housenumber":"2528",
    "addr:postcode":"28752",
    "addr:street":"Hankins Rd",
    "iso:country":"US",
    "sg:address":"2528 Hankins Rd",
    "sg:city":"Marion",
    "sg:classifiers":[
        {
            "category":"Recreation",
            "subcategory":"Marina",
            "type":"Entertainment"
        }
    ],
    "sg:phone":"+1 828 659 8800",
    "sg:postcode":"28752",
    "sg:province":"NC",
    "sg:tags":[
        "operation",
        "yard",
        "boat"
    ],
    "wof:name":"Terrell's Boat Yard",
    "wof:placetype":"venue"
},
  "geometry": {"coordinates":[-82.006094,35.732958],"type":"Point"}
}