{
  "type": "Feature",
  "properties": {
    "addr:full":"3914 Fieldcrest Rd Charlotte NC 28217",
    "addr:housenumber":"3914",
    "addr:postcode":"28217",
    "addr:street":"Fieldcrest Rd",
    "iso:country":"US",
    "sg:address":"3914 Fieldcrest Rd",
    "sg:city":"Charlotte",
    "sg:classifiers":[
        {
            "category":"Personal",
            "type":"Services"
        }
    ],
    "sg:phone":"+1 704 222 5336",
    "sg:postcode":"28217",
    "sg:province":"NC",
    "sg:tags":[
        "butlers'",
        "maids'"
    ],
    "wof:name":"Maid In Charlotte",
    "wof:placetype":"venue"
},
  "geometry": {"coordinates":[-80.89547,35.199263],"type":"Point"}
}