{
  "type": "Feature",
  "properties": {
    "addr:full":"3240 Bentwillow Dr Fuquay Varina NC 27526",
    "addr:postcode":"3240;27526",
    "addr:street":"Bentwillow Dr",
    "iso:country":"US",
    "sg:address":"3240 Bentwillow Dr",
    "sg:city":"Fuquay Varina",
    "sg:classifiers":[
        {
            "category":"Shopping",
            "subcategory":"Gifts & Souvenirs",
            "type":"Retail Goods"
        }
    ],
    "sg:phone":"+1 919 567 2056",
    "sg:postcode":"27526",
    "sg:province":"NC",
    "wof:name":"Two Bs In A Basket",
    "wof:placetype":"venue"
},
  "geometry": {"coordinates":[-78.744412,35.63592],"type":"Point"}
}