{
  "type": "Feature",
  "properties": {
    "addr:full":"508 W Dixon Blvd Shelby NC 28152",
    "addr:housenumber":"508",
    "addr:postcode":"28152",
    "addr:street":"W Dixon Blvd",
    "iso:country":"US",
    "sg:address":"508 W Dixon Blvd",
    "sg:city":"Shelby",
    "sg:classifiers":[
        {
            "category":"Shopping",
            "type":"Retail Goods"
        }
    ],
    "sg:phone":"+1 704 482 9761",
    "sg:postcode":"28152",
    "sg:province":"NC",
    "sg:tags":[
        "cosmetic",
        "perfume"
    ],
    "wof:name":"Kings Beauty Supply",
    "wof:placetype":"venue"
},
  "geometry": {"coordinates":[-81.55373,35.282328],"type":"Point"}
}