{
  "type": "Feature",
  "properties": {
    "iso:country":"US",
    "sg:address":"2017 Echo Ln",
    "sg:city":"Gastonia",
    "sg:classifiers":[
        {
            "category":"Social Services",
            "subcategory":"Child Care",
            "type":"Services"
        }
    ],
    "sg:phone":"+1 704 865 1513",
    "sg:postcode":"28052",
    "sg:province":"NC",
    "sg:tags":[
        "day"
    ],
    "wof:name":"Annie H Farley",
    "wof:placetype":"venue"
},
  "geometry": {"coordinates":[-81.21228000000001,35.234778],"type":"Point"}
}