{
  "type": "Feature",
  "properties": {
    "addr:full":"6446 Southern Nash High Rd Bailey NC 27807",
    "addr:housenumber":"6446",
    "addr:postcode":"27807",
    "addr:street":"Southern;High Rd",
    "iso:country":"US",
    "sg:address":"6446 Southern Nash High Rd",
    "sg:city":"Bailey",
    "sg:classifiers":[
        {
            "category":"Education",
            "subcategory":"School",
            "type":"Public Place"
        }
    ],
    "sg:phone":"+1 252 235 5200",
    "sg:postcode":"27807",
    "sg:province":"NC",
    "wof:name":"Southern Nash High School",
    "wof:placetype":"venue"
},
  "geometry": {"coordinates":[-78.085773,35.84961],"type":"Point"}
}