{
  "type": "Feature",
  "properties": {
    "iso:country":"US",
    "sg:address":"190 Winterbell Dr",
    "sg:city":"Mooresville",
    "sg:classifiers":[
        {
            "category":"Professional",
            "subcategory":"Advertising",
            "type":"Services"
        }
    ],
    "sg:phone":"+1 704 662 8776",
    "sg:postcode":"28115",
    "sg:province":"NC",
    "sg:tags":[
        "distribution"
    ],
    "wof:name":"Distributor Herbalife Indpndnt",
    "wof:placetype":"venue"
},
  "geometry": {"coordinates":[-80.779414,35.610111],"type":"Point"}
}