{
  "type": "Feature",
  "properties": {
    "iso:country":"US",
    "sg:address":"1677 S Asbury Church Rd",
    "sg:city":"Washington",
    "sg:classifiers":[
        {
            "category":"Building & Trades",
            "subcategory":"Construction",
            "type":"Services"
        }
    ],
    "sg:phone":"+1 252 946 0293",
    "sg:postcode":"27889",
    "sg:province":"NC",
    "sg:tags":[
        "house"
    ],
    "wof:name":"Evans C E & R Construction",
    "wof:placetype":"venue"
},
  "geometry": {"coordinates":[-76.990943,35.526245],"type":"Point"}
}