{
  "type": "Feature",
  "properties": {
    "addr:full":"221 Locust St Spruce Pine NC 28777",
    "addr:housenumber":"221",
    "addr:postcode":"28777",
    "addr:street":"Locust St",
    "iso:country":"US",
    "sg:address":"221 Locust St",
    "sg:city":"Spruce Pine",
    "sg:classifiers":[
        {
            "category":"Shopping",
            "type":"Retail Goods"
        },
        {
            "category":"Recreation",
            "type":"Entertainment"
        }
    ],
    "sg:phone":"+1 828 765 1562",
    "sg:postcode":"28777",
    "sg:province":"NC",
    "sg:tags":[
        "art",
        "gallery",
        "merchandise",
        "dealer"
    ],
    "wof:name":"Laurel Twisted Gallery",
    "wof:placetype":"venue"
},
  "geometry": {"coordinates":[-82.068922,35.91548],"type":"Point"}
}