{
  "type": "Feature",
  "properties": {
    "addr:full":"9123 Covey Hollow Ct Charlotte NC 28210",
    "addr:housenumber":"9123",
    "addr:postcode":"28210",
    "addr:street":"Covey Hollow Ct",
    "iso:country":"US",
    "sg:address":"9123 Covey Hollow Ct",
    "sg:city":"Charlotte",
    "sg:classifiers":[
        {
            "category":"Real Estate",
            "subcategory":"Real Estate Agent",
            "type":"Services"
        }
    ],
    "sg:phone":"+1 704 554 1920",
    "sg:postcode":"28210",
    "sg:province":"NC",
    "sg:website":"www.geoffcampbell.com",
    "wof:name":"Geoff Campbell Realty Inc",
    "wof:placetype":"venue"
},
  "geometry": {"coordinates":[-80.847751,35.101894],"type":"Point"}
}