{
  "type": "Feature",
  "properties": {
    "addr:full":"259 Pilgrams Way Boone NC 28607",
    "addr:housenumber":"259",
    "addr:postcode":"28607",
    "addr:street":"Pilgrams Way",
    "iso:country":"US",
    "sg:address":"259 Pilgrams Way",
    "sg:city":"Boone",
    "sg:classifiers":[
        {
            "category":"Organizations",
            "subcategory":"Religious Organization",
            "type":"Services"
        }
    ],
    "sg:phone":"+1 828 264 8338",
    "sg:postcode":"28607",
    "sg:province":"NC",
    "sg:tags":[
        "church"
    ],
    "wof:name":"St Elizabeth Church",
    "wof:placetype":"venue"
},
  "geometry": {"coordinates":[-81.6614,36.195092],"type":"Point"}
}