{
  "type": "Feature",
  "properties": {
    "iso:country":"US",
    "sg:address":"10972 Old US Hwy 64",
    "sg:city":"Spring Hope",
    "sg:classifiers":[
        {
            "category":"Recreation",
            "subcategory":"Amusement Park",
            "type":"Entertainment"
        }
    ],
    "sg:phone":"+1 252 478 5705",
    "sg:postcode":"27882",
    "sg:province":"NC",
    "wof:name":"Toot-N-Tell",
    "wof:placetype":"venue"
},
  "geometry": {"coordinates":[-78.184905,35.921075],"type":"Point"}
}