{
  "type": "Feature",
  "properties": {
    "iso:country":"US",
    "sg:address":"2245 Zephyr Rd",
    "sg:city":"Dobson",
    "sg:classifiers":[
        {
            "category":"Organizations",
            "subcategory":"Religious Organization",
            "type":"Services"
        }
    ],
    "sg:phone":"+1 336 366 2408",
    "sg:postcode":"27017",
    "sg:province":"NC",
    "sg:tags":[
        "church"
    ],
    "wof:name":"Salem Fork Christian Church",
    "wof:placetype":"venue"
},
  "geometry": {"coordinates":[-80.780872,36.396747],"type":"Point"}
}