{
  "type": "Feature",
  "properties": {
    "iso:country":"US",
    "sg:address":"350 N Gordon Dr",
    "sg:city":"Winston Salem",
    "sg:classifiers":[
        {
            "category":"Professional",
            "subcategory":"Computer Services",
            "type":"Services"
        }
    ],
    "sg:phone":"+1   ",
    "sg:postcode":"27104",
    "sg:province":"NC",
    "sg:tags":[
        "related"
    ],
    "wof:name":"T3 Inc",
    "wof:placetype":"venue"
},
  "geometry": {"coordinates":[-80.317605,36.094648],"type":"Point"}
}