{
  "type": "Feature",
  "properties": {
    "iso:country":"US",
    "sg:address":"3443 Wilkinson Blvd",
    "sg:city":"Charlotte",
    "sg:classifiers":[
        {
            "category":"Restaurant",
            "type":"Food & Drink"
        }
    ],
    "sg:menulink":"http://www.allmenus.com/nc/charlotte/13062-churchs-chicken/menu/",
    "sg:phone":"+1 704 399 4035",
    "sg:postcode":"28208",
    "sg:province":"NC",
    "sg:tags":[
        "chicken",
        "wing"
    ],
    "wof:name":"Church's Chicken",
    "wof:placetype":"venue"
},
  "geometry": {"coordinates":[-80.898492,35.224182],"type":"Point"}
}