{
  "type": "Feature",
  "properties": {
    "addr:full":"4425 Park Rd Charlotte NC 28209",
    "addr:housenumber":"4425",
    "addr:postcode":"28209",
    "addr:street":"Park Rd",
    "iso:country":"US",
    "sg:address":"4425 Park Rd",
    "sg:city":"Charlotte",
    "sg:classifiers":[
        {
            "category":"Professional",
            "subcategory":"Employment Agencies",
            "type":"Services"
        }
    ],
    "sg:phone":"+1 704 523 8315",
    "sg:postcode":"28209",
    "sg:province":"NC",
    "sg:tags":[
        "opportunity"
    ],
    "sg:website":"http://www.selectstaffing.com",
    "wof:name":"Select Staffing",
    "wof:placetype":"venue"
},
  "geometry": {"coordinates":[-80.850922,35.17094],"type":"Point"}
}