{
  "type": "Feature",
  "properties": {
    "iso:country":"US",
    "sg:address":"2030 Clark Ave",
    "sg:city":"Raleigh",
    "sg:classifiers":[
        {
            "category":"Shopping",
            "subcategory":"Stationery & Office Supplies",
            "type":"Retail Goods"
        },
        {
            "category":"Shopping",
            "subcategory":"Party Supplies",
            "type":"Retail Goods"
        },
        {
            "category":"Shopping",
            "subcategory":"Gifts & Souvenirs",
            "type":"Retail Goods"
        },
        {
            "category":"Personal",
            "type":"Services"
        }
    ],
    "sg:phone":"+1 919 828 4053",
    "sg:postcode":"27605",
    "sg:province":"NC",
    "sg:tags":[
        "shop",
        "favors",
        "decoration",
        "planning",
        "event",
        "store"
    ],
    "wof:name":"The Party Shop",
    "wof:placetype":"venue"
},
  "geometry": {"coordinates":[-78.65982700000001,35.788997],"type":"Point"}
}