{
  "type": "Feature",
  "properties": {
    "iso:country":"US",
    "sg:address":"1316 Patton Ave",
    "sg:city":"Asheville",
    "sg:classifiers":[
        {
            "category":"Wholesale",
            "subcategory":"Tobacco Products",
            "type":"Manufacturing & Wholesale Goods"
        }
    ],
    "sg:phone":"+1 828 236 1131",
    "sg:postcode":"28806",
    "sg:province":"NC",
    "sg:tags":[
        "cigarette",
        "cigar",
        "dealer"
    ],
    "wof:name":"All-Safe Towing & Recovery",
    "wof:placetype":"venue"
},
  "geometry": {"coordinates":[-82.603185,35.584706],"type":"Point"}
}