{
  "type": "Feature",
  "properties": {
    "addr:full":"4716 Johnson Pond Rd Apex NC 27539",
    "addr:housenumber":"4716",
    "addr:postcode":"27539",
    "addr:street":"Johnson Pond Rd",
    "iso:country":"US",
    "sg:address":"4716 Johnson Pond Rd",
    "sg:city":"Apex",
    "sg:classifiers":[
        {
            "category":"Home & Garden",
            "subcategory":"Building Materials",
            "type":"Retail Goods"
        },
        {
            "category":"Building & Trades",
            "subcategory":"Construction",
            "type":"Services"
        }
    ],
    "sg:phone":"+1 919 779 9672",
    "sg:postcode":"27539",
    "sg:province":"NC",
    "sg:tags":[
        "builder",
        "gazebo",
        "patio"
    ],
    "wof:name":"Jmc Construction",
    "wof:placetype":"venue"
},
  "geometry": {"coordinates":[-78.734623,35.650026],"type":"Point"}
}