{
  "type": "Feature",
  "properties": {
    "addr:full":"6147 Winged Elm Ct Charlotte NC 28212",
    "addr:housenumber":"6147",
    "addr:postcode":"28212",
    "addr:street":"Winged Elm Ct",
    "iso:country":"US",
    "sg:address":"6147 Winged Elm Ct",
    "sg:city":"Charlotte",
    "sg:classifiers":[
        {
            "category":"Real Estate",
            "subcategory":"Real Estate Agent",
            "type":"Services"
        }
    ],
    "sg:phone":"+1 704 535 0225",
    "sg:postcode":"28212",
    "sg:province":"NC",
    "sg:tags":[
        "apartment",
        "community"
    ],
    "wof:name":"Forest Ridge Apartments",
    "wof:placetype":"venue"
},
  "geometry": {"coordinates":[-80.748594,35.197625],"type":"Point"}
}