{
  "type": "Feature",
  "properties": {
    "iso:country":"US",
    "sg:address":"153 Old County Rd",
    "sg:city":"Manteo",
    "sg:classifiers":[
        {
            "category":"Marine",
            "type":"Transportation"
        }
    ],
    "sg:phone":"+1 252 473 3046",
    "sg:postcode":"27954",
    "sg:province":"NC",
    "sg:tags":[
        "surveyor"
    ],
    "wof:name":"Andrews Marine Surveyors",
    "wof:placetype":"venue"
},
  "geometry": {"coordinates":[-75.702296,35.921509],"type":"Point"}
}