{
  "type": "Feature",
  "properties": {
    "addr:full":"1525 S Lafayette St Shelby NC 28152",
    "addr:housenumber":"1525",
    "addr:postcode":"28152",
    "addr:street":"S Lafayette St",
    "iso:country":"US",
    "sg:address":"1525 S Lafayette St",
    "sg:city":"Shelby",
    "sg:classifiers":[
        {
            "category":"Shopping",
            "subcategory":"Department Store",
            "type":"Retail Goods"
        }
    ],
    "sg:phone":"+1 704 471 2345",
    "sg:postcode":"28152",
    "sg:province":"NC",
    "sg:tags":[
        "shop"
    ],
    "wof:name":"Family Dollar Store",
    "wof:placetype":"venue"
},
  "geometry": {"coordinates":[-81.55462900000001,35.266705],"type":"Point"}
}