{
  "type": "Feature",
  "properties": {
    "iso:country":"US",
    "sg:address":"154 Backhoe Rd NE",
    "sg:city":"Leland",
    "sg:classifiers":[
        {
            "category":"Wholesale",
            "subcategory":"Electrical",
            "type":"Manufacturing & Wholesale Goods"
        }
    ],
    "sg:phone":"+1 910 383 0937",
    "sg:postcode":"28451",
    "sg:province":"NC",
    "sg:tags":[
        "equipment"
    ],
    "sg:website":"www.tidewatertechnologies.com",
    "wof:name":"Tidewater Technologies Inc",
    "wof:placetype":"venue"
},
  "geometry": {"coordinates":[-78.02717,34.217287],"type":"Point"}
}