{
  "type": "Feature",
  "properties": {
    "iso:country":"US",
    "sg:address":"2210 Taylorsville Rd",
    "sg:city":"Lenoir",
    "sg:classifiers":[
        {
            "category":"Food & Beverages",
            "subcategory":"Groceries & Convenience Stores",
            "type":"Retail Goods"
        }
    ],
    "sg:phone":"+1 828 754 8415",
    "sg:postcode":"28645",
    "sg:province":"NC",
    "sg:tags":[
        "grocer"
    ],
    "wof:name":"Oak Hill Superette",
    "wof:placetype":"venue"
},
  "geometry": {"coordinates":[-81.42604300000001,35.909418],"type":"Point"}
}