{
  "type": "Feature",
  "properties": {
    "iso:country":"US",
    "sg:address":"110 W Main St",
    "sg:city":"Aulander",
    "sg:classifiers":[
        {
            "category":"Insurance",
            "subcategory":"Insurance Agent",
            "type":"Services"
        }
    ],
    "sg:phone":"+1 252 345 1791",
    "sg:postcode":"27805",
    "sg:province":"NC",
    "wof:name":"Bertie County Farm Bureau",
    "wof:placetype":"venue"
},
  "geometry": {"coordinates":[-77.114284,36.22958],"type":"Point"}
}