{
  "type": "Feature",
  "properties": {
    "addr:full":"204 E Academy St Asheboro NC 27203",
    "addr:housenumber":"204",
    "addr:postcode":"27203",
    "addr:street":"E Academy St",
    "iso:country":"US",
    "sg:address":"204 E Academy St",
    "sg:city":"Asheboro",
    "sg:classifiers":[
        {
            "category":"Professional",
            "subcategory":"Lawyer & Legal Services",
            "type":"Services"
        }
    ],
    "sg:phone":"+1   ",
    "sg:postcode":"27203",
    "sg:province":"NC",
    "wof:name":"Dwi Service",
    "wof:placetype":"venue"
},
  "geometry": {"coordinates":[-79.812208,35.703176],"type":"Point"}
}