{
  "type": "Feature",
  "properties": {
    "addr:full":"2725 Horse Pen Creek Rd Greensboro NC 27410",
    "addr:housenumber":"2725",
    "addr:postcode":"27410",
    "addr:street":"Horse Pen Creek Rd",
    "iso:country":"US",
    "sg:address":"2725 Horse Pen Creek Rd",
    "sg:city":"Greensboro",
    "sg:classifiers":[
        {
            "category":"Health Services",
            "subcategory":"Doctor",
            "type":"Services"
        }
    ],
    "sg:phone":"+1 336 855 3060",
    "sg:postcode":"27410",
    "sg:province":"NC",
    "wof:name":"Roland M Jones DDS",
    "wof:placetype":"venue"
},
  "geometry": {"coordinates":[-79.87709099999999,36.118813],"type":"Point"}
}