{
  "type": "Feature",
  "properties": {
    "iso:country":"US",
    "sg:address":"2454 S Lafayette St",
    "sg:city":"Shelby",
    "sg:classifiers":[
        {
            "category":"Social Services",
            "subcategory":"Child Care",
            "type":"Services"
        }
    ],
    "sg:phone":"+1 704 484 9555",
    "sg:postcode":"28152",
    "sg:province":"NC",
    "wof:name":"Kiddieland Child Development",
    "wof:placetype":"venue"
},
  "geometry": {"coordinates":[-81.56494000000001,35.218763],"type":"Point"}
}