{
  "type": "Feature",
  "properties": {
    "addr:full":"8055 Reeps Grove Church Rd Vale NC 28168",
    "addr:housenumber":"8055",
    "addr:postcode":"28168",
    "addr:street":"Reeps Grove Church Rd",
    "iso:country":"US",
    "sg:address":"8055 Reeps Grove Church Rd",
    "sg:city":"Vale",
    "sg:classifiers":[
        {
            "category":"Organizations",
            "subcategory":"Religious Organization",
            "type":"Services"
        }
    ],
    "sg:phone":"+1 704 276 2971",
    "sg:postcode":"28168",
    "sg:province":"NC",
    "sg:tags":[
        "church"
    ],
    "wof:name":"Reepsgrove United Mthdst Chr",
    "wof:placetype":"venue"
},
  "geometry": {"coordinates":[-81.448751,35.539578],"type":"Point"}
}