{
  "type": "Feature",
  "properties": {
    "iso:country":"US",
    "sg:address":"5415 Lake Vista Dr",
    "sg:city":"Durham",
    "sg:classifiers":[
        {
            "category":"Professional",
            "subcategory":"Business Services",
            "type":"Services"
        }
    ],
    "sg:phone":"+1   ",
    "sg:postcode":"27712",
    "sg:province":"NC",
    "wof:name":"June Merlino Consulting",
    "wof:placetype":"venue"
},
  "geometry": {"coordinates":[-78.955656,36.084593],"type":"Point"}
}