{
  "type": "Feature",
  "properties": {
    "addr:full":"4805 Cardinal Grove Blvd Raleigh NC 27616",
    "addr:housenumber":"4805",
    "addr:postcode":"27616",
    "addr:street":"Cardinal Grove Blvd",
    "iso:country":"US",
    "sg:address":"4805 Cardinal Grove Blvd",
    "sg:city":"Raleigh",
    "sg:classifiers":[
        {
            "category":"Professional",
            "subcategory":"Detective & Security Services",
            "type":"Services"
        }
    ],
    "sg:phone":"+1 919 524 4474",
    "sg:postcode":"27616",
    "sg:province":"NC",
    "sg:tags":[
        "unarmed",
        "patrol",
        "armed"
    ],
    "wof:name":"Supreme Security",
    "wof:placetype":"venue"
},
  "geometry": {"coordinates":[-78.54968700000001,35.843493],"type":"Point"}
}