{
  "type": "Feature",
  "properties": {
    "iso:country":"US",
    "sg:address":"6 Duncan Ln",
    "sg:city":"Pinehurst",
    "sg:classifiers":[
        {
            "category":"Professional",
            "type":"Services"
        }
    ],
    "sg:phone":"+1 910 235 9211",
    "sg:postcode":"28374",
    "sg:province":"NC",
    "sg:tags":[
        "establishment"
    ],
    "wof:name":"Mpd Digital",
    "wof:placetype":"venue"
},
  "geometry": {"coordinates":[-79.45879100000001,35.219231],"type":"Point"}
}