{
  "type": "Feature",
  "properties": {
    "addr:full":"19400 Jetton Rd Cornelius NC 28031",
    "addr:housenumber":"19400",
    "addr:postcode":"28031",
    "addr:street":"Jetton Rd",
    "iso:country":"US",
    "sg:address":"19400 Jetton Rd",
    "sg:city":"Cornelius",
    "sg:classifiers":[
        {
            "category":"Home & Garden",
            "subcategory":"Furniture",
            "type":"Retail Goods"
        }
    ],
    "sg:phone":"+1 704 987 3544",
    "sg:postcode":"28031",
    "sg:province":"NC",
    "wof:name":"Porches & Yards",
    "wof:placetype":"venue"
},
  "geometry": {"coordinates":[-80.891469,35.476785],"type":"Point"}
}