{
  "type": "Feature",
  "properties": {
    "iso:country":"US",
    "sg:address":"610 Madame Moores Ln",
    "sg:city":"New Bern",
    "sg:classifiers":[
        {
            "category":"Professional",
            "type":"Services"
        }
    ],
    "sg:phone":"+1 252 638 4456",
    "sg:postcode":"28562",
    "sg:province":"NC",
    "wof:name":"Society For Preserv & Enc",
    "wof:placetype":"venue"
},
  "geometry": {"coordinates":[-77.04920300000001,35.08391],"type":"Point"}
}