{
  "type": "Feature",
  "properties": {
    "addr:full":"4325 Lake Boone Trl Raleigh NC 27607",
    "addr:housenumber":"4325",
    "addr:postcode":"27607",
    "addr:street":"Lake Boone Trl",
    "iso:country":"US",
    "sg:address":"4325 Lake Boone Trl",
    "sg:city":"Raleigh",
    "sg:classifiers":[
        {
            "category":"Health Services",
            "subcategory":"Clinic",
            "type":"Services"
        }
    ],
    "sg:phone":"+1 919 420 0336",
    "sg:postcode":"27607",
    "sg:province":"NC",
    "sg:tags":[
        "home"
    ],
    "sg:website":"www.interimhealthcare.com",
    "wof:name":"Interim Healthcare",
    "wof:placetype":"venue"
},
  "geometry": {"coordinates":[-78.704948,35.815392],"type":"Point"}
}