{
  "type": "Feature",
  "properties": {
    "iso:country":"US",
    "sg:address":"808 W Ketchie St",
    "sg:city":"China Grove",
    "sg:classifiers":[
        {
            "category":"Social Services",
            "subcategory":"Child Care",
            "type":"Services"
        }
    ],
    "sg:phone":"+1   ",
    "sg:postcode":"28023",
    "sg:province":"NC",
    "sg:tags":[
        "day"
    ],
    "wof:name":"Mama Carols Day Care Center",
    "wof:placetype":"venue"
},
  "geometry": {"coordinates":[-80.58515,35.57826],"type":"Point"}
}