{
  "type": "Feature",
  "properties": {
    "iso:country":"US",
    "sg:address":"4365 Panther Pl",
    "sg:city":"Charlotte",
    "sg:classifiers":[
        {
            "category":"Organizations",
            "subcategory":"Community Association",
            "type":"Services"
        }
    ],
    "sg:phone":"+1 704 494 4228",
    "sg:postcode":"28269",
    "sg:province":"NC",
    "wof:name":"Huntingdon Hoa",
    "wof:placetype":"venue"
},
  "geometry": {"coordinates":[-80.805308,35.329311],"type":"Point"}
}