{
  "type": "Feature",
  "properties": {
    "iso:country":"US",
    "sg:address":"319 State Hwy 42 S",
    "sg:city":"Asheboro",
    "sg:classifiers":[
        {
            "category":"Food & Beverages",
            "subcategory":"Groceries & Convenience Stores",
            "type":"Retail Goods"
        }
    ],
    "sg:phone":"+1 336 629 1794",
    "sg:postcode":"27205",
    "sg:province":"NC",
    "sg:tags":[
        "grocer"
    ],
    "wof:name":"Cox's Grocery",
    "wof:placetype":"venue"
},
  "geometry": {"coordinates":[-79.784003,35.696563],"type":"Point"}
}