{
  "type": "Feature",
  "properties": {
    "addr:full":"706 Walston Ave Kinston NC 28504",
    "addr:housenumber":"706",
    "addr:postcode":"28504",
    "addr:street":"Walston Ave",
    "iso:country":"US",
    "sg:address":"706 Walston Ave",
    "sg:city":"Kinston",
    "sg:classifiers":[
        {
            "category":"Personal",
            "subcategory":"Beauty Salon",
            "type":"Services"
        }
    ],
    "sg:phone":"+1 252 522 5579",
    "sg:postcode":"28504",
    "sg:province":"NC",
    "sg:tags":[
        "shop"
    ],
    "wof:name":"Faucette's Salon",
    "wof:placetype":"venue"
},
  "geometry": {"coordinates":[-77.603076,35.269897],"type":"Point"}
}