{
  "type": "Feature",
  "properties": {
    "iso:country":"US",
    "sg:address":"340 Watts Landing Rd",
    "sg:city":"Hampstead",
    "sg:classifiers":[
        {
            "category":"Building & Trades",
            "subcategory":"Construction",
            "type":"Services"
        }
    ],
    "sg:phone":"+1 910 329 4663",
    "sg:postcode":"28443",
    "sg:province":"NC",
    "sg:tags":[
        "residential",
        "contractor"
    ],
    "wof:name":"Sanders Builders Inc",
    "wof:placetype":"venue"
},
  "geometry": {"coordinates":[-77.594104,34.444395],"type":"Point"}
}