{
  "type": "Feature",
  "properties": {
    "addr:full":"870 SE Maynard Rd Cary NC 27511",
    "addr:housenumber":"870",
    "addr:postcode":"27511",
    "addr:street":"Se Maynard Rd",
    "iso:country":"US",
    "sg:address":"870 SE Maynard Rd",
    "sg:city":"Cary",
    "sg:classifiers":[
        {
            "category":"Restaurant",
            "type":"Food & Drink"
        }
    ],
    "sg:phone":"+1 919 469 3622",
    "sg:postcode":"27511",
    "sg:province":"NC",
    "wof:name":"Taco Bell",
    "wof:placetype":"venue"
},
  "geometry": {"coordinates":[-78.764126,35.775595],"type":"Point"}
}