{
  "type": "Feature",
  "properties": {
    "addr:full":"1401 S Stratford Rd Winston Salem NC 27103",
    "addr:housenumber":"1401",
    "addr:postcode":"27103",
    "addr:street":"S Stratford Rd",
    "iso:country":"US",
    "sg:address":"1401 S Stratford Rd",
    "sg:city":"Winston Salem",
    "sg:classifiers":[
        {
            "category":"Personal",
            "subcategory":"Beauty Salon",
            "type":"Services"
        }
    ],
    "sg:phone":"+1 336 768 6299",
    "sg:postcode":"27103",
    "sg:province":"NC",
    "wof:name":"Hair Shapers",
    "wof:placetype":"venue"
},
  "geometry": {"coordinates":[-80.30307999999999,36.07505],"type":"Point"}
}