{
  "type": "Feature",
  "properties": {
    "iso:country":"US",
    "sg:address":"1310 S Ridge Ave",
    "sg:city":"Kannapolis",
    "sg:classifiers":[
        {
            "category":"Home & Garden",
            "subcategory":"Mobile Homes",
            "type":"Retail Goods"
        }
    ],
    "sg:phone":"+1 704 938 4151",
    "sg:postcode":"28083",
    "sg:province":"NC",
    "wof:name":"Affordable Custom Living",
    "wof:placetype":"venue"
},
  "geometry": {"coordinates":[-80.623367,35.476258],"type":"Point"}
}