{
  "type": "Feature",
  "properties": {
    "iso:country":"US",
    "sg:address":"624 Lewallen Rd",
    "sg:city":"Asheboro",
    "sg:classifiers":[
        {
            "category":"Retail",
            "subcategory":"Auto Repair",
            "type":"Services"
        }
    ],
    "sg:phone":"+1 336 629 4800",
    "sg:postcode":"27205",
    "sg:province":"NC",
    "sg:tags":[
        "body",
        "automobile",
        "painting",
        "paint"
    ],
    "wof:name":"Superior Body Shop Inc",
    "wof:placetype":"venue"
},
  "geometry": {"coordinates":[-79.833842,35.698951],"type":"Point"}
}