{
  "type": "Feature",
  "properties": {
    "iso:country":"US",
    "sg:address":"3100 Tower Blvd",
    "sg:city":"Durham",
    "sg:classifiers":[
        {
            "category":"Banks & Credit Unions",
            "subcategory":"Investment Brokerage",
            "type":"Services"
        }
    ],
    "sg:phone":"+1 919 419 2500",
    "sg:postcode":"27707",
    "sg:province":"NC",
    "sg:tags":[
        "stock",
        "bond"
    ],
    "sg:website":"www.morgankeegan.com",
    "wof:name":"Morgan Keegan & Co",
    "wof:placetype":"venue"
},
  "geometry": {"coordinates":[-78.957925,35.972798],"type":"Point"}
}