{
  "type": "Feature",
  "properties": {
    "addr:full":"1606 Wellington Ave Wilmington NC 28401",
    "addr:housenumber":"1606",
    "addr:postcode":"28401",
    "addr:street":"Wellington Ave",
    "iso:country":"US",
    "sg:address":"1606 Wellington Ave",
    "sg:city":"Wilmington",
    "sg:classifiers":[
        {
            "category":"Retail",
            "subcategory":"Repair Shop",
            "type":"Services"
        }
    ],
    "sg:phone":"+1 910 799 4327",
    "sg:postcode":"28401",
    "sg:province":"NC",
    "sg:tags":[
        "repairing",
        "aids",
        "hearing"
    ],
    "wof:name":"New Sound Hearing Svc",
    "wof:placetype":"venue"
},
  "geometry": {"coordinates":[-77.923496,34.198527],"type":"Point"}
}