{
  "type": "Feature",
  "properties": {
    "addr:full":"1424 Smokey Park Hwy Candler NC 28715",
    "addr:housenumber":"1424",
    "addr:postcode":"28715",
    "addr:street":"Smokey Park Hwy",
    "iso:country":"US",
    "sg:address":"1424 Smokey Park Hwy",
    "sg:city":"Candler",
    "sg:classifiers":[
        {
            "category":"Retail",
            "subcategory":"Auto Repair",
            "type":"Services"
        }
    ],
    "sg:phone":"+1 828 665 0204",
    "sg:postcode":"28715",
    "sg:province":"NC",
    "sg:tags":[
        "repairing",
        "automobile"
    ],
    "wof:name":"Rice Auto Repair",
    "wof:placetype":"venue"
},
  "geometry": {"coordinates":[-82.678833,35.545075],"type":"Point"}
}