{
  "type": "Feature",
  "properties": {
    "addr:full":"17216 Connor Quay Pt Cornelius NC 28031",
    "addr:housenumber":"17216",
    "addr:postcode":"28031",
    "addr:street":"Connor Quay Pt",
    "iso:country":"US",
    "sg:address":"17216 Connor Quay Pt",
    "sg:city":"Cornelius",
    "sg:classifiers":[
        {
            "category":"Freight",
            "type":"Transportation"
        }
    ],
    "sg:phone":"+1 704 895 6860",
    "sg:postcode":"28031",
    "sg:province":"NC",
    "sg:tags":[
        "dry",
        "bulk",
        "trucking"
    ],
    "wof:name":"Wills Trucking Inc",
    "wof:placetype":"venue"
},
  "geometry": {"coordinates":[-80.926834,35.461972],"type":"Point"}
}