{
  "type": "Feature",
  "properties": {
    "addr:full":"4420 Lake Boone Trl Raleigh NC 27607",
    "addr:housenumber":"4420",
    "addr:postcode":"27607",
    "addr:street":"Lake Boone Trl",
    "iso:country":"US",
    "sg:address":"4420 Lake Boone Trl",
    "sg:city":"Raleigh",
    "sg:classifiers":[
        {
            "category":"Health Services",
            "subcategory":"Doctor",
            "type":"Services"
        }
    ],
    "sg:phone":"+1 919 781 7450",
    "sg:postcode":"27607",
    "sg:province":"NC",
    "sg:tags":[
        "physician",
        "surgeon"
    ],
    "wof:name":"Capital Area Ob & Gyn Assoc",
    "wof:placetype":"venue"
},
  "geometry": {"coordinates":[-78.70366300000001,35.815541],"type":"Point"}
}