{
  "type": "Feature",
  "properties": {
    "addr:full":"4110 Treetops Cir Winterville NC 28590",
    "addr:housenumber":"4110",
    "addr:postcode":"28590",
    "addr:street":"Treetops Cir",
    "iso:country":"US",
    "sg:address":"4110 Treetops Cir",
    "sg:city":"Winterville",
    "sg:classifiers":[
        {
            "category":"Building & Trades",
            "subcategory":"Cleaning & Sanitation",
            "type":"Services"
        }
    ],
    "sg:phone":"+1 252 321 0012",
    "sg:postcode":"28590",
    "sg:province":"NC",
    "sg:tags":[
        "janitor"
    ],
    "wof:name":"Donell Diggs Cleaning Svc",
    "wof:placetype":"venue"
},
  "geometry": {"coordinates":[-77.37676,35.550368],"type":"Point"}
}