{
  "type": "Feature",
  "properties": {
    "addr:full":"4607 Franklin Ave Wilmington NC 28403",
    "addr:housenumber":"4607",
    "addr:postcode":"28403",
    "addr:street":"Franklin Ave",
    "iso:country":"US",
    "sg:address":"4607 Franklin Ave",
    "sg:city":"Wilmington",
    "sg:classifiers":[
        {
            "category":"Professional",
            "subcategory":"Detective & Security Services",
            "type":"Services"
        }
    ],
    "sg:phone":"+1 910 793 0058",
    "sg:postcode":"28403",
    "sg:province":"NC",
    "sg:tags":[
        "guard",
        "patrol"
    ],
    "wof:name":"Professional Security",
    "wof:placetype":"venue"
},
  "geometry": {"coordinates":[-77.886833,34.238751],"type":"Point"}
}