{
  "type": "Feature",
  "properties": {
    "addr:full":"305 W Main St Jonesville NC 28642",
    "addr:housenumber":"305",
    "addr:postcode":"28642",
    "addr:street":"W Main St",
    "iso:country":"US",
    "sg:address":"305 W Main St",
    "sg:city":"Jonesville",
    "sg:classifiers":[
        {
            "category":"Organizations",
            "subcategory":"Religious Organization",
            "type":"Services"
        }
    ],
    "sg:phone":"+1 336 835 4797",
    "sg:postcode":"28642",
    "sg:province":"NC",
    "sg:tags":[
        "church"
    ],
    "wof:name":"Ebenezer Methodist Church",
    "wof:placetype":"venue"
},
  "geometry": {"coordinates":[-80.84592000000001,36.235545],"type":"Point"}
}