{
  "type": "Feature",
  "properties": {
    "iso:country":"US",
    "sg:address":"2040 Elvira St",
    "sg:city":"Fayetteville",
    "sg:classifiers":[
        {
            "category":"Real Estate",
            "subcategory":"Real Estate Operator",
            "type":"Services"
        }
    ],
    "sg:phone":"+1 910 323 9094",
    "sg:postcode":"28303",
    "sg:province":"NC",
    "sg:tags":[
        "building",
        "apartment"
    ],
    "wof:name":"Haymount Manor Apartments",
    "wof:placetype":"venue"
},
  "geometry": {"coordinates":[-78.913545,35.068139],"type":"Point"}
}