{
  "type": "Feature",
  "properties": {
    "iso:country":"US",
    "sg:address":"2004 Hunters Pt",
    "sg:city":"Clayton",
    "sg:classifiers":[
        {
            "category":"Building & Trades",
            "subcategory":"Construction",
            "type":"Services"
        }
    ],
    "sg:phone":"+1 919 553 3781",
    "sg:postcode":"27520",
    "sg:province":"NC",
    "sg:tags":[
        "house"
    ],
    "wof:name":"Mac Edwards General Const",
    "wof:placetype":"venue"
},
  "geometry": {"coordinates":[-78.49374299999999,35.654659],"type":"Point"}
}