{
  "type": "Feature",
  "properties": {
    "addr:full":"5371 Cokesbury Rd Fuquay Varina NC 27526",
    "addr:housenumber":"5371",
    "addr:postcode":"27526",
    "addr:street":"Cokesbury Rd",
    "iso:country":"US",
    "sg:address":"5371 Cokesbury Rd",
    "sg:city":"Fuquay Varina",
    "sg:classifiers":[
        {
            "category":"Building & Trades",
            "subcategory":"Plumbing",
            "type":"Services"
        }
    ],
    "sg:phone":"+1 919 552 7956",
    "sg:postcode":"27526",
    "sg:province":"NC",
    "sg:tags":[
        "conditioning",
        "air",
        "system",
        "contractor"
    ],
    "wof:name":"Griffin Heating & Air",
    "wof:placetype":"venue"
},
  "geometry": {"coordinates":[-78.882122,35.549491],"type":"Point"}
}