{
  "type": "Feature",
  "properties": {
    "iso:country":"US",
    "sg:address":"2319 Yanceyville St",
    "sg:city":"Greensboro",
    "sg:classifiers":[
        {
            "category":"Organizations",
            "subcategory":"Religious Organization",
            "type":"Services"
        }
    ],
    "sg:phone":"+1   ",
    "sg:postcode":"27405",
    "sg:province":"NC",
    "wof:name":"Fairview Baptist Church",
    "wof:placetype":"venue"
},
  "geometry": {"coordinates":[-79.775053,36.10445],"type":"Point"}
}