{
  "type": "Feature",
  "properties": {
    "addr:full":"309 Chapanoke Rd Raleigh NC 27603",
    "addr:housenumber":"309",
    "addr:postcode":"27603",
    "addr:street":"Chapanoke Rd",
    "iso:country":"US",
    "sg:address":"309 Chapanoke Rd",
    "sg:city":"Raleigh",
    "sg:classifiers":[
        {
            "category":"Government",
            "subcategory":"Office",
            "type":"Public Place"
        }
    ],
    "sg:phone":"+1 919 773 2844",
    "sg:postcode":"27603",
    "sg:province":"NC",
    "sg:tags":[
        "state",
        "security"
    ],
    "wof:name":"Civil Air Patrol",
    "wof:placetype":"venue"
},
  "geometry": {"coordinates":[-78.649373,35.735571],"type":"Point"}
}