{
  "type": "Feature",
  "properties": {
    "addr:full":"1 Dixie Trl Raleigh NC 27607",
    "addr:housenumber":"1",
    "addr:postcode":"27607",
    "addr:street":"Dixie Trl",
    "iso:country":"US",
    "sg:address":"1 Dixie Trl",
    "sg:city":"Raleigh",
    "sg:classifiers":[
        {
            "category":"Restaurant",
            "type":"Food & Drink"
        }
    ],
    "sg:phone":"+1 919 821 9985",
    "sg:postcode":"27607",
    "sg:province":"NC",
    "sg:tags":[
        "eating"
    ],
    "sg:website":"www.eastvillagegrill.com",
    "wof:name":"East Village Grill and Bar",
    "wof:placetype":"venue"
},
  "geometry": {"coordinates":[-78.67574999999999,35.792138],"type":"Point"}
}