{
  "type": "Feature",
  "properties": {
    "iso:country":"US",
    "sg:address":"2808 E Market St",
    "sg:city":"Greensboro",
    "sg:classifiers":[
        {
            "category":"Retail",
            "subcategory":"Auto Repair",
            "type":"Services"
        }
    ],
    "sg:phone":"+1 336 274 6000",
    "sg:postcode":"27405",
    "sg:province":"NC",
    "sg:tags":[
        "muffler",
        "exhaust",
        "system"
    ],
    "wof:name":"Muffler World",
    "wof:placetype":"venue"
},
  "geometry": {"coordinates":[-79.74656899999999,36.08159],"type":"Point"}
}