{
  "type": "Feature",
  "properties": {
    "iso:country":"US",
    "sg:address":"98 Brookside Dr",
    "sg:city":"Canton",
    "sg:classifiers":[
        {
            "category":"Building & Trades",
            "subcategory":"Construction",
            "type":"Services"
        }
    ],
    "sg:phone":"+1 828 648 5789",
    "sg:postcode":"28716",
    "sg:province":"NC",
    "sg:tags":[
        "floor",
        "laying",
        "contractor"
    ],
    "wof:name":"County Carpenter",
    "wof:placetype":"venue"
},
  "geometry": {"coordinates":[-82.850792,35.514833],"type":"Point"}
}