{
  "type": "Feature",
  "properties": {
    "addr:full":"5900 Bearoak Ln Charlotte NC 28269",
    "addr:housenumber":"5900",
    "addr:postcode":"28269",
    "addr:street":"Bearoak Ln",
    "iso:country":"US",
    "sg:address":"5900 Bearoak Ln",
    "sg:city":"Charlotte",
    "sg:classifiers":[
        {
            "category":"Professional",
            "subcategory":"Business Services",
            "type":"Services"
        }
    ],
    "sg:phone":"+1   ",
    "sg:postcode":"28269",
    "sg:province":"NC",
    "wof:name":"Denmart Enterprises Inc",
    "wof:placetype":"venue"
},
  "geometry": {"coordinates":[-80.75524799999999,35.37442],"type":"Point"}
}